Workbook
Name \0: #REF!
Name \a: #REF!
Name \e: #REF!
Name \F: #REF!
Name \I: #REF!
Name \P: #REF!
Name \q: #REF!
Name \x: #REF!
Name \z: #REF!
Name __RE1: #REF!
Name _1001: #REF!
Name _1Excel_BuiltIn__FilterDatabase_1: #REF!
Name _28655: #REF!
Name _28698: #REF!
Name _28699: #REF!
Name _28724: #REF!
Name _28727: #REF!
Name _28734: #REF!
Name _28738: #REF!
Name _28745: #REF!
Name _28748: #REF!
Name _30662_2011TTL: #REF!
Name _30687: #REF!
Name _30688: #REF!
Name _30689: #REF!
Name _30690: #REF!
Name _31143: #REF!
Name _31771: #REF!
Name _32781: #REF!
Name _AU19452: #REF!
Name _AU24412: #REF!
Name _AU25231: #REF!
Name _AU25799: #REF!
Name _AU26137: #REF!
Name _AU26725: #REF!
Name _AU27858: #REF!
Name _AU28837: #REF!
Name _AU29288: #REF!
Name _AU295224: #REF!
Name _AU295249: #REF!
Name _AU298980: #REF!
Name _AU299820: #REF!
Name _AU299933: #REF!
Name _AU300040: #REF!
Name _AU300384: #REF!
Name _au300879: #REF!
Name _AU301555: #REF!
Name _AU301558: #REF!
Name _AU301565: #REF!
Name _AU302053: #REF!
Name _AU302054: #REF!
Name _AU302055: #REF!
Name _AU302281: #REF!
Name _AU303526: #REF!
Name _AU303617: #REF!
Name _AU305018: #REF!
Name _AU305578: #REF!
Name _AU32838: #REF!
Name _AU33316: #REF!
Name _AU33877: #REF!

Sheet Template
M1: V6
A2: Stibo Attribute | B2: Stibo Attribute ID | C2: Stibo Validation | D2: Cluster | E2: Grouping | F2: Attributes Description | G2: Field Mapping Type | H2: Brand File Name & Link | I2: Brand File Sheet Name | J2: Field Name in the Brand File | K2: Mapping Logic | L2: Mapping file for additional Brand specific mapping | M2: mapping logic | N2: Inline/Licensed | O2: Footwear | P2: Apparel | Q2: Accessories | R2: Sport Equipment
A3: Country | B3: =VLOOKUP(A3,MDD!A:B,2,0) -> AT_Country | C3: =VLOOKUP(A3,MDD!A:C,3,0) -> LOV | D3: Basic | F3: Co Dependent with Description E.g : ID - Indonesia PH - Philiphine TH - Thailand SG - Singapore MY - Malaysia VN - Vietnam KH : Cambodia
A4: Company | B4: =VLOOKUP(A4,MDD!A:B,2,0) -> AT_CompanyCode | C4: =VLOOKUP(A4,MDD!A:C,3,0) -> LOV | D4: Basic | F4: Co Dependent with Description 0888 - PT. Map Aktif Adiperkasa 0886 - PT. MAP FTL Adiperkasa 0882 - Magna Management Asia etc (Refer to LOV)
A5: SBU | B5: =VLOOKUP(A5,MDD!A:B,2,0) -> AT_SBU | C5: =VLOOKUP(A5,MDD!A:C,3,0) -> LOV | D5: Basic | F5: Co Dependent with Description E.g SP - Sports FQ - Footlocker Etc (refer to LOV)
A6: Brand | B6: =VLOOKUP(A6,MDD!A:B,2,0) -> AT_Brand | C6: =VLOOKUP(A6,MDD!A:C,3,0) -> LOV | D6: Basic | F6: Co Dependent with Description E.g ADI - Adidas NIK - Nike NEW - New Balance Etc (refer to LOV)
A7: Brand Group | B7: =VLOOKUP(A7,MDD!A:B,2,0) -> AT_BrandGroup | C7: =VLOOKUP(A7,MDD!A:C,3,0) -> LOV | D7: Basic | F7: Multiple brand codes that managed under 1 brand group e.g. Adidas, Lego, Hasbro
A8: Brand Type | B8: =VLOOKUP(A8,MDD!A:B,2,0) -> AT_BrandType | C8: =VLOOKUP(A8,MDD!A:C,3,0) -> LOV | D8: Commercial | F8: Whether a brand act as a retailer, selling directly to customers (MAA brands, SDI brands) or as a distributor (Non-MAA brands, Non-SDI brands)
A9: Brand Category | B9: =VLOOKUP(A9,MDD!A:B,2,0) -> AT_BrandCategory | C9: =VLOOKUP(A9,MDD!A:C,3,0) -> LOV | D9: Commercial | F9: Group of brands that classified based on their performance/ contribution e.g. Top brands, Selected brands, Non-Top brands
A10: Brand Status | B10: =VLOOKUP(A10,MDD!A:B,2,0) -> AT_BrandStatus | C10: =VLOOKUP(A10,MDD!A:C,3,0) -> LOV | D10: Commercial | F10: Indicating whether the brands is actively being sold or, no longer continued or exit the market (Active/Discontinue)
A11: BY Indicator | B11: =VLOOKUP(A11,MDD!A:B,2,0) -> AT_BYIndicator | C11: =VLOOKUP(A11,MDD!A:C,3,0) -> LOV | D11: System indicator | F11: Article to be ordered
A12: SAP Indicator | B12: =VLOOKUP(A12,MDD!A:B,2,0) -> AT_SAPIndicator | C12: =VLOOKUP(A12,MDD!A:C,3,0) -> LOV | D12: System indicator | F12: Article has been created
A13: Ecom Indicator | B13: =VLOOKUP(A13,MDD!A:B,2,0) -> AT_EcomIndicator | C13: =VLOOKUP(A13,MDD!A:C,3,0) -> LOV | D13: System indicator | F13: Article to be Publish at Online Sales Channel
A14: Principal Style Code | B14: =VLOOKUP(A14,MDD!A:B,2,0) -> AT_PrincipalStyleCode | C14: =VLOOKUP(A14,MDD!A:C,3,0) -> text | D14: Basic | F14: Original Principal Code
A15: Principal Style Description | B15: =VLOOKUP(A15,MDD!A:B,2,0) -> AT_PrincipalStyleDescription | C15: =VLOOKUP(A15,MDD!A:C,3,0) -> text | D15: Basic | E15: Description | F15: Original Principal Product Name
A16: Principal Color Code | B16: =VLOOKUP(A16,MDD!A:B,2,0) -> AT_PrincipalColorCode | C16: =VLOOKUP(A16,MDD!A:C,3,0) -> text | D16: Basic | E16: Color | F16: Original Principal Color
A17: Principal Color Description | B17: =VLOOKUP(A17,MDD!A:B,2,0) -> AT_PrincipalColorName | C17: =VLOOKUP(A17,MDD!A:C,3,0) -> text | D17: Basic | E17: Color | F17: Original Principal Color Description
A18: Principal Gender Code | B18: =VLOOKUP(A18,MDD!A:B,2,0) -> AT_PrincipalGenderCode | C18: =VLOOKUP(A18,MDD!A:C,3,0) -> text | D18: Basic | E18: Gender | F18: Original Principal Gender
A19: Principal Gender Description | B19: =VLOOKUP(A19,MDD!A:B,2,0) -> AT_PrincipalGenderDescription | C19: =VLOOKUP(A19,MDD!A:C,3,0) -> text | D19: Basic | E19: Gender | F19: Original Principal Gender Description
A20: Principal Age Code | B20: =VLOOKUP(A20,MDD!A:B,2,0) -> AT_PrincipalAgeCode | C20: =VLOOKUP(A20,MDD!A:C,3,0) -> text | D20: Basic | E20: Age | F20: Original Principal Age
A21: Principal Age Description | B21: =VLOOKUP(A21,MDD!A:B,2,0) -> AT_PrincipalAgeDescription | C21: =VLOOKUP(A21,MDD!A:C,3,0) -> text | D21: Basic | E21: Age | F21: Original Principal Age Description
A22: Principal Size | B22: =VLOOKUP(A22,MDD!A:B,2,0) -> AT_PrincipalSize | C22: =VLOOKUP(A22,MDD!A:C,3,0) -> text | D22: Basic | E22: Sizing | F22: Original Size from Principal (co-dependent with description)
A23: SAP Style Code | B23: =VLOOKUP(A23,MDD!A:B,2,0) -> AT_SAPStyleCode | C23: =VLOOKUP(A23,MDD!A:C,3,0) -> text | D23: Basic | F23: Adjusted principal style code that has been map to SAP generic (without brand code)
A24: Generic | B24: =VLOOKUP(A24,MDD!A:B,2,0) -> AT_Generic | C24: =VLOOKUP(A24,MDD!A:C,3,0) -> text | D24: Basic | F24: MAA Generic Code (Max 12 Digits - 3 Digits brand code + 9 Digits Principal Style)
A25: Generic Description | B25: =VLOOKUP(A25,MDD!A:B,2,0) -> AT_GenericDescription | C25: =VLOOKUP(A25,MDD!A:C,3,0) -> regexp | D25: Basic | E25: Description | F25: MAA Generic Description Mapping (Max 40 Digits - 3 Digits brand code + Principal style + (Age/Gender) + Color
A26: Variant | B26: =VLOOKUP(A26,MDD!A:B,2,0) -> AT_Variant | C26: =VLOOKUP(A26,MDD!A:C,3,0) -> text | D26: Basic | F26: MAA Article Code (Max 18 Digits - Generic code + 3 Digits MAA / SAP Color (103 color guidance) + 3 Digits MAA size code mapping
A27: Variant Description | B27: =VLOOKUP(A27,MDD!A:B,2,0) -> AT_VariantDescription | C27: =VLOOKUP(A27,MDD!A:C,3,0) -> text | D27: Basic | E27: Description | F27: MAA Generic Description Mapping (Max 40 Digits - 3 Digits brand code + Principal style + (Age/Gender) + Color + Size
A28: SAP Color | B28: =VLOOKUP(A28,MDD!A:B,2,0) -> AT_Color | C28: =VLOOKUP(A28,MDD!A:C,3,0) -> LOV | D28: Basic | E28: Color | F28: MAA 103 Basic SAP Color Code & Description
A29: SAP Size | B29: =VLOOKUP(A29,MDD!A:B,2,0) -> AT_Size | C29: =VLOOKUP(A29,MDD!A:C,3,0) -> LOV | D29: Basic | E29: Sizing | F29: MAA SAP Size Code & Description
A30: Created on | B30: =VLOOKUP(A30,MDD!A:B,2,0) -> AT_Createdon | C30: =VLOOKUP(A30,MDD!A:C,3,0) -> legacyisodatetime | D30: Basic | F30: When is the creation date
A31: Created by | B31: =VLOOKUP(A31,MDD!A:B,2,0) -> AT_Createdby | C31: =VLOOKUP(A31,MDD!A:C,3,0) -> text | D31: Basic | F31: Who is creating the articles
A32: Musical Box Article Code | B32: =VLOOKUP(A32,MDD!A:B,2,0) -> AT_MusicalBoxArticleCode | C32: =VLOOKUP(A32,MDD!A:C,3,0) -> text | D32: Basic | F32: MAA Musical Box Code (Max 18 Digits - 3 Digits brand code + 3 digits of MB- +9 digits of SAP Style Code + 3 Digits Assortment Code)
A33: MB Style code | B33: =VLOOKUP(A33,MDD!A:B,2,0) -> AT_MBStyleCode | C33: =VLOOKUP(A33,MDD!A:C,3,0) -> text | D33: Basic | F33: Max 12 digits MB Style (MB- + SAP Style Code )
A34: MB Assortment Code | B34: =VLOOKUP(A34,MDD!A:B,2,0) -> AT_MBAssortmentCode | C34: =VLOOKUP(A34,MDD!A:C,3,0) -> LOV | D34: Basic | F34: 3 Digits Assortment code (based on matrix of qty per sizes)
A35: Musical Box Article Description | B35: =VLOOKUP(A35,MDD!A:B,2,0) -> AT_MusicalBoxArticleDescription | C35: =VLOOKUP(A35,MDD!A:C,3,0) -> text | D35: Basic | E35: Description | F35: MAA Musical Box Description Mapping (Max 40 Digits - 3 Digits brand code + Principal style + (Age/Gender) + Color + (-MB)
A36: Musical Box Components Qty | B36: =VLOOKUP(A36,MDD!A:B,2,0) -> AT_MusicalBoxComponentsQty | C36: =VLOOKUP(A36,MDD!A:C,3,0) -> LOV | D36: Basic | F36: Components qty of Musical Box Articles : Breakdown qty per sizes
A37: Musical Box UOM | B37: =VLOOKUP(A37,MDD!A:B,2,0) -> AT_MusicalBoxUOM | C37: =VLOOKUP(A37,MDD!A:C,3,0) -> LOV | D37: Basic | F37: UOM for Musical Box (Default : CAR)
A38: SAP Age | B38: =VLOOKUP(A38,MDD!A:B,2,0) -> AT_SAPAge | C38: =VLOOKUP(A38,MDD!A:C,3,0) -> LOV | D38: Basic | E38: Age | F38: MAA SAP Age (Co - Dependent with Description) E.g : CH - Children AA - All Ages AD - Adults
A39: SAP Gender | B39: =VLOOKUP(A39,MDD!A:B,2,0) -> AT_Gender | C39: =VLOOKUP(A39,MDD!A:C,3,0) -> LOV | D39: Basic | E39: Gender | F39: MAA SAP Gender (co dependent with description) E.g : M - Male F - Female U - Unisex
A40: Season | B40: =VLOOKUP(A40,MDD!A:B,2,0) -> AT_Season | C40: =VLOOKUP(A40,MDD!A:C,3,0) -> LOV | D40: Basic | F40: MAA SAP Season (Co Dependent with Description) E.g : SP - Spring SM - Summer FW - Fall Winter SS - Spring Summer etc (refer to LOV)
A41: Season Year | B41: =VLOOKUP(A41,MDD!A:B,2,0) -> AT_SeasonYear | C41: =VLOOKUP(A41,MDD!A:C,3,0) -> number | D41: Basic | F41: MAA SAP Year
A42: Country of Origin | B42: =VLOOKUP(A42,MDD!A:B,2,0) -> AT_CountryOrigin | C42: =VLOOKUP(A42,MDD!A:C,3,0) -> LOV | D42: Basic | F42: Co Dependent with Description E.g CN - China VN - Vietnam SG - Singapore etc (refer to LOV)
A43: Vendor | B43: =VLOOKUP(A43,MDD!A:B,2,0) -> AT_Vendor | C43: =VLOOKUP(A43,MDD!A:C,3,0) -> LOV | D43: Basic | F43: MAA Vendor code (Co Dependent with description) Format : Country Code - Comp Code - Vendor Code - Vendor Name MY - 0198 - 10303 - CROCS FOOTWEAR (MALAYSIA) SDN BHD ID - 0888 - 6863 - SKECHERS SARL etc (refer to LOV)
A44: Main Vendor Identification | B44: =VLOOKUP(A44,MDD!A:B,2,0) -> AT_MainVendorIdentification | C44: =VLOOKUP(A44,MDD!A:C,3,0) -> text | D44: Basic | F44: to identify priority vendor
A45: Exchange Rate | B45: =VLOOKUP(A45,MDD!A:B,2,0) -> AT_ExchangeRate | C45: =VLOOKUP(A45,MDD!A:C,3,0) -> number | D45: Price | F45: Exchange Rate to Local Currency
A46: Pricing Distribution Channel | B46: =VLOOKUP(A46,MDD!A:B,2,0) -> AT_PricingDistributionChannel | C46: =VLOOKUP(A46,MDD!A:C,3,0) -> LOV | D46: Price | F46: To identify price channel Co Dependent with Description) E.g : 01 - Retailer 02 - Wholesale 03 - E-comm
A47: Retail Price Currency | B47: =VLOOKUP(A47,MDD!A:B,2,0) -> AT_RetailPriceCurrency | C47: =VLOOKUP(A47,MDD!A:C,3,0) -> LOV | D47: Price
A48: Original Price | B48: =VLOOKUP(A48,MDD!A:B,2,0) -> AT_OriginalPrice | C48: =VLOOKUP(A48,MDD!A:C,3,0) -> regexp | D48: Price | F48: MAA Original Price
A49: Valid From | B49: =VLOOKUP(A49,MDD!A:B,2,0) -> #N/A | C49: =VLOOKUP(A49,MDD!A:C,3,0) -> #N/A | D49: Price | F49: Identify pricing valid period
A50: Valid To | B50: =VLOOKUP(A50,MDD!A:B,2,0) -> #N/A | C50: =VLOOKUP(A50,MDD!A:C,3,0) -> #N/A | D50: Price | F50: Identify pricing valid period Conditional (default as priority 31.12.9999 - editable)
A51: Created on | B51: =VLOOKUP(A51,MDD!A:B,2,0) -> AT_Createdon | C51: =VLOOKUP(A51,MDD!A:C,3,0) -> legacyisodatetime | D51: Basic | F51: Identify when the pricing is registered (Maintainance date)
A52: Created by | B52: =VLOOKUP(A52,MDD!A:B,2,0) -> AT_Createdby | C52: =VLOOKUP(A52,MDD!A:C,3,0) -> text | D52: Basic | F52: Identify who is registering the pricing (User)
A53: Current price | B53: =VLOOKUP(A53,MDD!A:B,2,0) -> AT_CurrentPrice | C53: =VLOOKUP(A53,MDD!A:C,3,0) -> regexp | D53: Price | F53: MAA Current Price
A54: Valid From | B54: =VLOOKUP(A54,MDD!A:B,2,0) -> #N/A | C54: =VLOOKUP(A54,MDD!A:C,3,0) -> #N/A | D54: Price | F54: Identify pricing valid period
A55: Valid To | B55: =VLOOKUP(A55,MDD!A:B,2,0) -> #N/A | C55: =VLOOKUP(A55,MDD!A:C,3,0) -> #N/A | D55: Price | F55: Identify pricing valid period Conditional (default as priority 31.12.9999 - editable)
A56: Created on | B56: =VLOOKUP(A56,MDD!A:B,2,0) -> AT_Createdon | C56: =VLOOKUP(A56,MDD!A:C,3,0) -> legacyisodatetime | D56: Basic | F56: Identify when the pricing is registered (Maintainance date)
A57: Created by | B57: =VLOOKUP(A57,MDD!A:B,2,0) -> AT_Createdby | C57: =VLOOKUP(A57,MDD!A:C,3,0) -> text | D57: Basic | F57: Identify who is registering the pricing (User)
A58: Discount Bucket | B58: =VLOOKUP(A58,MDD!A:B,2,0) -> AT_DiscountBucket | C58: =VLOOKUP(A58,MDD!A:C,3,0) -> number | D58: Price | F58: Comparison between original vs current price (non-rounded)
A59: Discount Bucket (Rounded) | B59: =VLOOKUP(A59,MDD!A:B,2,0) -> AT_DiscountBucketRounded | C59: =VLOOKUP(A59,MDD!A:C,3,0) -> number | D59: Price | F59: Comparison between original vs current price (rounded)
A60: Estimated Landed Cost | B60: =VLOOKUP(A60,MDD!A:B,2,0) -> AT_EstimatedLandedCost | C60: =VLOOKUP(A60,MDD!A:C,3,0) -> number | D60: Cost
A61: FOB | B61: =VLOOKUP(A61,MDD!A:B,2,0) -> AT_FOB | C61: =VLOOKUP(A61,MDD!A:C,3,0) -> regexp | D61: Cost
A62: FOB Currency | B62: =VLOOKUP(A62,MDD!A:B,2,0) -> AT_FOBCurrency | C62: =VLOOKUP(A62,MDD!A:C,3,0) -> LOV | D62: Cost
A63: Freight Cost | B63: =VLOOKUP(A63,MDD!A:B,2,0) -> AT_FreightCost | C63: =VLOOKUP(A63,MDD!A:C,3,0) -> regexp | D63: Cost
A64: Royalty | B64: =VLOOKUP(A64,MDD!A:B,2,0) -> AT_Royalty | C64: =VLOOKUP(A64,MDD!A:C,3,0) -> regexp | D64: Cost
A65: Royalty Deduction | B65: =VLOOKUP(A65,MDD!A:B,2,0) -> AT_RoyaltyDeduction | C65: =VLOOKUP(A65,MDD!A:C,3,0) -> regexp | D65: Cost
A66: Commision | B66: =VLOOKUP(A66,MDD!A:B,2,0) -> #N/A | C66: =VLOOKUP(A66,MDD!A:C,3,0) -> #N/A | D66: Cost
A67: SGS | B67: =VLOOKUP(A67,MDD!A:B,2,0) -> AT_SGS | C67: =VLOOKUP(A67,MDD!A:C,3,0) -> regexp | D67: Cost
A68: Marketing Fee | B68: =VLOOKUP(A68,MDD!A:B,2,0) -> AT_MarketingFee | C68: =VLOOKUP(A68,MDD!A:C,3,0) -> regexp | D68: Cost
A69: Haddad Office Charge | B69: =VLOOKUP(A69,MDD!A:B,2,0) -> AT_HaddadOfficeCharge | C69: =VLOOKUP(A69,MDD!A:C,3,0) -> regexp | D69: Cost
A70: Haddad Office Charge - Deduction | B70: =VLOOKUP(A70,MDD!A:B,2,0) -> AT_HaddadOfficeChargeDeduction | C70: =VLOOKUP(A70,MDD!A:C,3,0) -> regexp | D70: Cost
A71: Safeguard Duty (ID Only) | B71: =VLOOKUP(A71,MDD!A:B,2,0) -> AT_SafeguardDutyIdOnly | C71: =VLOOKUP(A71,MDD!A:C,3,0) -> number | D71: Cost
... A73: Others | B73: =VLOOKUP(A73,MDD!A:B,2,0) -> AT_Others | C73: =VLOOKUP(A73,MDD!A:C,3,0) -> number | D73: Cost
A74: MC Structure (Merchandise Category) | B74: =VLOOKUP(A74,MDD!A:B,2,0) -> #N/A | C74: =VLOOKUP(A74,MDD!A:C,3,0) -> #N/A | D74: MC | F74: Structure : 1 Digits of SAP Product Div + 2 Digits of SAP Product Group + 2 Digits of SAP Product Category + 3 Digits of Brand Code + 1 Digits of SAP Product Flag
A75: SAP Product Division | B75: =VLOOKUP(A75,MDD!A:B,2,0) -> #N/A | C75: =VLOOKUP(A75,MDD!A:C,3,0) -> #N/A | D75: MC | F75: Co Dependent with Description E.g : F - Footwear | A - Apparel etc
A76: SAP Product Group | B76: =VLOOKUP(A76,MDD!A:B,2,0) -> #N/A | C76: =VLOOKUP(A76,MDD!A:C,3,0) -> #N/A | D76: MC | F76: Co Dependent with Description) E.g : FS - Lifestyle Shoes | 34 - Sports Shoes etc
A77: SAP Product Category | B77: =VLOOKUP(A77,MDD!A:B,2,0) -> #N/A | C77: =VLOOKUP(A77,MDD!A:C,3,0) -> #N/A | D77: MC | F77: Co Dependent with Description E.g : RU - Running | CS - Casual Shoes etc
A78: SAP Product Flag | B78: =VLOOKUP(A78,MDD!A:B,2,0) -> AT_SAPProductFlag | C78: =VLOOKUP(A78,MDD!A:C,3,0) -> LOV | D78: MC | F78: Co Dependent with Description E.g : A - Intercompany 5 - Direct Local 1 - Consignment etc To indicate the bussiness model (Direct, local, intercompany,consignment, non MD) E.g : A - Intercompany | 5 - Direct Local | 1 - Consignment
A79: Principal Merchandise Hierarchy L1 | B79: =VLOOKUP(A79,MDD!A:B,2,0) -> AT_PrincipalMerchandiseHierarchyL1 | C79: =VLOOKUP(A79,MDD!A:C,3,0) -> text | D79: Hierarchy | F79: Principal Merchandise Hierarchy Level 1
A80: Principal Merchandise Hierarchy L2 | B80: =VLOOKUP(A80,MDD!A:B,2,0) -> AT_PrincipalMerchandiseHierarchyL2 | C80: =VLOOKUP(A80,MDD!A:C,3,0) -> text | D80: Hierarchy | F80: Principal Merchandise Hierarchy Level 2
A81: Principal Merchandise Hierarchy L3 | B81: =VLOOKUP(A81,MDD!A:B,2,0) -> AT_PrincipalMerchandiseHierarchyL3 | C81: =VLOOKUP(A81,MDD!A:C,3,0) -> text | D81: Hierarchy | F81: Principal Merchandise Hierarchy Level 3
A82: Principal Merchandise Hierarchy L4 | B82: =VLOOKUP(A82,MDD!A:B,2,0) -> AT_PrincipalMerchandiseHierarchyL4 | C82: =VLOOKUP(A82,MDD!A:C,3,0) -> text | D82: Hierarchy | F82: Principal Merchandise Hierarchy Level 4
A83: Principal Merchandise Hierarchy L5 | B83: =VLOOKUP(A83,MDD!A:B,2,0) -> AT_PrincipalMerchandiseHierarchyL5 | C83: =VLOOKUP(A83,MDD!A:C,3,0) -> text | D83: Hierarchy | F83: Principal Merchandise Hierarchy Level 5
A84: Material Type | B84: =VLOOKUP(A84,MDD!A:B,2,0) -> AT_MaterialType | C84: =VLOOKUP(A84,MDD!A:C,3,0) -> LOV | D84: Commercial | F84: Direct/ Intercompany/ etc
A85: Article Category | B85: =VLOOKUP(A85,MDD!A:B,2,0) -> AT_SAPArticleCategory | C85: =VLOOKUP(A85,MDD!A:C,3,0) -> LOV | D85: Basic | F85: SAP Article Category to indicate whether the article is single,Generic,etc
A86: Internal Barcode | B86: =VLOOKUP(A86,MDD!A:B,2,0) -> AT_InternalBarcode | C86: =VLOOKUP(A86,MDD!A:C,3,0) -> regexp | D86: Basic | E86: Barcode
A87: Principal Barcode | B87: =VLOOKUP(A87,MDD!A:B,2,0) -> AT_PrincipalBarcode | C87: =VLOOKUP(A87,MDD!A:C,3,0) -> regexp | D87: Basic | E87: Barcode | F87: Original Principal Barcode
A88: FG Barcode | B88: =VLOOKUP(A88,MDD!A:B,2,0) -> AT_FGBarcode | C88: =VLOOKUP(A88,MDD!A:C,3,0) -> regexp | D88: Basic | E88: Barcode | F88: FG Barcode (Only for Sport Direct)
A89: Main EAN Indicator | B89: =VLOOKUP(A89,MDD!A:B,2,0) -> AT_MainEANIndicator | C89: =VLOOKUP(A89,MDD!A:C,3,0) -> LOV | D89: Basic | E89: Barcode
A90: EAN Category | B90: =VLOOKUP(A90,MDD!A:B,2,0) -> AT_EANCategory | C90: =VLOOKUP(A90,MDD!A:C,3,0) -> LOV | D90: Basic | E90: Barcode
A91: Unit of Measurement (UoM) | B91: =VLOOKUP(A91,MDD!A:B,2,0) -> AT_UOM | C91: =VLOOKUP(A91,MDD!A:C,3,0) -> LOV | D91: Basic
A92: HS Code | B92: =VLOOKUP(A92,MDD!A:B,2,0) -> AT_HSCode | C92: =VLOOKUP(A92,MDD!A:C,3,0) -> text | D92: Cost
A93: Nature of Article (NOA) | B93: =VLOOKUP(A93,MDD!A:B,2,0) -> #N/A | C93: =VLOOKUP(A93,MDD!A:C,3,0) -> #N/A | D93: Commercial
A94: Article Type | B94: =VLOOKUP(A94,MDD!A:B,2,0) -> #N/A | C94: =VLOOKUP(A94,MDD!A:C,3,0) -> #N/A | D94: Commercial | F94: Inline/License/SSE
A95: Thumbnail Image | B95: =VLOOKUP(A95,MDD!A:B,2,0) -> #N/A | C95: =VLOOKUP(A95,MDD!A:C,3,0) -> #N/A | D95: Image (BY) | E95: Images
A96: BY Age | B96: =VLOOKUP(A96,MDD!A:B,2,0) -> AT_BYAge | C96: =VLOOKUP(A96,MDD!A:C,3,0) -> LOV | D96: Basic
A97: BY Gender | B97: =VLOOKUP(A97,MDD!A:B,2,0) -> AT_BYGender | C97: =VLOOKUP(A97,MDD!A:C,3,0) -> LOV | D97: Basic | E97: Gender
A98: BCI | B98: =VLOOKUP(A98,MDD!A:B,2,0) -> AT_BCI | C98: =VLOOKUP(A98,MDD!A:C,3,0) -> LOV | D98: Image (BY)
A99: BY Color Group | B99: =VLOOKUP(A99,MDD!A:B,2,0) -> #N/A | C99: =VLOOKUP(A99,MDD!A:C,3,0) -> #N/A | D99: Basic | E99: Color | F99: 6 Color Group
A100: BY Standardized Color | B100: =VLOOKUP(A100,MDD!A:B,2,0) -> #N/A | C100: =VLOOKUP(A100,MDD!A:C,3,0) -> #N/A | D100: Basic | E100: Color | F100: 53 Color Description
A101: Price Range | B101: =VLOOKUP(A101,MDD!A:B,2,0) -> AT_PriceRange | C101: =VLOOKUP(A101,MDD!A:C,3,0) -> LOV | D101: Basic
...

Sheet Adidas-API
G1: Linelist V6 | J1: API | M1: V6
A2: Stibo Attribute | B2: Stibo Attribute ID | C2: Stibo Validation | D2: Cluster | E2: Grouping | F2: Attributes Description | G2: Field Mapping Type | H2: Brand File Name & Link | I2: Brand File Sheet Name | J2: Field Name in the Brand File | K2: Mapping Logic | L2: Mapping file for additional Brand specific mapping | M2: mapping logic | N2: Inline | O2: Footwear | P2: Apparel | Q2: Accessories | R2: Equipment
A3: Country | B3: =VLOOKUP(A3,MDD!A:B,2,0) -> AT_Country | C3: =VLOOKUP(A3,MDD!A:C,3,0) -> LOV | D3: Basic | F3: Co Dependent with Description E.g : ID - Indonesia PH - Philiphine TH - Thailand SG - Singapore MY - Malaysia VN - Vietnam KH : Cambodia | G3: Manual Input in Portal | J3: TBC | M3: Refer to LOV | O3: D | P3: D | Q3: D | R3: D | V3: API SOURCES - is it only DTB?
A4: Company | B4: =VLOOKUP(A4,MDD!A:B,2,0) -> AT_CompanyCode | C4: =VLOOKUP(A4,MDD!A:C,3,0) -> LOV | D4: Basic | F4: Co Dependent with Description 0888 - PT. Map Aktif Adiperkasa 0886 - PT. MAP FTL Adiperkasa 0882 - Magna Management Asia etc (Refer to LOV) | G4: Manual Input in Portal | J4: #N/A | M4: Refer to LOV | O4: D | P4: D | Q4: D | R4: D | V4: Fields/Columns
A5: SBU | B5: =VLOOKUP(A5,MDD!A:B,2,0) -> AT_SBU | C5: =VLOOKUP(A5,MDD!A:C,3,0) -> LOV | D5: Basic | F5: Co Dependent with Description E.g SP - Sports FQ - Footlocker Etc (refer to LOV) | G5: Manual Input in Portal | J5: #N/A | M5: Refer to LOV | O5: D | P5: D | Q5: D | R5: D
A6: Brand | B6: =VLOOKUP(A6,MDD!A:B,2,0) -> AT_Brand | C6: =VLOOKUP(A6,MDD!A:C,3,0) -> LOV | D6: Basic | F6: Co Dependent with Description E.g ADI - Adidas NIK - Nike NEW - New Balance Etc (refer to LOV) | G6: Manual Input in Portal | J6: #N/A | M6: Refer to LOV | O6: D | P6: D | Q6: D | R6: D | U6: Fiellds/Attributes MAA Needs
A7: Brand Group | B7: =VLOOKUP(A7,MDD!A:B,2,0) -> AT_BrandGroup | C7: =VLOOKUP(A7,MDD!A:C,3,0) -> LOV | D7: Basic | F7: Multiple brand codes that managed under 1 brand group e.g. Adidas, Lego, Hasbro | G7: Formula in System | J7: #N/A | M7: Refer to LOV | O7: F | P7: F | Q7: F | R7: F | U7: Thumbnail image | V7: Criteria 1
A8: Brand Type | B8: =VLOOKUP(A8,MDD!A:B,2,0) -> AT_BrandType | C8: =VLOOKUP(A8,MDD!A:C,3,0) -> LOV | D8: Commercial | F8: Whether a brand act as a retailer, selling directly to customers (MAA brands, SDI brands) or as a distributor (Non-MAA brands, Non-SDI brands) | G8: Formula in System | J8: #N/A | M8: Refer to LOV | O8: F | P8: F | Q8: F | R8: F | V8: View : Standard View
A9: Brand Category | B9: =VLOOKUP(A9,MDD!A:B,2,0) -> AT_BrandCategory | C9: =VLOOKUP(A9,MDD!A:C,3,0) -> LOV | D9: Commercial | F9: Group of brands that classified based on their performance/ contribution e.g. Top brands, Selected brands, Non-Top brands | G9: Formula in System | J9: #N/A | M9: Refer to LOV | O9: F | P9: F | Q9: F | R9: F | V9: Category : On Model
A10: Brand Status | B10: =VLOOKUP(A10,MDD!A:B,2,0) -> AT_BrandStatus | C10: =VLOOKUP(A10,MDD!A:C,3,0) -> LOV | D10: Commercial | F10: Indicating whether the brands is actively being sold or, no longer continued or exit the market (Active/Discontinue) | G10: Formula in System | J10: #N/A | M10: Refer to LOV | O10: F | P10: F | Q10: F | R10: F | V10: Background : White
A11: BY Indicator | B11: =VLOOKUP(A11,MDD!A:B,2,0) -> AT_BYIndicator | C11: =VLOOKUP(A11,MDD!A:C,3,0) -> LOV | D11: System indicator | F11: Article to be ordered | G11: Formula in System | J11: #N/A | O11: F | P11: F | Q11: F | R11: F
A12: SAP Indicator | B12: =VLOOKUP(A12,MDD!A:B,2,0) -> AT_SAPIndicator | C12: =VLOOKUP(A12,MDD!A:C,3,0) -> LOV | D12: System indicator | F12: Article has been created | G12: Formula in System | J12: #N/A | O12: F | P12: F | Q12: F | R12: F | V12: Criteria 2
A13: Ecom Indicator | B13: =VLOOKUP(A13,MDD!A:B,2,0) -> AT_EcomIndicator | C13: =VLOOKUP(A13,MDD!A:C,3,0) -> LOV | D13: System indicator | F13: Article to be Publish at Online Sales Channel | G13: Manual Input | J13: #N/A | O13: D | P13: D | Q13: D | R13: D | V13: View : Side Lateral Center View
A14: Principal Style Code | B14: =VLOOKUP(A14,MDD!A:B,2,0) -> AT_PrincipalStyleCode | C14: =VLOOKUP(A14,MDD!A:C,3,0) -> text | D14: Basic | F14: Original Principal Code | G14: Mapping from principal | J14: Article No. | M14: Footwear/Apparel/Accessories Linelist: column 'Article No.' or 'Article Number' Backlog (other excel 1) : Column 'Material No' Notes: Backlog will be ready before shipment. | O14: A | P14: A | Q14: A | R14: A | V14: Category : Photography
A15: Principal Style Description | B15: =VLOOKUP(A15,MDD!A:B,2,0) -> AT_PrincipalStyleDescription | C15: =VLOOKUP(A15,MDD!A:C,3,0) -> text | D15: Basic | E15: Description | F15: Original Principal Product Name | G15: Mapping from principal | J15: Article Name | M15: Footwear/Apparel/Accessories Linelist: column 'Model Name' Notes: Sometimes model name is not available, so will use Dummy/0 and it will be fixed later on after the data updated | O15: A | P15: A | Q15: A | R15: A | V15: Background : White
A16: Principal Color Code | B16: =VLOOKUP(A16,MDD!A:B,2,0) -> AT_PrincipalColorCode | C16: =VLOOKUP(A16,MDD!A:C,3,0) -> text | D16: Basic | E16: Color | F16: Original Principal Color | G16: Mapping from principal | J16: #N/A | M16: No color code. Notes : for Adidas, there's no multiple color in 1 style code | O16: E | P16: E | Q16: E | R16: E
A17: Principal Color Description | B17: =VLOOKUP(A17,MDD!A:B,2,0) -> AT_PrincipalColorName | C17: =VLOOKUP(A17,MDD!A:C,3,0) -> text | D17: Basic | E17: Color | F17: Original Principal Color Description | G17: Mapping from principal | J17: B2B Color1 | M17: Footwear/Apparel/Accessories DTB (downloaded from portal) Column : 'B2B Color 1' Portal Note: AI image recognition might be able to support this mapping | O17: A | P17: A | Q17: A | R17: A | V17: Criteria 3
A18: Principal Gender Code | B18: =VLOOKUP(A18,MDD!A:B,2,0) -> AT_PrincipalGenderCode | C18: =VLOOKUP(A18,MDD!A:C,3,0) -> text | D18: Basic | E18: Gender | F18: Original Principal Gender | G18: Not Avaiable | J18: #N/A | M18: No gender code. | O18: E | P18: E | Q18: E | R18: E | V18: View : Left Side Center View
A19: Principal Gender Description | B19: =VLOOKUP(A19,MDD!A:B,2,0) -> AT_PrincipalGenderDescription | C19: =VLOOKUP(A19,MDD!A:C,3,0) -> text | D19: Basic | E19: Gender | F19: Original Principal Gender Description | G19: Formula in System | J19: B2B Gender | M19: Footwear/Apparel/Accessories Linelist: column 'Gender' DTB (Downloaded from portal) : Column 'Gender' | O19: A | P19: A | Q19: A | R19: A | V19: Category : Photography
A20: Principal Age Code | B20: =VLOOKUP(A20,MDD!A:B,2,0) -> AT_PrincipalAgeCode | C20: =VLOOKUP(A20,MDD!A:C,3,0) -> text | D20: Basic | E20: Age | F20: Original Principal Age | G20: Not Avaiable | J20: #N/A | M20: No age code. | O20: E | P20: E | Q20: E | R20: E | V20: Background : White
A21: Principal Age Description | B21: =VLOOKUP(A21,MDD!A:B,2,0) -> AT_PrincipalAgeDescription | C21: =VLOOKUP(A21,MDD!A:C,3,0) -> text | D21: Basic | E21: Age | F21: Original Principal Age Description | G21: Formula in System | J21: B2B Age Group | M21: Footwear/Apparel/Accessories Linelist: column 'Age Group' DTB (Downloaded from portal) : Column 'Age Group' | O21: A | P21: A | Q21: A | R21: A
A22: Principal Size | B22: =VLOOKUP(A22,MDD!A:B,2,0) -> AT_PrincipalSize | C22: =VLOOKUP(A22,MDD!A:C,3,0) -> text | D22: Basic | E22: Sizing | F22: Original Size from Principal (co-dependent with description) | G22: Mapping from principal | J22: #N/A | M22: Footwear/Apparel/Accessories Backlog (Other excel) Sheet: EAN List, column 'Size' Notes: There are 2 tab sheets in Backlog file. 1st, backlog for generic, 2nd is sizing and EAN list. | O22: A | P22: A | Q22: A | R22: A | V22: Criteria 4
A23: SAP Style Code | B23: =VLOOKUP(A23,MDD!A:B,2,0) -> AT_SAPStyleCode | C23: =VLOOKUP(A23,MDD!A:C,3,0) -> text | D23: Basic | F23: Adjusted principal style code that has been map to SAP generic (without brand code) | G23: Formula in System | J23: #N/A | M23: Footwear/Apparel/Accessories Principal Style Code (max 9 digits) Example: 123456 | O23: A | P23: A | Q23: A | R23: A | V23: View : Any view available in DTB
A24: Generic | B24: =VLOOKUP(A24,MDD!A:B,2,0) -> AT_Generic | C24: =VLOOKUP(A24,MDD!A:C,3,0) -> text | D24: Basic | F24: MAA Generic Code (Max 12 Digits - 3 Digits brand code + 9 Digits Principal Style) | G24: Formula in System | J24: #N/A | M24: Footwear/Apparel/Accessories Mapping formula: Brand Code + Principal Style Code Example: ADI123456 | O24: F | P24: F | Q24: F | R24: F | V24: Category : Any category in DTB
A25: Generic Description | B25: =VLOOKUP(A25,MDD!A:B,2,0) -> AT_GenericDescription | C25: =VLOOKUP(A25,MDD!A:C,3,0) -> regexp | D25: Basic | E25: Description | F25: MAA Generic Description Mapping (Max 40 Digits - 3 Digits brand code + Principal style + (Age/Gender) + Color | G25: Formula in System | J25: #N/A | M25: Mapping formula : 3 Digits Brand Code + Principal Style Description + SAP (Age/Gender) + SAP Mapping Color Description | O25: F | P25: F | Q25: F | R25: F | V25: Background : Any Background in DTB
A26: Variant | B26: =VLOOKUP(A26,MDD!A:B,2,0) -> AT_Variant | C26: =VLOOKUP(A26,MDD!A:C,3,0) -> text | D26: Basic | F26: MAA Article Code (Max 18 Digits - Generic code + 3 Digits MAA / SAP Color (103 color guidance) + 3 Digits MAA size code mapping | G26: Formula in System | J26: #N/A | M26: Footwear/Apparel/Accessories Mapping formula: Generic + 3 Digits SAP Color Code + 3 Digits SAP Size code Example: ADI123456005006 | O26: F | P26: F | Q26: F | R26: F | U26: Principal style code | V26: Article No.
A27: Variant Description | B27: =VLOOKUP(A27,MDD!A:B,2,0) -> AT_VariantDescription | C27: =VLOOKUP(A27,MDD!A:C,3,0) -> text | D27: Basic | E27: Description | F27: MAA Generic Description Mapping (Max 40 Digits - 3 Digits brand code + Principal style + (Age/Gender) + Color + Size | G27: Formula in System | J27: #N/A | M27: Mapping formula : 3 Digits Brand Code + Principal Style Description + SAP (Age/Gender) + SAP Mapping Color Description + Size Description | O27: F | P27: F | Q27: F | R27: F | U27: Principal Style Description | V27: Article Name
A28: SAP Color | B28: =VLOOKUP(A28,MDD!A:B,2,0) -> AT_Color | C28: =VLOOKUP(A28,MDD!A:C,3,0) -> LOV | D28: Basic | E28: Color | F28: MAA 103 Basic SAP Color Code & Description | G28: AI Images Analysist | J28: #N/A | M28: Footwear/Apparel/Accessories Portal Images : Defined from Images by AI (considering LOV) | O28: C | P28: C | Q28: C | R28: C | U28: Principal Merchandise Hierarchy L1 | V28: B2B Product Division
A29: SAP Size | B29: =VLOOKUP(A29,MDD!A:B,2,0) -> AT_Size | C29: =VLOOKUP(A29,MDD!A:C,3,0) -> LOV | D29: Basic | E29: Sizing | F29: MAA SAP Size Code & Description | G29: Mapping from principal | J29: #N/A | M29: Footwear/Apparel/Accessories Principal size will be mapped to SAP size code Notes : The mapping follows LOV For these specific principal size containing "-" in the last character so it should be using H e.g : 10- so 10H, 7- should be 7H. 7.5 should be 7H so on | O29: F | P29: F | Q29: F | R29: F | U29: Principal Merchandise Hierarchy L2 | V29: Product Group
A30: Created on | B30: =VLOOKUP(A30,MDD!A:B,2,0) -> AT_Createdon | C30: =VLOOKUP(A30,MDD!A:C,3,0) -> legacyisodatetime | D30: Basic | F30: When is the creation date | G30: Formula in System | J30: #N/A | M30: Default based on user key in (DD.MM.YYYY) | O30: F | P30: F | Q30: F | R30: F | U30: Principal Merchandise Hierarchy L3 | V30: B2B Business Segment
A31: Created by | B31: =VLOOKUP(A31,MDD!A:B,2,0) -> AT_Createdby | C31: =VLOOKUP(A31,MDD!A:C,3,0) -> text | D31: Basic | F31: Who is creating the articles | G31: Formula in System | J31: #N/A | M31: Default on the creation date (format DD.MM.YYYY) | O31: F | P31: F | Q31: F | R31: F | U31: Principal Merchandise Hierarchy L4 | V31: B2B Product Type
A32: Musical Box Article Code | B32: =VLOOKUP(A32,MDD!A:B,2,0) -> AT_MusicalBoxArticleCode | C32: =VLOOKUP(A32,MDD!A:C,3,0) -> text | D32: Basic | F32: MAA Musical Box Code (Max 18 Digits - 3 Digits brand code + 3 digits of MB- +9 digits of SAP Style Code + 3 Digits Assortment Code) | G32: Not Avaiable | J32: #N/A | M32: N/A | O32: E | P32: E | Q32: E | R32: E | U32: Principal Merchandise Hierarchy L5 | V32: B2B Sports Category
A33: MB Style code | B33: =VLOOKUP(A33,MDD!A:B,2,0) -> AT_MBStyleCode | C33: =VLOOKUP(A33,MDD!A:C,3,0) -> text | D33: Basic | F33: Max 12 digits MB Style (MB- + SAP Style Code ) | G33: Not Avaiable | J33: #N/A | M33: N/A | O33: E | P33: E | Q33: E | R33: E | U33: Principal Color Description | V33: B2B Color1
A34: MB Assortment Code | B34: =VLOOKUP(A34,MDD!A:B,2,0) -> AT_MBAssortmentCode | C34: =VLOOKUP(A34,MDD!A:C,3,0) -> LOV | D34: Basic | F34: 3 Digits Assortment code (based on matrix of qty per sizes) | G34: Not Avaiable | J34: #N/A | M34: N/A | O34: E | P34: E | Q34: E | R34: E | U34: Principal Gender Description | V34: B2B Gender
A35: Musical Box Article Description | B35: =VLOOKUP(A35,MDD!A:B,2,0) -> AT_MusicalBoxArticleDescription | C35: =VLOOKUP(A35,MDD!A:C,3,0) -> text | D35: Basic | E35: Description | F35: MAA Musical Box Description Mapping (Max 40 Digits - 3 Digits brand code + Principal style + (Age/Gender) + Color + (-MB) | G35: Not Avaiable | J35: #N/A | M35: N/A | O35: E | P35: E | Q35: E | R35: E | U35: Principal Age Description | V35: B2B Age Group
A36: Musical Box Components Qty | B36: =VLOOKUP(A36,MDD!A:B,2,0) -> AT_MusicalBoxComponentsQty | C36: =VLOOKUP(A36,MDD!A:C,3,0) -> LOV | D36: Basic | F36: Components qty of Musical Box Articles : Breakdown qty per sizes | G36: Not Avaiable | J36: #N/A | M36: N/A | O36: E | P36: E | Q36: E | R36: E | U36: 1. Current Price | V36: TBC
A37: Musical Box UOM | B37: =VLOOKUP(A37,MDD!A:B,2,0) -> AT_MusicalBoxUOM | C37: =VLOOKUP(A37,MDD!A:C,3,0) -> LOV | D37: Basic | F37: UOM for Musical Box (Default : CAR) | G37: Not Avaiable | J37: #N/A | M37: N/A | O37: E | P37: E | Q37: E | R37: E | U37: 2. Original Price
A38: SAP Age | B38: =VLOOKUP(A38,MDD!A:B,2,0) -> AT_SAPAge | C38: =VLOOKUP(A38,MDD!A:C,3,0) -> LOV | D38: Basic | E38: Age | F38: MAA SAP Age (Co - Dependent with Description) E.g : CH - Children AA - All Ages AD - Adults | G38: Formula in System | J38: #N/A | M38: Footwear/Apparel/Accessories Source: Linelist & DTB (Downloaded from portal) : 'Age Group' Column: Age Group Mapping: Adult = Adult Adults = Adult Infant = Children Infants = Children Junior = Children Youth = Children Children = Children Kids = Children | O38: B | P38: B | Q38: B | R38: B | U38: Principal Sizes | V38: Tab: EAN UPC. Column: Display Size-United Kingdom
A39: SAP Gender | B39: =VLOOKUP(A39,MDD!A:B,2,0) -> AT_Gender | C39: =VLOOKUP(A39,MDD!A:C,3,0) -> LOV | D39: Basic | E39: Gender | F39: MAA SAP Gender (co dependent with description) E.g : M - Male F - Female U - Unisex | G39: Formula in System | J39: #N/A | M39: Footwear/ Apparel/ Accesories Source: Linelist & DTB (downloaded from portal) Column: Gender Mapping: M = Male (M) W = Female (W) U = Unisex (U) Female : Female (W) Women : Female (W) Male : Male (M) Men : Male (M) Unisex : Unisex (U) | O39: B | P39: B | Q39: B | R39: B | U39: Principal Barcode | V39: Tab: EAN UPC. Column: EAN Number
A40: Season | B40: =VLOOKUP(A40,MDD!A:B,2,0) -> AT_Season | C40: =VLOOKUP(A40,MDD!A:C,3,0) -> LOV | D40: Basic | F40: MAA SAP Season (Co Dependent with Description) E.g : SP - Spring SM - Summer FW - Fall Winter SS - Spring Summer etc (refer to LOV) | G40: Manual Input in Portal | J40: TBC | O40: D | P40: D | Q40: D | R40: D | U40: Product Fit | V40: B2B Consumer Fit
A41: Season Year | B41: =VLOOKUP(A41,MDD!A:B,2,0) -> AT_SeasonYear | C41: =VLOOKUP(A41,MDD!A:C,3,0) -> number | D41: Basic | F41: MAA SAP Year | G41: Manual Input in Portal | J41: TBC | O41: D | P41: D | Q41: D | R41: D | U41: Country of Origin | V41: TBC
A42: Country of Origin | B42: =VLOOKUP(A42,MDD!A:B,2,0) -> AT_CountryOrigin | C42: =VLOOKUP(A42,MDD!A:C,3,0) -> LOV | D42: Basic | F42: Co Dependent with Description E.g CN - China VN - Vietnam SG - Singapore etc (refer to LOV) | G42: Formula in System | J42: TBC | M42: Automated - Defaulted - Referring to the currency applied in inputted country | O42: D | P42: D | Q42: D | R42: D | U42: Retail Price Currency | V42: TBC
A43: Vendor | B43: =VLOOKUP(A43,MDD!A:B,2,0) -> AT_Vendor | C43: =VLOOKUP(A43,MDD!A:C,3,0) -> LOV | D43: Basic | F43: MAA Vendor code (Co Dependent with description) Format : Country Code - Comp Code - Vendor Code - Vendor Name MY - 0198 - 10303 - CROCS FOOTWEAR (MALAYSIA) SDN BHD ID - 0888 - 6863 - SKECHERS SARL etc (refer to LOV) | G43: Manual Input | J43: #N/A | O43: D | P43: D | Q43: D | R43: D | U43: 1. Incoming Month | V43: Retail Intro Date
A44: Main Vendor Identification | B44: =VLOOKUP(A44,MDD!A:B,2,0) -> AT_MainVendorIdentification | C44: =VLOOKUP(A44,MDD!A:C,3,0) -> text | D44: Basic | F44: to identify priority vendor | G44: Formula in System | J44: #N/A | M44: Default : 1st entry data | O44: F | P44: F | Q44: F | R44: F | U44: 2. Launching Date
A45: Exchange Rate | B45: =VLOOKUP(A45,MDD!A:B,2,0) -> AT_ExchangeRate | C45: =VLOOKUP(A45,MDD!A:C,3,0) -> number | D45: Price | F45: Exchange Rate to Local Currency | J45: #N/A | O45: F | P45: F | Q45: F | R45: F | U45: Ecomm Short Description (EN) | V45: 1. B2C Copy Short
A46: Pricing Distribution Channel | B46: =VLOOKUP(A46,MDD!A:B,2,0) -> AT_PricingDistributionChannel | C46: =VLOOKUP(A46,MDD!A:C,3,0) -> LOV | D46: Price | F46: To identify price channel Co Dependent with Description) E.g : 01 - Retailer 02 - Wholesale 03 - E-comm | J46: #N/A | M46: Defaulted as 'Retail' | O46: F | P46: D | Q46: F | R46: F | V46: 2. B2B Copy Short
A47: Retail Price Currency | B47: =VLOOKUP(A47,MDD!A:B,2,0) -> AT_RetailPriceCurrency | C47: =VLOOKUP(A47,MDD!A:C,3,0) -> LOV | D47: Price | G47: Formula in System | J47: TBC | M47: Default by currency per country e.g : IIndonesia (IDR), Philiphine (PHP), etc | O47: F | P47: F | Q47: F | R47: F | U47: Ecomm Long Description (EN) | V47: 1. B2C Copy
A48: Original Price | B48: =VLOOKUP(A48,MDD!A:B,2,0) -> AT_OriginalPrice | C48: =VLOOKUP(A48,MDD!A:C,3,0) -> regexp | D48: Price | F48: MAA Original Price | G48: Mapping from principal | J48: TBC | M48: Footwear/ Apparel/ Accesories Source: Linelist & Backlog Column: RRP | O48: A | P48: A | Q48: A | R48: A | V48: 2. B2B Copy
A49: Valid From | B49: =VLOOKUP(A49,MDD!A:B,2,0) -> #N/A | C49: =VLOOKUP(A49,MDD!A:C,3,0) -> #N/A | D49: Price | F49: Identify pricing valid period | G49: Formula in System | J49: #N/A | M49: Based on price creation date (DD.MM.YYYY) | O49: F | P49: F | Q49: F | R49: F | U49: Technology Used | V49: B2B Technology Concept
A50: Valid To | B50: =VLOOKUP(A50,MDD!A:B,2,0) -> #N/A | C50: =VLOOKUP(A50,MDD!A:C,3,0) -> #N/A | D50: Price | F50: Identify pricing valid period Conditional (default as priority 31.12.9999 - editable) | G50: Formula in System | J50: #N/A | M50: Default date (31.12.9999) | O50: F | P50: F | Q50: F | R50: F | U50: Care Instruction (EN) | V50: Bleaching Instruction
A51: Created on | B51: =VLOOKUP(A51,MDD!A:B,2,0) -> AT_Createdon | C51: =VLOOKUP(A51,MDD!A:C,3,0) -> legacyisodatetime | D51: Basic | F51: Identify when the pricing is registered (Maintainance date) | G51: Formula in System | J51: #N/A | M51: Based article creation date (DD.MM.YYYY) | O51: F | P51: F | Q51: F | R51: F | V51: Extra Care Instructions
A52: Created by | B52: =VLOOKUP(A52,MDD!A:B,2,0) -> AT_Createdby | C52: =VLOOKUP(A52,MDD!A:C,3,0) -> text | D52: Basic | F52: Identify who is registering the pricing (User) | G52: Formula in System | J52: #N/A | M52: Based initial user creation | O52: F | P52: F | Q52: F | R52: F | V52: Ironing Instruction
A53: Current price | B53: =VLOOKUP(A53,MDD!A:B,2,0) -> AT_CurrentPrice | C53: =VLOOKUP(A53,MDD!A:C,3,0) -> regexp | D53: Price | F53: MAA Current Price | G53: Mapping from principal | J53: TBC | M53: Footwear/ Apparel/ Accesories Source: Linelist & Backlog Column: RRP | O53: A | P53: A | Q53: A | R53: A | V53: Professional Care Instructions
A54: Valid From | B54: =VLOOKUP(A54,MDD!A:B,2,0) -> #N/A | C54: =VLOOKUP(A54,MDD!A:C,3,0) -> #N/A | D54: Price | F54: Identify pricing valid period | G54: Formula in System | J54: #N/A | M54: Based on price creation date (DD.MM.YYYY) | O54: F | P54: F | Q54: F | R54: F | V54: Washing Instruction
A55: Valid To | B55: =VLOOKUP(A55,MDD!A:B,2,0) -> #N/A | C55: =VLOOKUP(A55,MDD!A:C,3,0) -> #N/A | D55: Price | F55: Identify pricing valid period Conditional (default as priority 31.12.9999 - editable) | G55: Formula in System | J55: #N/A | M55: Default date (31.12.9999) | O55: F | P55: F | Q55: F | R55: F | U55: BCI | V55: TBC
A56: Created on | B56: =VLOOKUP(A56,MDD!A:B,2,0) -> AT_Createdon | C56: =VLOOKUP(A56,MDD!A:C,3,0) -> legacyisodatetime | D56: Basic | F56: Identify when the pricing is registered (Maintainance date) | G56: Formula in System | J56: #N/A | M56: Based article creation date (DD.MM.YYYY) | O56: F | P56: F | Q56: F | R56: F | U56: Silhouette | V56: B2B Closure Type
A57: Created by | B57: =VLOOKUP(A57,MDD!A:B,2,0) -> AT_Createdby | C57: =VLOOKUP(A57,MDD!A:C,3,0) -> text | D57: Basic | F57: Identify who is registering the pricing (User) | G57: Formula in System | J57: #N/A | M57: Based initial user creation | O57: F | P57: F | Q57: F | R57: F | U57: Width | V57: B2B Consumer Fit
A58: Discount Bucket | B58: =VLOOKUP(A58,MDD!A:B,2,0) -> AT_DiscountBucket | C58: =VLOOKUP(A58,MDD!A:C,3,0) -> number | D58: Price | F58: Comparison between original vs current price (non-rounded) | G58: Formula in System | J58: #N/A | M58: Calculated by formula (Ori vs Current Price) | O58: F | P58: F | Q58: F | R58: F | U58: Material-Upper | V58: B2B Upper Main Material
A59: Discount Bucket (Rounded) | B59: =VLOOKUP(A59,MDD!A:B,2,0) -> AT_DiscountBucketRounded | C59: =VLOOKUP(A59,MDD!A:C,3,0) -> number | D59: Price | F59: Comparison between original vs current price (rounded) | G59: Formula in System | J59: #N/A | M59: Calculated by formula (Ori vs Current Price) - Rounding Version | O59: F | P59: F | Q59: F | R59: F | U59: Fastening | V59: B2B Closure Type
A60: Estimated Landed Cost | B60: =VLOOKUP(A60,MDD!A:B,2,0) -> AT_EstimatedLandedCost | C60: =VLOOKUP(A60,MDD!A:C,3,0) -> number | D60: Cost | G60: Formula in System | J60: #N/A | O60: F | P60: F | Q60: F | R60: F | U60: Franchise | V60: TBC
A61: FOB | B61: =VLOOKUP(A61,MDD!A:B,2,0) -> AT_FOB | C61: =VLOOKUP(A61,MDD!A:C,3,0) -> regexp | D61: Cost | G61: Formula in System | J61: #N/A | M61: Calculated by formula based on RRP vs Margin, Tax, other charges components | O61: F | P61: F | Q61: F | R61: F | U61: Content | V61: Material Composition
A62: FOB Currency | B62: =VLOOKUP(A62,MDD!A:B,2,0) -> AT_FOBCurrency | C62: =VLOOKUP(A62,MDD!A:C,3,0) -> LOV | D62: Cost | G62: Formula in System | J62: #N/A | M62: Default by currency per country e.g : IIndonesia (IDR), Philiphine (PHP), etc | O62: F | P62: F | Q62: F | R62: F | U62: Fabric | V62: TBC
A63: Freight Cost | B63: =VLOOKUP(A63,MDD!A:B,2,0) -> AT_FreightCost | C63: =VLOOKUP(A63,MDD!A:C,3,0) -> regexp | D63: Cost | G63: Not Avaiable | J63: #N/A | O63: F | P63: F | Q63: F | R63: F | U63: Pattern/Print | V63: TBC
A64: Royalty | B64: =VLOOKUP(A64,MDD!A:B,2,0) -> AT_Royalty | C64: =VLOOKUP(A64,MDD!A:C,3,0) -> regexp | D64: Cost | G64: Not Avaiable | J64: #N/A | O64: F | P64: F | Q64: F | R64: F | U64: Style | V64: B2B Product Type
A65: Royalty Deduction | B65: =VLOOKUP(A65,MDD!A:B,2,0) -> AT_RoyaltyDeduction | C65: =VLOOKUP(A65,MDD!A:C,3,0) -> regexp | D65: Cost | G65: Not Avaiable | J65: #N/A | O65: F | P65: F | Q65: F | R65: F | U65: Material | V65: Material Composition
A66: Commision | B66: =VLOOKUP(A66,MDD!A:B,2,0) -> #N/A | C66: =VLOOKUP(A66,MDD!A:C,3,0) -> #N/A | D66: Cost | G66: Not Avaiable | J66: #N/A | O66: F | P66: F | Q66: F | R66: F | U66: Pack Details | V66: B2B Quantity Unit
A67: SGS | B67: =VLOOKUP(A67,MDD!A:B,2,0) -> AT_SGS | C67: =VLOOKUP(A67,MDD!A:C,3,0) -> regexp | D67: Cost | G67: Not Avaiable | J67: #N/A | O67: F | P67: F | Q67: F | R67: F | U67: Season | V67: TBC
A68: Marketing Fee | B68: =VLOOKUP(A68,MDD!A:B,2,0) -> AT_MarketingFee | C68: =VLOOKUP(A68,MDD!A:C,3,0) -> regexp | D68: Cost | G68: Not Avaiable | J68: #N/A | O68: F | P68: F | Q68: F | R68: F | U68: Season Year | V68: TBC
A69: Haddad Office Charge | B69: =VLOOKUP(A69,MDD!A:B,2,0) -> AT_HaddadOfficeCharge | C69: =VLOOKUP(A69,MDD!A:C,3,0) -> regexp | D69: Cost | G69: Not Avaiable | J69: #N/A | O69: F | P69: F | Q69: F | R69: F | U69: Country | V69: TBC
A70: Haddad Office Charge - Deduction | B70: =VLOOKUP(A70,MDD!A:B,2,0) -> AT_HaddadOfficeChargeDeduction | C70: =VLOOKUP(A70,MDD!A:C,3,0) -> regexp | D70: Cost | G70: Not Avaiable | J70: #N/A | O70: F | P70: F | Q70: F | R70: F | U70: Collection 1 | V70: B2B Sport
A71: Safeguard Duty (ID Only) | B71: =VLOOKUP(A71,MDD!A:B,2,0) -> AT_SafeguardDutyIdOnly | C71: =VLOOKUP(A71,MDD!A:C,3,0) -> number | D71: Cost | G71: Not Avaiable | J71: #N/A | O71: F | P71: F | Q71: F | R71: F | U71: Collection 2 | V71: B2B Product Type
A72: Label Cost | B72: =VLOOKUP(A72,MDD!A:B,2,0) -> AT_LabelCost | C72: =VLOOKUP(A72,MDD!A:C,3,0) -> regexp | D72: Cost | G72: Not Avaiable | J72: #N/A | O72: F | P72: F | Q72: F | R72: F | U72: Country Size | V72: TBC
A73: Others | B73: =VLOOKUP(A73,MDD!A:B,2,0) -> AT_Others | C73: =VLOOKUP(A73,MDD!A:C,3,0) -> number | D73: Cost | G73: Not Avaiable | J73: #N/A | O73: F | P73: F | Q73: F | R73: F | U73: Ecomm Ages Category | V73: B2B Age Group
A74: MC Structure (Merchandise Category) | B74: =VLOOKUP(A74,MDD!A:B,2,0) -> #N/A | C74: =VLOOKUP(A74,MDD!A:C,3,0) -> #N/A | D74: MC | F74: Structure : 1 Digits of SAP Product Div + 2 Digits of SAP Product Group + 2 Digits of SAP Product Category + 3 Digits of Brand Code + 1 Digits of SAP Product Flag | G74: Formula in System | J74: #N/A | M74: Structure : 1 Digits SAP Product Division + 2 Digits SAP Product Group Code + 2 Digits SAP Product Category + 3 Digits Brand Code + 1 Digits MC Flag | O74: F | P74: F | Q74: F | R74: F | U74: SPU Grouping | V74: TBC
A75: SAP Product Division | B75: =VLOOKUP(A75,MDD!A:B,2,0) -> #N/A | C75: =VLOOKUP(A75,MDD!A:C,3,0) -> #N/A | D75: MC | F75: Co Dependent with Description E.g : F - Footwear | A - Apparel etc | G75: Formula in System | J75: #N/A | M75: Footwear/ Apparel / Accesories Source: Linelist Column: Product Division Value: Footwear = Footwear Apparel = Apparel Hardware + Group | O75: B | P75: B | Q75: B | R75: B | U75: SPU Grouping Name | V75: TBC
A76: SAP Product Group | B76: =VLOOKUP(A76,MDD!A:B,2,0) -> #N/A | C76: =VLOOKUP(A76,MDD!A:C,3,0) -> #N/A | D76: MC | F76: Co Dependent with Description) E.g : FS - Lifestyle Shoes | 34 - Sports Shoes etc | G76: Mapping from principal | J76: #N/A | M76: Footwear/ Apparel / Accesories Source: Linelist Column: Product Group Notes: MD will provide the mapping later on | O76: B | P76: B | Q76: B | R76: B | U76: Product Length (cm) | V76: Article Length
A77: SAP Product Category | B77: =VLOOKUP(A77,MDD!A:B,2,0) -> #N/A | C77: =VLOOKUP(A77,MDD!A:C,3,0) -> #N/A | D77: MC | F77: Co Dependent with Description E.g : RU - Running | CS - Casual Shoes etc | G77: Manual Input | J77: #N/A | M77: Footwear/ Apparel / Accesories Source: Linelist Column: Business Segment Notes: MD will provide the mapping later on | O77: B | P77: B | Q77: B | R77: B | U77: Product Width (cm) | V77: Article Width
A78: SAP Product Flag | B78: =VLOOKUP(A78,MDD!A:B,2,0) -> AT_SAPProductFlag | C78: =VLOOKUP(A78,MDD!A:C,3,0) -> LOV | D78: MC | F78: Co Dependent with Description E.g : A - Intercompany 5 - Direct Local 1 - Consignment etc To indicate the bussiness model (Direct, local, intercompany,consignment, non MD) E.g : A - Intercompany | 5 - Direct Local | 1 - Consignment | G78: Formula in System | J78: #N/A | M78: Footwear/ Apparel / Accesories Adidas is Direct local - Flag 5 (Default will be better) | O78: F | P78: F | Q78: F | R78: F | U78: Product Height (cm) | V78: Article Height
A79: Principal Merchandise Hierarchy L1 | B79: =VLOOKUP(A79,MDD!A:B,2,0) -> AT_PrincipalMerchandiseHierarchyL1 | C79: =VLOOKUP(A79,MDD!A:C,3,0) -> text | D79: Hierarchy | F79: Principal Merchandise Hierarchy Level 1 | G79: Mapping from principal | J79: B2B Product Division | M79: Line list : column 'Product Division' | O79: A | P79: A | Q79: A | R79: A | U79: Product Weight (grams) | V79: Article Weight
A80: Principal Merchandise Hierarchy L2 | B80: =VLOOKUP(A80,MDD!A:B,2,0) -> AT_PrincipalMerchandiseHierarchyL2 | C80: =VLOOKUP(A80,MDD!A:C,3,0) -> text | D80: Hierarchy | F80: Principal Merchandise Hierarchy Level 2 | G80: Mapping from principal | J80: Product Group | M80: Line list : 'Business Segment' | O80: A | P80: A | Q80: A | R80: A
A81: Principal Merchandise Hierarchy L3 | B81: =VLOOKUP(A81,MDD!A:B,2,0) -> AT_PrincipalMerchandiseHierarchyL3 | C81: =VLOOKUP(A81,MDD!A:C,3,0) -> text | D81: Hierarchy | F81: Principal Merchandise Hierarchy Level 3 | G81: Not Avaiable | J81: B2B Business Segment | M81: Line list : 'Product Group' | O81: A | P81: A | Q81: A | R81: A
A82: Principal Merchandise Hierarchy L4 | B82: =VLOOKUP(A82,MDD!A:B,2,0) -> AT_PrincipalMerchandiseHierarchyL4 | C82: =VLOOKUP(A82,MDD!A:C,3,0) -> text | D82: Hierarchy | F82: Principal Merchandise Hierarchy Level 4 | G82: Not Avaiable | J82: B2B Product Type | M82: Line list : 'Product Type' | O82: A | P82: A | Q82: A | R82: A
A83: Principal Merchandise Hierarchy L5 | B83: =VLOOKUP(A83,MDD!A:B,2,0) -> AT_PrincipalMerchandiseHierarchyL5 | C83: =VLOOKUP(A83,MDD!A:C,3,0) -> text | D83: Hierarchy | F83: Principal Merchandise Hierarchy Level 5 | G83: Not Avaiable | J83: B2B Sports Category | M83: Line list : 'Sports Category' | O83: A | P83: A | Q83: A | R83: A
A84: Material Type | B84: =VLOOKUP(A84,MDD!A:B,2,0) -> AT_MaterialType | C84: =VLOOKUP(A84,MDD!A:C,3,0) -> LOV | D84: Commercial | F84: Direct/ Intercompany/ etc | G84: Formula in System | J84: #N/A | M84: Footwear/ Apparel / Accesories Adidas is Direct local - QVB (Default will be better) | O84: F | P84: F | Q84: F | R84: F
A85: Article Category | B85: =VLOOKUP(A85,MDD!A:B,2,0) -> AT_SAPArticleCategory | C85: =VLOOKUP(A85,MDD!A:C,3,0) -> LOV | D85: Basic | F85: SAP Article Category to indicate whether the article is single,Generic,etc | G85: Formula in System | J85: #N/A | M85: Footwear & Apparel : Generic and Variant Accessories : Single or Generic Variant | O85: F | P85: F | Q85: F | R85: F
A86: Internal Barcode | B86: =VLOOKUP(A86,MDD!A:B,2,0) -> AT_InternalBarcode | C86: =VLOOKUP(A86,MDD!A:C,3,0) -> regexp | D86: Basic | E86: Barcode | G86: Not Avaiable | J86: #N/A | M86: N/A | O86: E | P86: E | Q86: E | R86: E
A87: Principal Barcode | B87: =VLOOKUP(A87,MDD!A:B,2,0) -> AT_PrincipalBarcode | C87: =VLOOKUP(A87,MDD!A:C,3,0) -> regexp | D87: Basic | E87: Barcode | F87: Original Principal Barcode | G87: Mapping from principal | J87: Tab: EAN UPC. Column: EAN Number | M87: Footwear/ Apparel / Accesories Source: Backlog Sheet: EAN List | O87: A | P87: A | Q87: A | R87: A
A88: FG Barcode | B88: =VLOOKUP(A88,MDD!A:B,2,0) -> AT_FGBarcode | C88: =VLOOKUP(A88,MDD!A:C,3,0) -> regexp | D88: Basic | E88: Barcode | F88: FG Barcode (Only for Sport Direct) | G88: Not Avaiable | J88: #N/A | O88: D | P88: D | Q88: D | R88: D
A89: Main EAN Indicator | B89: =VLOOKUP(A89,MDD!A:B,2,0) -> AT_MainEANIndicator | C89: =VLOOKUP(A89,MDD!A:C,3,0) -> LOV | D89: Basic | E89: Barcode | G89: Formula in System | J89: #N/A | O89: F | P89: F | Q89: F | R89: F
A90: EAN Category | B90: =VLOOKUP(A90,MDD!A:B,2,0) -> AT_EANCategory | C90: =VLOOKUP(A90,MDD!A:C,3,0) -> LOV | D90: Basic | E90: Barcode | G90: Formula in System | J90: #N/A | O90: F | P90: F | Q90: F | R90: F
A91: Unit of Measurement (UoM) | B91: =VLOOKUP(A91,MDD!A:B,2,0) -> AT_UOM | C91: =VLOOKUP(A91,MDD!A:C,3,0) -> LOV | D91: Basic | G91: Formula in System | J91: #N/A | M91: In SAP for solid article is always be setting up as 'EA' | O91: F | P91: F | Q91: F | R91: F
A92: HS Code | B92: =VLOOKUP(A92,MDD!A:B,2,0) -> AT_HSCode | C92: =VLOOKUP(A92,MDD!A:C,3,0) -> text | D92: Cost | G92: Manual Input | J92: #N/A | M92: N/A | O92: F | P92: F | Q92: F | R92: F
A93: Nature of Article (NOA) | B93: =VLOOKUP(A93,MDD!A:B,2,0) -> #N/A | C93: =VLOOKUP(A93,MDD!A:C,3,0) -> #N/A | D93: Commercial | G93: Manual Input | J93: #N/A | O93: D | P93: D | Q93: D | R93: D
A94: Article Type | B94: =VLOOKUP(A94,MDD!A:B,2,0) -> #N/A | C94: =VLOOKUP(A94,MDD!A:C,3,0) -> #N/A | D94: Commercial | F94: Inline/License/SSE | G94: Formula in System | J94: #N/A | O94: F | P94: F | Q94: F | R94: F
A95: Thumbnail Image | B95: =VLOOKUP(A95,MDD!A:B,2,0) -> #N/A | C95: =VLOOKUP(A95,MDD!A:C,3,0) -> #N/A | D95: Image (BY) | E95: Images | G95: Mapping from principal | J95: Criteria 1 View : Standard View Category : On Model Background : White Criteria 2 View : Side Lateral Center View Category : Photography Background : White Criteria 3 View : Left Side Center View Category : Photography Background : White Criteria 4 View : Any view available in DTB Category : Any category in DTB Background : Any Background in DTB | O95: A | P95: A | Q95: A | R95: A
A96: BY Age | B96: =VLOOKUP(A96,MDD!A:B,2,0) -> AT_BYAge | C96: =VLOOKUP(A96,MDD!A:C,3,0) -> LOV | D96: Basic | G96: Formula in System | J96: #N/A | M96: Footwear/Apparel/Accessories Source: Linelist & DTB (Downloaded from portal) : 'Age Group' Column: Age Group Mapping: Adult = Adult Adults = Adult Infant = Infant Infants = Infant Junior = Kids Youth = Kids Kids = Kids Children = Kids | O96: B | P96: B | Q96: B | R96: B
A97: BY Gender | B97: =VLOOKUP(A97,MDD!A:B,2,0) -> AT_BYGender | C97: =VLOOKUP(A97,MDD!A:C,3,0) -> LOV | D97: Basic | E97: Gender | G97: Formula in System | J97: #N/A | M97: Footwear/ Apparel/ Accesories Source: Linelist & DTB (downloaded from portal) Column: Gender Mapping: M = Male (M) W = Female (W) U = Unisex (U) Female : Female (W) Women : Female (W) Male : Male (M) Men : Male (M) Unisex : Unisex (U) | O97: B | P97: B | Q97: B | R97: B
A98: BCI | B98: =VLOOKUP(A98,MDD!A:B,2,0) -> AT_BCI | C98: =VLOOKUP(A98,MDD!A:C,3,0) -> LOV | D98: Image (BY) | G98: Manual Input | J98: TBC | M98: Manual input | O98: D | P98: D | Q98: D | R98: D
A99: BY Color Group | B99: =VLOOKUP(A99,MDD!A:B,2,0) -> #N/A | C99: =VLOOKUP(A99,MDD!A:C,3,0) -> #N/A | D99: Basic | E99: Color | F99: 6 Color Group | G99: Formula in System | J99: #N/A | M99: Footwear/Apparel/Accessories Portal Images : Defined from Images by AI (refer to LOV) | O99: F | P99: F | Q99: F | R99: F
A100: BY Standardized Color | B100: =VLOOKUP(A100,MDD!A:B,2,0) -> #N/A | C100: =VLOOKUP(A100,MDD!A:C,3,0) -> #N/A | D100: Basic | E100: Color | F100: 53 Color Description | G100: Formula in System | J100: #N/A | M100: Footwear/Apparel/Accessories Portal Images : Defined from Images by AI (refer to LOV) | O100: C | P100: C | Q100: C | R100: C
...

Sheet Sample Lotto - Inline
A2: Stibo Attribute | B2: Stibo Attribute ID | C2: Stibo Validation | D2: Cluster | E2: Grouping | F2: Attributes Description | G2: Field Mapping Type | H2: Brand File Name & Link | I2: Brand File Sheet Name | J2: Field Name in the Brand File | K2: Mapping Logic | L2: Mapping file for additional Brand specific mapping
A3: Country | B3: =VLOOKUP(A3,MDD!A:B,2,0) -> AT_Country | C3: =VLOOKUP(A3,MDD!A:C,3,0) -> LOV | D3: Basic | F3: Co Dependent with Description E.g : ID - Indonesia PH - Philiphine TH - Thailand SG - Singapore MY - Malaysia VN - Vietnam KH : Cambodia
A4: Company | B4: =VLOOKUP(A4,MDD!A:B,2,0) -> AT_CompanyCode | C4: =VLOOKUP(A4,MDD!A:C,3,0) -> LOV | D4: Basic | F4: Co Dependent with Description 0888 - PT. Map Aktif Adiperkasa 0886 - PT. MAP FTL Adiperkasa 0882 - Magna Management Asia etc (Refer to LOV)
A5: SBU | B5: =VLOOKUP(A5,MDD!A:B,2,0) -> AT_SBU | C5: =VLOOKUP(A5,MDD!A:C,3,0) -> LOV | D5: Basic | F5: Co Dependent with Description E.g SP - Sports FQ - Footlocker Etc (refer to LOV)
A6: Brand | B6: =VLOOKUP(A6,MDD!A:B,2,0) -> AT_Brand | C6: =VLOOKUP(A6,MDD!A:C,3,0) -> LOV | D6: Basic | F6: Co Dependent with Description E.g ADI - Adidas NIK - Nike NEW - New Balance Etc (refer to LOV)
A7: Brand Group | B7: =VLOOKUP(A7,MDD!A:B,2,0) -> AT_BrandGroup | C7: =VLOOKUP(A7,MDD!A:C,3,0) -> LOV | D7: Basic | F7: Multiple brand codes that managed under 1 brand group e.g. Adidas, Lego, Hasbro
A8: Brand Type | B8: =VLOOKUP(A8,MDD!A:B,2,0) -> AT_BrandType | C8: =VLOOKUP(A8,MDD!A:C,3,0) -> LOV | D8: Commercial | F8: Whether a brand act as a retailer, selling directly to customers (MAA brands, SDI brands) or as a distributor (Non-MAA brands, Non-SDI brands)
A9: Brand Category | B9: =VLOOKUP(A9,MDD!A:B,2,0) -> AT_BrandCategory | C9: =VLOOKUP(A9,MDD!A:C,3,0) -> LOV | D9: Commercial | F9: Group of brands that classified based on their performance/ contribution e.g. Top brands, Selected brands, Non-Top brands
A10: Brand Status | B10: =VLOOKUP(A10,MDD!A:B,2,0) -> AT_BrandStatus | C10: =VLOOKUP(A10,MDD!A:C,3,0) -> LOV | D10: Commercial | F10: Indicating whether the brands is actively being sold or, no longer continued or exit the market (Active/Discontinue)
A11: BY Indicator | B11: =VLOOKUP(A11,MDD!A:B,2,0) -> AT_BYIndicator | C11: =VLOOKUP(A11,MDD!A:C,3,0) -> LOV | D11: System indicator | F11: Article to be ordered
A12: SAP Indicator | B12: =VLOOKUP(A12,MDD!A:B,2,0) -> AT_SAPIndicator | C12: =VLOOKUP(A12,MDD!A:C,3,0) -> LOV | D12: System indicator | F12: Article has been created
A13: Ecom Indicator | B13: =VLOOKUP(A13,MDD!A:B,2,0) -> AT_EcomIndicator | C13: =VLOOKUP(A13,MDD!A:C,3,0) -> LOV | D13: System indicator | F13: Article to be Publish at Online Sales Channel
A14: Principal Style Code | B14: =VLOOKUP(A14,MDD!A:B,2,0) -> AT_PrincipalStyleCode | C14: =VLOOKUP(A14,MDD!A:C,3,0) -> text | D14: Basic | F14: Original Principal Code
A15: Principal Style Description | B15: =VLOOKUP(A15,MDD!A:B,2,0) -> AT_PrincipalStyleDescription | C15: =VLOOKUP(A15,MDD!A:C,3,0) -> text | D15: Basic | E15: Description | F15: Original Principal Product Name
A16: Principal Color Code | B16: =VLOOKUP(A16,MDD!A:B,2,0) -> AT_PrincipalColorCode | C16: =VLOOKUP(A16,MDD!A:C,3,0) -> text | D16: Basic | E16: Color | F16: Original Principal Color
A17: Principal Color Description | B17: =VLOOKUP(A17,MDD!A:B,2,0) -> AT_PrincipalColorName | C17: =VLOOKUP(A17,MDD!A:C,3,0) -> text | D17: Basic | E17: Color | F17: Original Principal Color Description
A18: Principal Gender Code | B18: =VLOOKUP(A18,MDD!A:B,2,0) -> AT_PrincipalGenderCode | C18: =VLOOKUP(A18,MDD!A:C,3,0) -> text | D18: Basic | E18: Gender | F18: Original Principal Gender
A19: Principal Gender Description | B19: =VLOOKUP(A19,MDD!A:B,2,0) -> AT_PrincipalGenderDescription | C19: =VLOOKUP(A19,MDD!A:C,3,0) -> text | D19: Basic | E19: Gender | F19: Original Principal Gender Description
A20: Principal Age Code | B20: =VLOOKUP(A20,MDD!A:B,2,0) -> AT_PrincipalAgeCode | C20: =VLOOKUP(A20,MDD!A:C,3,0) -> text | D20: Basic | E20: Age | F20: Original Principal Age
A21: Principal Age Description | B21: =VLOOKUP(A21,MDD!A:B,2,0) -> AT_PrincipalAgeDescription | C21: =VLOOKUP(A21,MDD!A:C,3,0) -> text | D21: Basic | E21: Age | F21: Original Principal Age Description
A22: Principal Size | B22: =VLOOKUP(A22,MDD!A:B,2,0) -> AT_PrincipalSize | C22: =VLOOKUP(A22,MDD!A:C,3,0) -> text | D22: Basic | E22: Sizing | F22: Original Size from Principal (co-dependent with description)
A23: SAP Style Code | B23: =VLOOKUP(A23,MDD!A:B,2,0) -> AT_SAPStyleCode | C23: =VLOOKUP(A23,MDD!A:C,3,0) -> text | D23: Basic | F23: Adjusted principal style code that has been map to SAP generic (without brand code)
A24: Generic | B24: =VLOOKUP(A24,MDD!A:B,2,0) -> AT_Generic | C24: =VLOOKUP(A24,MDD!A:C,3,0) -> text | D24: Basic | F24: MAA Generic Code (Max 12 Digits - 3 Digits brand code + 9 Digits Principal Style)
A25: Generic Description | B25: =VLOOKUP(A25,MDD!A:B,2,0) -> AT_GenericDescription | C25: =VLOOKUP(A25,MDD!A:C,3,0) -> regexp | D25: Basic | E25: Description | F25: MAA Generic Description Mapping (Max 40 Digits - 3 Digits brand code + Principal style + (Age/Gender) + Color
A26: Variant | B26: =VLOOKUP(A26,MDD!A:B,2,0) -> AT_Variant | C26: =VLOOKUP(A26,MDD!A:C,3,0) -> text | D26: Basic | F26: MAA Article Code (Max 18 Digits - Generic code + 3 Digits MAA / SAP Color (103 color guidance) + 3 Digits MAA size code mapping
A27: Variant Description | B27: =VLOOKUP(A27,MDD!A:B,2,0) -> AT_VariantDescription | C27: =VLOOKUP(A27,MDD!A:C,3,0) -> text | D27: Basic | E27: Description | F27: MAA Generic Description Mapping (Max 40 Digits - 3 Digits brand code + Principal style + (Age/Gender) + Color + Size
A28: SAP Color | B28: =VLOOKUP(A28,MDD!A:B,2,0) -> AT_Color | C28: =VLOOKUP(A28,MDD!A:C,3,0) -> LOV | D28: Basic | E28: Color | F28: MAA 103 Basic SAP Color Code & Description
A29: SAP Size | B29: =VLOOKUP(A29,MDD!A:B,2,0) -> AT_Size | C29: =VLOOKUP(A29,MDD!A:C,3,0) -> LOV | D29: Basic | E29: Sizing | F29: MAA SAP Size Code & Description
A30: Created on | B30: =VLOOKUP(A30,MDD!A:B,2,0) -> AT_Createdon | C30: =VLOOKUP(A30,MDD!A:C,3,0) -> legacyisodatetime | D30: Basic | F30: When is the creation date
A31: Created by | B31: =VLOOKUP(A31,MDD!A:B,2,0) -> AT_Createdby | C31: =VLOOKUP(A31,MDD!A:C,3,0) -> text | D31: Basic | F31: Who is creating the articles
A32: Musical Box Article Code | B32: =VLOOKUP(A32,MDD!A:B,2,0) -> AT_MusicalBoxArticleCode | C32: =VLOOKUP(A32,MDD!A:C,3,0) -> text | D32: Basic | F32: MAA Musical Box Code (Max 18 Digits - 3 Digits brand code + 3 digits of MB- +9 digits of SAP Style Code + 3 Digits Assortment Code)
A33: MB Style code | B33: =VLOOKUP(A33,MDD!A:B,2,0) -> AT_MBStyleCode | C33: =VLOOKUP(A33,MDD!A:C,3,0) -> text | D33: Basic | F33: Max 12 digits MB Style (MB- + SAP Style Code )
A34: MB Assortment Code | B34: =VLOOKUP(A34,MDD!A:B,2,0) -> AT_MBAssortmentCode | C34: =VLOOKUP(A34,MDD!A:C,3,0) -> LOV | D34: Basic | F34: 3 Digits Assortment code (based on matrix of qty per sizes)
A35: Musical Box Article Description | B35: =VLOOKUP(A35,MDD!A:B,2,0) -> AT_MusicalBoxArticleDescription | C35: =VLOOKUP(A35,MDD!A:C,3,0) -> text | D35: Basic | E35: Description | F35: MAA Musical Box Description Mapping (Max 40 Digits - 3 Digits brand code + Principal style + (Age/Gender) + Color + (-MB)
A36: Musical Box Components Qty | B36: =VLOOKUP(A36,MDD!A:B,2,0) -> AT_MusicalBoxComponentsQty | C36: =VLOOKUP(A36,MDD!A:C,3,0) -> LOV | D36: Basic | F36: Components qty of Musical Box Articles : Breakdown qty per sizes
A37: Musical Box UOM | B37: =VLOOKUP(A37,MDD!A:B,2,0) -> AT_MusicalBoxUOM | C37: =VLOOKUP(A37,MDD!A:C,3,0) -> LOV | D37: Basic | F37: UOM for Musical Box (Default : CAR)
A38: SAP Age | B38: =VLOOKUP(A38,MDD!A:B,2,0) -> AT_SAPAge | C38: =VLOOKUP(A38,MDD!A:C,3,0) -> LOV | D38: Basic | E38: Age | F38: MAA SAP Age (Co - Dependent with Description) E.g : CH - Children AA - All Ages AD - Adults
A39: SAP Gender | B39: =VLOOKUP(A39,MDD!A:B,2,0) -> AT_Gender | C39: =VLOOKUP(A39,MDD!A:C,3,0) -> LOV | D39: Basic | E39: Gender | F39: MAA SAP Gender (co dependent with description) E.g : M - Male F - Female U - Unisex
A40: Season | B40: =VLOOKUP(A40,MDD!A:B,2,0) -> AT_Season | C40: =VLOOKUP(A40,MDD!A:C,3,0) -> LOV | D40: Basic | F40: MAA SAP Season (Co Dependent with Description) E.g : SP - Spring SM - Summer FW - Fall Winter SS - Spring Summer etc (refer to LOV)
A41: Season Year | B41: =VLOOKUP(A41,MDD!A:B,2,0) -> AT_SeasonYear | C41: =VLOOKUP(A41,MDD!A:C,3,0) -> number | D41: Basic | F41: MAA SAP Year
A42: Country of Origin | B42: =VLOOKUP(A42,MDD!A:B,2,0) -> AT_CountryOrigin | C42: =VLOOKUP(A42,MDD!A:C,3,0) -> LOV | D42: Basic | F42: Co Dependent with Description E.g CN - China VN - Vietnam SG - Singapore etc (refer to LOV)
A43: Vendor | B43: =VLOOKUP(A43,MDD!A:B,2,0) -> AT_Vendor | C43: =VLOOKUP(A43,MDD!A:C,3,0) -> LOV | D43: Basic | F43: MAA Vendor code (Co Dependent with description) Format : Country Code - Comp Code - Vendor Code - Vendor Name MY - 0198 - 10303 - CROCS FOOTWEAR (MALAYSIA) SDN BHD ID - 0888 - 6863 - SKECHERS SARL etc (refer to LOV)
A44: Main Vendor Identification | B44: =VLOOKUP(A44,MDD!A:B,2,0) -> AT_MainVendorIdentification | C44: =VLOOKUP(A44,MDD!A:C,3,0) -> text | D44: Basic | F44: to identify priority vendor
A45: Exchange Rate | B45: =VLOOKUP(A45,MDD!A:B,2,0) -> AT_ExchangeRate | C45: =VLOOKUP(A45,MDD!A:C,3,0) -> number | D45: Price | F45: Exchange Rate to Local Currency
A46: Pricing Distribution Channel | B46: =VLOOKUP(A46,MDD!A:B,2,0) -> AT_PricingDistributionChannel | C46: =VLOOKUP(A46,MDD!A:C,3,0) -> LOV | D46: Price | F46: To identify price channel Co Dependent with Description) E.g : 01 - Retailer 02 - Wholesale 03 - E-comm
A47: Retail Price Currency | B47: =VLOOKUP(A47,MDD!A:B,2,0) -> AT_RetailPriceCurrency | C47: =VLOOKUP(A47,MDD!A:C,3,0) -> LOV | D47: Price
A48: Original Price | B48: =VLOOKUP(A48,MDD!A:B,2,0) -> AT_OriginalPrice | C48: =VLOOKUP(A48,MDD!A:C,3,0) -> regexp | D48: Price | F48: MAA Original Price
A49: Valid From | B49: =VLOOKUP(A49,MDD!A:B,2,0) -> #N/A | C49: =VLOOKUP(A49,MDD!A:C,3,0) -> #N/A | D49: Price | F49: Identify pricing valid period
A50: Valid To | B50: =VLOOKUP(A50,MDD!A:B,2,0) -> #N/A | C50: =VLOOKUP(A50,MDD!A:C,3,0) -> #N/A | D50: Price | F50: Identify pricing valid period Conditional (default as priority 31.12.9999 - editable)
A51: Created on | B51: =VLOOKUP(A51,MDD!A:B,2,0) -> AT_Createdon | C51: =VLOOKUP(A51,MDD!A:C,3,0) -> legacyisodatetime | D51: Basic | F51: Identify when the pricing is registered (Maintainance date)
A52: Created by | B52: =VLOOKUP(A52,MDD!A:B,2,0) -> AT_Createdby | C52: =VLOOKUP(A52,MDD!A:C,3,0) -> text | D52: Basic | F52: Identify who is registering the pricing (User)
A53: Current price | B53: =VLOOKUP(A53,MDD!A:B,2,0) -> AT_CurrentPrice | C53: =VLOOKUP(A53,MDD!A:C,3,0) -> regexp | D53: Price | F53: MAA Current Price
A54: Valid From | B54: =VLOOKUP(A54,MDD!A:B,2,0) -> #N/A | C54: =VLOOKUP(A54,MDD!A:C,3,0) -> #N/A | D54: Price | F54: Identify pricing valid period
A55: Valid To | B55: =VLOOKUP(A55,MDD!A:B,2,0) -> #N/A | C55: =VLOOKUP(A55,MDD!A:C,3,0) -> #N/A | D55: Price | F55: Identify pricing valid period Conditional (default as priority 31.12.9999 - editable)
A56: Created on | B56: =VLOOKUP(A56,MDD!A:B,2,0) -> AT_Createdon | C56: =VLOOKUP(A56,MDD!A:C,3,0) -> legacyisodatetime | D56: Basic | F56: Identify when the pricing is registered (Maintainance date)
A57: Created by | B57: =VLOOKUP(A57,MDD!A:B,2,0) -> AT_Createdby | C57: =VLOOKUP(A57,MDD!A:C,3,0) -> text | D57: Basic | F57: Identify who is registering the pricing (User)
A58: Discount Bucket | B58: =VLOOKUP(A58,MDD!A:B,2,0) -> AT_DiscountBucket | C58: =VLOOKUP(A58,MDD!A:C,3,0) -> number | D58: Price | F58: Comparison between original vs current price (non-rounded)
A59: Discount Bucket (Rounded) | B59: =VLOOKUP(A59,MDD!A:B,2,0) -> AT_DiscountBucketRounded | C59: =VLOOKUP(A59,MDD!A:C,3,0) -> number | D59: Price | F59: Comparison between original vs current price (rounded)
A60: Estimated Landed Cost | B60: =VLOOKUP(A60,MDD!A:B,2,0) -> AT_EstimatedLandedCost | C60: =VLOOKUP(A60,MDD!A:C,3,0) -> number | D60: Cost
A61: FOB | B61: =VLOOKUP(A61,MDD!A:B,2,0) -> AT_FOB | C61: =VLOOKUP(A61,MDD!A:C,3,0) -> regexp | D61: Cost
A62: FOB Currency | B62: =VLOOKUP(A62,MDD!A:B,2,0) -> AT_FOBCurrency | C62: =VLOOKUP(A62,MDD!A:C,3,0) -> LOV | D62: Cost
A63: Freight Cost | B63: =VLOOKUP(A63,MDD!A:B,2,0) -> AT_FreightCost | C63: =VLOOKUP(A63,MDD!A:C,3,0) -> regexp | D63: Cost
A64: Royalty | B64: =VLOOKUP(A64,MDD!A:B,2,0) -> AT_Royalty | C64: =VLOOKUP(A64,MDD!A:C,3,0) -> regexp | D64: Cost
A65: Royalty Deduction | B65: =VLOOKUP(A65,MDD!A:B,2,0) -> AT_RoyaltyDeduction | C65: =VLOOKUP(A65,MDD!A:C,3,0) -> regexp | D65: Cost
A66: Commision | B66: =VLOOKUP(A66,MDD!A:B,2,0) -> #N/A | C66: =VLOOKUP(A66,MDD!A:C,3,0) -> #N/A | D66: Cost
A67: SGS | B67: =VLOOKUP(A67,MDD!A:B,2,0) -> AT_SGS | C67: =VLOOKUP(A67,MDD!A:C,3,0) -> regexp | D67: Cost
A68: Marketing Fee | B68: =VLOOKUP(A68,MDD!A:B,2,0) -> AT_MarketingFee | C68: =VLOOKUP(A68,MDD!A:C,3,0) -> regexp | D68: Cost
A69: Haddad Office Charge | B69: =VLOOKUP(A69,MDD!A:B,2,0) -> AT_HaddadOfficeCharge | C69: =VLOOKUP(A69,MDD!A:C,3,0) -> regexp | D69: Cost
A70: Haddad Office Charge - Deduction | B70: =VLOOKUP(A70,MDD!A:B,2,0) -> AT_HaddadOfficeChargeDeduction | C70: =VLOOKUP(A70,MDD!A:C,3,0) -> regexp | D70: Cost
A71: Safeguard Duty (ID Only) | B71: =VLOOKUP(A71,MDD!A:B,2,0) -> AT_SafeguardDutyIdOnly | C71: =VLOOKUP(A71,MDD!A:C,3,0) -> number | D71: Cost
... A73: Others | B73: =VLOOKUP(A73,MDD!A:B,2,0) -> AT_Others | C73: =VLOOKUP(A73,MDD!A:C,3,0) -> number | D73: Cost
A74: MC Structure (Merchandise Category) | B74: =VLOOKUP(A74,MDD!A:B,2,0) -> #N/A | C74: =VLOOKUP(A74,MDD!A:C,3,0) -> #N/A | D74: MC | F74: Structure : 1 Digits of SAP Product Div + 2 Digits of SAP Product Group + 2 Digits of SAP Product Category + 3 Digits of Brand Code + 1 Digits of SAP Product Flag
A75: SAP Product Division | B75: =VLOOKUP(A75,MDD!A:B,2,0) -> #N/A | C75: =VLOOKUP(A75,MDD!A:C,3,0) -> #N/A | D75: MC | F75: Co Dependent with Description E.g : F - Footwear | A - Apparel etc
A76: SAP Product Group | B76: =VLOOKUP(A76,MDD!A:B,2,0) -> #N/A | C76: =VLOOKUP(A76,MDD!A:C,3,0) -> #N/A | D76: MC | F76: Co Dependent with Description) E.g : FS - Lifestyle Shoes | 34 - Sports Shoes etc
A77: SAP Product Category | B77: =VLOOKUP(A77,MDD!A:B,2,0) -> #N/A | C77: =VLOOKUP(A77,MDD!A:C,3,0) -> #N/A | D77: MC | F77: Co Dependent with Description E.g : RU - Running | CS - Casual Shoes etc
A78: SAP Product Flag | B78: =VLOOKUP(A78,MDD!A:B,2,0) -> AT_SAPProductFlag | C78: =VLOOKUP(A78,MDD!A:C,3,0) -> LOV | D78: MC | F78: Co Dependent with Description E.g : A - Intercompany 5 - Direct Local 1 - Consignment etc To indicate the bussiness model (Direct, local, intercompany,consignment, non MD) E.g : A - Intercompany | 5 - Direct Local | 1 - Consignment
A79: Principal Merchandise Hierarchy L1 | B79: =VLOOKUP(A79,MDD!A:B,2,0) -> AT_PrincipalMerchandiseHierarchyL1 | C79: =VLOOKUP(A79,MDD!A:C,3,0) -> text | D79: Hierarchy | F79: Principal Merchandise Hierarchy Level 1
A80: Principal Merchandise Hierarchy L2 | B80: =VLOOKUP(A80,MDD!A:B,2,0) -> AT_PrincipalMerchandiseHierarchyL2 | C80: =VLOOKUP(A80,MDD!A:C,3,0) -> text | D80: Hierarchy | F80: Principal Merchandise Hierarchy Level 2
A81: Principal Merchandise Hierarchy L3 | B81: =VLOOKUP(A81,MDD!A:B,2,0) -> AT_PrincipalMerchandiseHierarchyL3 | C81: =VLOOKUP(A81,MDD!A:C,3,0) -> text | D81: Hierarchy | F81: Principal Merchandise Hierarchy Level 3
A82: Principal Merchandise Hierarchy L4 | B82: =VLOOKUP(A82,MDD!A:B,2,0) -> AT_PrincipalMerchandiseHierarchyL4 | C82: =VLOOKUP(A82,MDD!A:C,3,0) -> text | D82: Hierarchy | F82: Principal Merchandise Hierarchy Level 4
A83: Principal Merchandise Hierarchy L5 | B83: =VLOOKUP(A83,MDD!A:B,2,0) -> AT_PrincipalMerchandiseHierarchyL5 | C83: =VLOOKUP(A83,MDD!A:C,3,0) -> text | D83: Hierarchy | F83: Principal Merchandise Hierarchy Level 5
A84: Material Type | B84: =VLOOKUP(A84,MDD!A:B,2,0) -> AT_MaterialType | C84: =VLOOKUP(A84,MDD!A:C,3,0) -> LOV | D84: Commercial | F84: Direct/ Intercompany/ etc
A85: Article Category | B85: =VLOOKUP(A85,MDD!A:B,2,0) -> AT_SAPArticleCategory | C85: =VLOOKUP(A85,MDD!A:C,3,0) -> LOV | D85: Basic | F85: SAP Article Category to indicate whether the article is single,Generic,etc
A86: Internal Barcode | B86: =VLOOKUP(A86,MDD!A:B,2,0) -> AT_InternalBarcode | C86: =VLOOKUP(A86,MDD!A:C,3,0) -> regexp | D86: Basic | E86: Barcode
A87: Principal Barcode | B87: =VLOOKUP(A87,MDD!A:B,2,0) -> AT_PrincipalBarcode | C87: =VLOOKUP(A87,MDD!A:C,3,0) -> regexp | D87: Basic | E87: Barcode | F87: Original Principal Barcode
A88: FG Barcode | B88: =VLOOKUP(A88,MDD!A:B,2,0) -> AT_FGBarcode | C88: =VLOOKUP(A88,MDD!A:C,3,0) -> regexp | D88: Basic | E88: Barcode | F88: FG Barcode (Only for Sport Direct)
A89: Main EAN Indicator | B89: =VLOOKUP(A89,MDD!A:B,2,0) -> AT_MainEANIndicator | C89: =VLOOKUP(A89,MDD!A:C,3,0) -> LOV | D89: Basic | E89: Barcode
A90: EAN Category | B90: =VLOOKUP(A90,MDD!A:B,2,0) -> AT_EANCategory | C90: =VLOOKUP(A90,MDD!A:C,3,0) -> LOV | D90: Basic | E90: Barcode
A91: Unit of Measurement (UoM) | B91: =VLOOKUP(A91,MDD!A:B,2,0) -> AT_UOM | C91: =VLOOKUP(A91,MDD!A:C,3,0) -> LOV | D91: Basic
A92: HS Code | B92: =VLOOKUP(A92,MDD!A:B,2,0) -> AT_HSCode | C92: =VLOOKUP(A92,MDD!A:C,3,0) -> text | D92: Cost
A93: Nature of Article (NOA) | B93: =VLOOKUP(A93,MDD!A:B,2,0) -> #N/A | C93: =VLOOKUP(A93,MDD!A:C,3,0) -> #N/A | D93: Commercial
A94: Article Type | B94: =VLOOKUP(A94,MDD!A:B,2,0) -> #N/A | C94: =VLOOKUP(A94,MDD!A:C,3,0) -> #N/A | D94: Commercial | F94: Inline/License/SSE
A95: Thumbnail Image | B95: =VLOOKUP(A95,MDD!A:B,2,0) -> #N/A | C95: =VLOOKUP(A95,MDD!A:C,3,0) -> #N/A | D95: Image (BY) | E95: Images
A96: BY Age | B96: =VLOOKUP(A96,MDD!A:B,2,0) -> AT_BYAge | C96: =VLOOKUP(A96,MDD!A:C,3,0) -> LOV | D96: Basic
A97: BY Gender | B97: =VLOOKUP(A97,MDD!A:B,2,0) -> AT_BYGender | C97: =VLOOKUP(A97,MDD!A:C,3,0) -> LOV | D97: Basic | E97: Gender
A98: BCI | B98: =VLOOKUP(A98,MDD!A:B,2,0) -> AT_BCI | C98: =VLOOKUP(A98,MDD!A:C,3,0) -> LOV | D98: Image (BY)
A99: BY Color Group | B99: =VLOOKUP(A99,MDD!A:B,2,0) -> #N/A | C99: =VLOOKUP(A99,MDD!A:C,3,0) -> #N/A | D99: Basic | E99: Color | F99: 6 Color Group
A100: BY Standardized Color | B100: =VLOOKUP(A100,MDD!A:B,2,0) -> #N/A | C100: =VLOOKUP(A100,MDD!A:C,3,0) -> #N/A | D100: Basic | E100: Color | F100: 53 Color Description
A101: Price Range | B101: =VLOOKUP(A101,MDD!A:B,2,0) -> AT_PriceRange | C101: =VLOOKUP(A101,MDD!A:C,3,0) -> LOV | D101: Basic
A102: Silhouette | B102: =VLOOKUP(A102,MDD!A:B,2,0) -> AT_Silhouette | C102: =VLOOKUP(A102,MDD!A:C,3,0) -> LOV | D102: Basic
...

Sheet Sample - 2XU
A2: Stibo Attribute | B2: Stibo Attribute ID | C2: Stibo Validation | D2: Cluster | E2: Grouping | F2: Attributes Description | G2: Field Mapping Type | H2: Brand File Name & Link | I2: Brand File Sheet Name | J2: Field Name in the Brand File | K2: Mapping Logic | L2: Mapping file for additional Brand specific mapping
A3: Country | B3: =VLOOKUP(A3,MDD!A:B,2,0) -> AT_Country | C3: =VLOOKUP(A3,MDD!A:C,3,0) -> LOV | D3: Basic | F3: Co Dependent with Description E.g : ID - Indonesia PH - Philiphine TH - Thailand SG - Singapore MY - Malaysia VN - Vietnam KH : Cambodia | G3: Manual Input | I3: NA | J3: NA
A4: Company | B4: =VLOOKUP(A4,MDD!A:B,2,0) -> AT_CompanyCode | C4: =VLOOKUP(A4,MDD!A:C,3,0) -> LOV | D4: Basic | F4: Co Dependent with Description 0888 - PT. Map Aktif Adiperkasa 0886 - PT. MAP FTL Adiperkasa 0882 - Magna Management Asia etc (Refer to LOV) | G4: Manual Input | I4: NA | J4: NA
A5: SBU | B5: =VLOOKUP(A5,MDD!A:B,2,0) -> AT_SBU | C5: =VLOOKUP(A5,MDD!A:C,3,0) -> LOV | D5: Basic | F5: Co Dependent with Description E.g SP - Sports FQ - Footlocker Etc (refer to LOV) | G5: Manual Input | I5: NA | J5: NA
A6: Brand | B6: =VLOOKUP(A6,MDD!A:B,2,0) -> AT_Brand | C6: =VLOOKUP(A6,MDD!A:C,3,0) -> LOV | D6: Basic | F6: Co Dependent with Description E.g ADI - Adidas NIK - Nike NEW - New Balance Etc (refer to LOV) | G6: Manual Input | I6: NA | J6: NA
A7: Brand Group | B7: =VLOOKUP(A7,MDD!A:B,2,0) -> AT_BrandGroup | C7: =VLOOKUP(A7,MDD!A:C,3,0) -> LOV | D7: Basic | F7: Multiple brand codes that managed under 1 brand group e.g. Adidas, Lego, Hasbro | G7: Formula | I7: NA | J7: NA
A8: Brand Type | B8: =VLOOKUP(A8,MDD!A:B,2,0) -> AT_BrandType | C8: =VLOOKUP(A8,MDD!A:C,3,0) -> LOV | D8: Commercial | F8: Whether a brand act as a retailer, selling directly to customers (MAA brands, SDI brands) or as a distributor (Non-MAA brands, Non-SDI brands) | G8: Formula | I8: NA | J8: NA
A9: Brand Category | B9: =VLOOKUP(A9,MDD!A:B,2,0) -> AT_BrandCategory | C9: =VLOOKUP(A9,MDD!A:C,3,0) -> LOV | D9: Commercial | F9: Group of brands that classified based on their performance/ contribution e.g. Top brands, Selected brands, Non-Top brands | G9: Formula | I9: NA | J9: NA
A10: Brand Status | B10: =VLOOKUP(A10,MDD!A:B,2,0) -> AT_BrandStatus | C10: =VLOOKUP(A10,MDD!A:C,3,0) -> LOV | D10: Commercial | F10: Indicating whether the brands is actively being sold or, no longer continued or exit the market (Active/Discontinue) | G10: Formula | I10: NA | J10: NA
A11: BY Indicator | B11: =VLOOKUP(A11,MDD!A:B,2,0) -> AT_BYIndicator | C11: =VLOOKUP(A11,MDD!A:C,3,0) -> LOV | D11: System indicator | F11: Article to be ordered | G11: Formula | I11: NA | J11: NA
A12: SAP Indicator | B12: =VLOOKUP(A12,MDD!A:B,2,0) -> AT_SAPIndicator | C12: =VLOOKUP(A12,MDD!A:C,3,0) -> LOV | D12: System indicator | F12: Article has been created | G12: Formula | H12: NA | I12: NA | J12: NA
A13: Ecom Indicator | B13: =VLOOKUP(A13,MDD!A:B,2,0) -> AT_EcomIndicator | C13: =VLOOKUP(A13,MDD!A:C,3,0) -> LOV | D13: System indicator | F13: Article to be Publish at Online Sales Channel
A14: Principal Style Code | B14: =VLOOKUP(A14,MDD!A:B,2,0) -> AT_PrincipalStyleCode | C14: =VLOOKUP(A14,MDD!A:C,3,0) -> text | D14: Basic | F14: Original Principal Code | G14: Mapping from Principal | H14: H1 27 Product Bible.xlsx | J14: Product Code
A15: Principal Style Description | B15: =VLOOKUP(A15,MDD!A:B,2,0) -> AT_PrincipalStyleDescription | C15: =VLOOKUP(A15,MDD!A:C,3,0) -> text | D15: Basic | E15: Description | F15: Original Principal Product Name | G15: Mapping from Principal | H15: H1 27 Product Bible.xlsx | J15: Product Name
A16: Principal Color Code | B16: =VLOOKUP(A16,MDD!A:B,2,0) -> AT_PrincipalColorCode | C16: =VLOOKUP(A16,MDD!A:C,3,0) -> text | D16: Basic | E16: Color | F16: Original Principal Color | G16: Mapping from Principal | H16: H1 27 Product Bible.xlsx | J16: Colour Code
A17: Principal Color Description | B17: =VLOOKUP(A17,MDD!A:B,2,0) -> AT_PrincipalColorName | C17: =VLOOKUP(A17,MDD!A:C,3,0) -> text | D17: Basic | E17: Color | F17: Original Principal Color Description | G17: Mapping from Principal | H17: H1 27 Product Bible.xlsx | J17: Colour Description
A18: Principal Gender Code | B18: =VLOOKUP(A18,MDD!A:B,2,0) -> AT_PrincipalGenderCode | C18: =VLOOKUP(A18,MDD!A:C,3,0) -> text | D18: Basic | E18: Gender | F18: Original Principal Gender
A19: Principal Gender Description | B19: =VLOOKUP(A19,MDD!A:B,2,0) -> AT_PrincipalGenderDescription | C19: =VLOOKUP(A19,MDD!A:C,3,0) -> text | D19: Basic | E19: Gender | F19: Original Principal Gender Description | G19: Mapping from Principal | H19: H1 27 Product Bible.xlsx | J19: Gender
A20: Principal Age Code | B20: =VLOOKUP(A20,MDD!A:B,2,0) -> AT_PrincipalAgeCode | C20: =VLOOKUP(A20,MDD!A:C,3,0) -> text | D20: Basic | E20: Age | F20: Original Principal Age
A21: Principal Age Description | B21: =VLOOKUP(A21,MDD!A:B,2,0) -> AT_PrincipalAgeDescription | C21: =VLOOKUP(A21,MDD!A:C,3,0) -> text | D21: Basic | E21: Age | F21: Original Principal Age Description
A22: Principal Size | B22: =VLOOKUP(A22,MDD!A:B,2,0) -> AT_PrincipalSize | C22: =VLOOKUP(A22,MDD!A:C,3,0) -> text | D22: Basic | E22: Sizing | F22: Original Size from Principal (co-dependent with description) | G22: Mapping from Principal | H22: H1 27 Product Bible.xlsx | I22: EAN Barcode | J22: Size
A23: SAP Style Code | B23: =VLOOKUP(A23,MDD!A:B,2,0) -> AT_SAPStyleCode | C23: =VLOOKUP(A23,MDD!A:C,3,0) -> text | D23: Basic | F23: Adjusted principal style code that has been map to SAP generic (without brand code) | G23: Formula | K23: "Apparel & Accessories Max 9 Digits : 7 Digits Principal Style Code + 2 Digits MD Mapping Example : UQ7707E WHT/BLK Result : UQ7707EWB" | L23: 2XU - Stibo Mapping (upd. 21 April 2026).xlsx
A24: Generic | B24: =VLOOKUP(A24,MDD!A:B,2,0) -> AT_Generic | C24: =VLOOKUP(A24,MDD!A:C,3,0) -> text | D24: Basic | F24: MAA Generic Code (Max 12 Digits - 3 Digits brand code + 9 Digits Principal Style)
A25: Generic Description | B25: =VLOOKUP(A25,MDD!A:B,2,0) -> AT_GenericDescription | C25: =VLOOKUP(A25,MDD!A:C,3,0) -> regexp | D25: Basic | E25: Description | F25: MAA Generic Description Mapping (Max 40 Digits - 3 Digits brand code + Principal style + (Age/Gender) + Color
A26: Variant | B26: =VLOOKUP(A26,MDD!A:B,2,0) -> AT_Variant | C26: =VLOOKUP(A26,MDD!A:C,3,0) -> text | D26: Basic | F26: MAA Article Code (Max 18 Digits - Generic code + 3 Digits MAA / SAP Color (103 color guidance) + 3 Digits MAA size code mapping
A27: Variant Description | B27: =VLOOKUP(A27,MDD!A:B,2,0) -> AT_VariantDescription | C27: =VLOOKUP(A27,MDD!A:C,3,0) -> text | D27: Basic | E27: Description | F27: MAA Generic Description Mapping (Max 40 Digits - 3 Digits brand code + Principal style + (Age/Gender) + Color + Size
A28: SAP Color | B28: =VLOOKUP(A28,MDD!A:B,2,0) -> AT_Color | C28: =VLOOKUP(A28,MDD!A:C,3,0) -> LOV | D28: Basic | E28: Color | F28: MAA 103 Basic SAP Color Code & Description
A29: SAP Size | B29: =VLOOKUP(A29,MDD!A:B,2,0) -> AT_Size | C29: =VLOOKUP(A29,MDD!A:C,3,0) -> LOV | D29: Basic | E29: Sizing | F29: MAA SAP Size Code & Description
A30: Created on | B30: =VLOOKUP(A30,MDD!A:B,2,0) -> AT_Createdon | C30: =VLOOKUP(A30,MDD!A:C,3,0) -> legacyisodatetime | D30: Basic | F30: When is the creation date
A31: Created by | B31: =VLOOKUP(A31,MDD!A:B,2,0) -> AT_Createdby | C31: =VLOOKUP(A31,MDD!A:C,3,0) -> text | D31: Basic | F31: Who is creating the articles
A32: Musical Box Article Code | B32: =VLOOKUP(A32,MDD!A:B,2,0) -> AT_MusicalBoxArticleCode | C32: =VLOOKUP(A32,MDD!A:C,3,0) -> text | D32: Basic | F32: MAA Musical Box Code (Max 18 Digits - 3 Digits brand code + 3 digits of MB- +9 digits of SAP Style Code + 3 Digits Assortment Code)
A33: MB Style code | B33: =VLOOKUP(A33,MDD!A:B,2,0) -> AT_MBStyleCode | C33: =VLOOKUP(A33,MDD!A:C,3,0) -> text | D33: Basic | F33: Max 12 digits MB Style (MB- + SAP Style Code )
A34: MB Assortment Code | B34: =VLOOKUP(A34,MDD!A:B,2,0) -> AT_MBAssortmentCode | C34: =VLOOKUP(A34,MDD!A:C,3,0) -> LOV | D34: Basic | F34: 3 Digits Assortment code (based on matrix of qty per sizes)
A35: Musical Box Article Description | B35: =VLOOKUP(A35,MDD!A:B,2,0) -> AT_MusicalBoxArticleDescription | C35: =VLOOKUP(A35,MDD!A:C,3,0) -> text | D35: Basic | E35: Description | F35: MAA Musical Box Description Mapping (Max 40 Digits - 3 Digits brand code + Principal style + (Age/Gender) + Color + (-MB)
A36: Musical Box Components Qty | B36: =VLOOKUP(A36,MDD!A:B,2,0) -> AT_MusicalBoxComponentsQty | C36: =VLOOKUP(A36,MDD!A:C,3,0) -> LOV | D36: Basic | F36: Components qty of Musical Box Articles : Breakdown qty per sizes
A37: Musical Box UOM | B37: =VLOOKUP(A37,MDD!A:B,2,0) -> AT_MusicalBoxUOM | C37: =VLOOKUP(A37,MDD!A:C,3,0) -> LOV | D37: Basic | F37: UOM for Musical Box (Default : CAR)
A38: SAP Age | B38: =VLOOKUP(A38,MDD!A:B,2,0) -> AT_SAPAge | C38: =VLOOKUP(A38,MDD!A:C,3,0) -> LOV | D38: Basic | E38: Age | F38: MAA SAP Age (Co - Dependent with Description) E.g : CH - Children AA - All Ages AD - Adults
A39: SAP Gender | B39: =VLOOKUP(A39,MDD!A:B,2,0) -> AT_Gender | C39: =VLOOKUP(A39,MDD!A:C,3,0) -> LOV | D39: Basic | E39: Gender | F39: MAA SAP Gender (co dependent with description) E.g : M - Male F - Female U - Unisex
A40: Season | B40: =VLOOKUP(A40,MDD!A:B,2,0) -> AT_Season | C40: =VLOOKUP(A40,MDD!A:C,3,0) -> LOV | D40: Basic | F40: MAA SAP Season (Co Dependent with Description) E.g : SP - Spring SM - Summer FW - Fall Winter SS - Spring Summer etc (refer to LOV)
A41: Season Year | B41: =VLOOKUP(A41,MDD!A:B,2,0) -> AT_SeasonYear | C41: =VLOOKUP(A41,MDD!A:C,3,0) -> number | D41: Basic | F41: MAA SAP Year
A42: Country of Origin | B42: =VLOOKUP(A42,MDD!A:B,2,0) -> AT_CountryOrigin | C42: =VLOOKUP(A42,MDD!A:C,3,0) -> LOV | D42: Basic | F42: Co Dependent with Description E.g CN - China VN - Vietnam SG - Singapore etc (refer to LOV)
A43: Vendor | B43: =VLOOKUP(A43,MDD!A:B,2,0) -> AT_Vendor | C43: =VLOOKUP(A43,MDD!A:C,3,0) -> LOV | D43: Basic | F43: MAA Vendor code (Co Dependent with description) Format : Country Code - Comp Code - Vendor Code - Vendor Name MY - 0198 - 10303 - CROCS FOOTWEAR (MALAYSIA) SDN BHD ID - 0888 - 6863 - SKECHERS SARL etc (refer to LOV)
A44: Main Vendor Identification | B44: =VLOOKUP(A44,MDD!A:B,2,0) -> AT_MainVendorIdentification | C44: =VLOOKUP(A44,MDD!A:C,3,0) -> text | D44: Basic | F44: to identify priority vendor
A45: Exchange Rate | B45: =VLOOKUP(A45,MDD!A:B,2,0) -> AT_ExchangeRate | C45: =VLOOKUP(A45,MDD!A:C,3,0) -> number | D45: Price | F45: Exchange Rate to Local Currency
A46: Pricing Distribution Channel | B46: =VLOOKUP(A46,MDD!A:B,2,0) -> AT_PricingDistributionChannel | C46: =VLOOKUP(A46,MDD!A:C,3,0) -> LOV | D46: Price | F46: To identify price channel Co Dependent with Description) E.g : 01 - Retailer 02 - Wholesale 03 - E-comm
A47: Retail Price Currency | B47: =VLOOKUP(A47,MDD!A:B,2,0) -> AT_RetailPriceCurrency | C47: =VLOOKUP(A47,MDD!A:C,3,0) -> LOV | D47: Price
A48: Original Price | B48: =VLOOKUP(A48,MDD!A:B,2,0) -> AT_OriginalPrice | C48: =VLOOKUP(A48,MDD!A:C,3,0) -> regexp | D48: Price | F48: MAA Original Price
A49: Valid From | B49: =VLOOKUP(A49,MDD!A:B,2,0) -> #N/A | C49: =VLOOKUP(A49,MDD!A:C,3,0) -> #N/A | D49: Price | F49: Identify pricing valid period
A50: Valid To | B50: =VLOOKUP(A50,MDD!A:B,2,0) -> #N/A | C50: =VLOOKUP(A50,MDD!A:C,3,0) -> #N/A | D50: Price | F50: Identify pricing valid period Conditional (default as priority 31.12.9999 - editable)
A51: Created on | B51: =VLOOKUP(A51,MDD!A:B,2,0) -> AT_Createdon | C51: =VLOOKUP(A51,MDD!A:C,3,0) -> legacyisodatetime | D51: Basic | F51: Identify when the pricing is registered (Maintainance date)
A52: Created by | B52: =VLOOKUP(A52,MDD!A:B,2,0) -> AT_Createdby | C52: =VLOOKUP(A52,MDD!A:C,3,0) -> text | D52: Basic | F52: Identify who is registering the pricing (User)
A53: Current price | B53: =VLOOKUP(A53,MDD!A:B,2,0) -> AT_CurrentPrice | C53: =VLOOKUP(A53,MDD!A:C,3,0) -> regexp | D53: Price | F53: MAA Current Price
A54: Valid From | B54: =VLOOKUP(A54,MDD!A:B,2,0) -> #N/A | C54: =VLOOKUP(A54,MDD!A:C,3,0) -> #N/A | D54: Price | F54: Identify pricing valid period
A55: Valid To | B55: =VLOOKUP(A55,MDD!A:B,2,0) -> #N/A | C55: =VLOOKUP(A55,MDD!A:C,3,0) -> #N/A | D55: Price | F55: Identify pricing valid period Conditional (default as priority 31.12.9999 - editable)
A56: Created on | B56: =VLOOKUP(A56,MDD!A:B,2,0) -> AT_Createdon | C56: =VLOOKUP(A56,MDD!A:C,3,0) -> legacyisodatetime | D56: Basic | F56: Identify when the pricing is registered (Maintainance date)
A57: Created by | B57: =VLOOKUP(A57,MDD!A:B,2,0) -> AT_Createdby | C57: =VLOOKUP(A57,MDD!A:C,3,0) -> text | D57: Basic | F57: Identify who is registering the pricing (User)
A58: Discount Bucket | B58: =VLOOKUP(A58,MDD!A:B,2,0) -> AT_DiscountBucket | C58: =VLOOKUP(A58,MDD!A:C,3,0) -> number | D58: Price | F58: Comparison between original vs current price (non-rounded)
A59: Discount Bucket (Rounded) | B59: =VLOOKUP(A59,MDD!A:B,2,0) -> AT_DiscountBucketRounded | C59: =VLOOKUP(A59,MDD!A:C,3,0) -> number | D59: Price | F59: Comparison between original vs current price (rounded)
A60: Estimated Landed Cost | B60: =VLOOKUP(A60,MDD!A:B,2,0) -> AT_EstimatedLandedCost | C60: =VLOOKUP(A60,MDD!A:C,3,0) -> number | D60: Cost
A61: FOB | B61: =VLOOKUP(A61,MDD!A:B,2,0) -> AT_FOB | C61: =VLOOKUP(A61,MDD!A:C,3,0) -> regexp | D61: Cost
A62: FOB Currency | B62: =VLOOKUP(A62,MDD!A:B,2,0) -> AT_FOBCurrency | C62: =VLOOKUP(A62,MDD!A:C,3,0) -> LOV | D62: Cost
A63: Freight Cost | B63: =VLOOKUP(A63,MDD!A:B,2,0) -> AT_FreightCost | C63: =VLOOKUP(A63,MDD!A:C,3,0) -> regexp | D63: Cost
A64: Royalty | B64: =VLOOKUP(A64,MDD!A:B,2,0) -> AT_Royalty | C64: =VLOOKUP(A64,MDD!A:C,3,0) -> regexp | D64: Cost
A65: Royalty Deduction | B65: =VLOOKUP(A65,MDD!A:B,2,0) -> AT_RoyaltyDeduction | C65: =VLOOKUP(A65,MDD!A:C,3,0) -> regexp | D65: Cost
A66: Commision | B66: =VLOOKUP(A66,MDD!A:B,2,0) -> #N/A | C66: =VLOOKUP(A66,MDD!A:C,3,0) -> #N/A | D66: Cost
A67: SGS | B67: =VLOOKUP(A67,MDD!A:B,2,0) -> AT_SGS | C67: =VLOOKUP(A67,MDD!A:C,3,0) -> regexp | D67: Cost
A68: Marketing Fee | B68: =VLOOKUP(A68,MDD!A:B,2,0) -> AT_MarketingFee | C68: =VLOOKUP(A68,MDD!A:C,3,0) -> regexp | D68: Cost
A69: Haddad Office Charge | B69: =VLOOKUP(A69,MDD!A:B,2,0) -> AT_HaddadOfficeCharge | C69: =VLOOKUP(A69,MDD!A:C,3,0) -> regexp | D69: Cost
A70: Haddad Office Charge - Deduction | B70: =VLOOKUP(A70,MDD!A:B,2,0) -> AT_HaddadOfficeChargeDeduction | C70: =VLOOKUP(A70,MDD!A:C,3,0) -> regexp | D70: Cost
A71: Safeguard Duty (ID Only) | B71: =VLOOKUP(A71,MDD!A:B,2,0) -> AT_SafeguardDutyIdOnly | C71: =VLOOKUP(A71,MDD!A:C,3,0) -> number | D71: Cost
... A73: Others | B73: =VLOOKUP(A73,MDD!A:B,2,0) -> AT_Others | C73: =VLOOKUP(A73,MDD!A:C,3,0) -> number | D73: Cost
A74: MC Structure (Merchandise Category) | B74: =VLOOKUP(A74,MDD!A:B,2,0) -> #N/A | C74: =VLOOKUP(A74,MDD!A:C,3,0) -> #N/A | D74: MC | F74: Structure : 1 Digits of SAP Product Div + 2 Digits of SAP Product Group + 2 Digits of SAP Product Category + 3 Digits of Brand Code + 1 Digits of SAP Product Flag
A75: SAP Product Division | B75: =VLOOKUP(A75,MDD!A:B,2,0) -> #N/A | C75: =VLOOKUP(A75,MDD!A:C,3,0) -> #N/A | D75: MC | F75: Co Dependent with Description E.g : F - Footwear | A - Apparel etc
A76: SAP Product Group | B76: =VLOOKUP(A76,MDD!A:B,2,0) -> #N/A | C76: =VLOOKUP(A76,MDD!A:C,3,0) -> #N/A | D76: MC | F76: Co Dependent with Description) E.g : FS - Lifestyle Shoes | 34 - Sports Shoes etc
A77: SAP Product Category | B77: =VLOOKUP(A77,MDD!A:B,2,0) -> #N/A | C77: =VLOOKUP(A77,MDD!A:C,3,0) -> #N/A | D77: MC | F77: Co Dependent with Description E.g : RU - Running | CS - Casual Shoes etc
A78: SAP Product Flag | B78: =VLOOKUP(A78,MDD!A:B,2,0) -> AT_SAPProductFlag | C78: =VLOOKUP(A78,MDD!A:C,3,0) -> LOV | D78: MC | F78: Co Dependent with Description E.g : A - Intercompany 5 - Direct Local 1 - Consignment etc To indicate the bussiness model (Direct, local, intercompany,consignment, non MD) E.g : A - Intercompany | 5 - Direct Local | 1 - Consignment
A79: Principal Merchandise Hierarchy L1 | B79: =VLOOKUP(A79,MDD!A:B,2,0) -> AT_PrincipalMerchandiseHierarchyL1 | C79: =VLOOKUP(A79,MDD!A:C,3,0) -> text | D79: Hierarchy | F79: Principal Merchandise Hierarchy Level 1
A80: Principal Merchandise Hierarchy L2 | B80: =VLOOKUP(A80,MDD!A:B,2,0) -> AT_PrincipalMerchandiseHierarchyL2 | C80: =VLOOKUP(A80,MDD!A:C,3,0) -> text | D80: Hierarchy | F80: Principal Merchandise Hierarchy Level 2
A81: Principal Merchandise Hierarchy L3 | B81: =VLOOKUP(A81,MDD!A:B,2,0) -> AT_PrincipalMerchandiseHierarchyL3 | C81: =VLOOKUP(A81,MDD!A:C,3,0) -> text | D81: Hierarchy | F81: Principal Merchandise Hierarchy Level 3
A82: Principal Merchandise Hierarchy L4 | B82: =VLOOKUP(A82,MDD!A:B,2,0) -> AT_PrincipalMerchandiseHierarchyL4 | C82: =VLOOKUP(A82,MDD!A:C,3,0) -> text | D82: Hierarchy | F82: Principal Merchandise Hierarchy Level 4
A83: Principal Merchandise Hierarchy L5 | B83: =VLOOKUP(A83,MDD!A:B,2,0) -> AT_PrincipalMerchandiseHierarchyL5 | C83: =VLOOKUP(A83,MDD!A:C,3,0) -> text | D83: Hierarchy | F83: Principal Merchandise Hierarchy Level 5
A84: Material Type | B84: =VLOOKUP(A84,MDD!A:B,2,0) -> AT_MaterialType | C84: =VLOOKUP(A84,MDD!A:C,3,0) -> LOV | D84: Commercial | F84: Direct/ Intercompany/ etc
A85: Article Category | B85: =VLOOKUP(A85,MDD!A:B,2,0) -> AT_SAPArticleCategory | C85: =VLOOKUP(A85,MDD!A:C,3,0) -> LOV | D85: Basic | F85: SAP Article Category to indicate whether the article is single,Generic,etc
A86: Internal Barcode | B86: =VLOOKUP(A86,MDD!A:B,2,0) -> AT_InternalBarcode | C86: =VLOOKUP(A86,MDD!A:C,3,0) -> regexp | D86: Basic | E86: Barcode
A87: Principal Barcode | B87: =VLOOKUP(A87,MDD!A:B,2,0) -> AT_PrincipalBarcode | C87: =VLOOKUP(A87,MDD!A:C,3,0) -> regexp | D87: Basic | E87: Barcode | F87: Original Principal Barcode | G87: Mapping from Principal | H87: H226CN1 1MAPA001 Order Confirmation.xlsx | I87: Rep9534.tmp | J87: Barcode/EAN
A88: FG Barcode | B88: =VLOOKUP(A88,MDD!A:B,2,0) -> AT_FGBarcode | C88: =VLOOKUP(A88,MDD!A:C,3,0) -> regexp | D88: Basic | E88: Barcode | F88: FG Barcode (Only for Sport Direct)
A89: Main EAN Indicator | B89: =VLOOKUP(A89,MDD!A:B,2,0) -> AT_MainEANIndicator | C89: =VLOOKUP(A89,MDD!A:C,3,0) -> LOV | D89: Basic | E89: Barcode
A90: EAN Category | B90: =VLOOKUP(A90,MDD!A:B,2,0) -> AT_EANCategory | C90: =VLOOKUP(A90,MDD!A:C,3,0) -> LOV | D90: Basic | E90: Barcode
A91: Unit of Measurement (UoM) | B91: =VLOOKUP(A91,MDD!A:B,2,0) -> AT_UOM | C91: =VLOOKUP(A91,MDD!A:C,3,0) -> LOV | D91: Basic
A92: HS Code | B92: =VLOOKUP(A92,MDD!A:B,2,0) -> AT_HSCode | C92: =VLOOKUP(A92,MDD!A:C,3,0) -> text | D92: Cost
A93: Nature of Article (NOA) | B93: =VLOOKUP(A93,MDD!A:B,2,0) -> #N/A | C93: =VLOOKUP(A93,MDD!A:C,3,0) -> #N/A | D93: Commercial
A94: Article Type | B94: =VLOOKUP(A94,MDD!A:B,2,0) -> #N/A | C94: =VLOOKUP(A94,MDD!A:C,3,0) -> #N/A | D94: Commercial | F94: Inline/License/SSE
A95: Thumbnail Image | B95: =VLOOKUP(A95,MDD!A:B,2,0) -> #N/A | C95: =VLOOKUP(A95,MDD!A:C,3,0) -> #N/A | D95: Image (BY) | E95: Images
A96: BY Age | B96: =VLOOKUP(A96,MDD!A:B,2,0) -> AT_BYAge | C96: =VLOOKUP(A96,MDD!A:C,3,0) -> LOV | D96: Basic
A97: BY Gender | B97: =VLOOKUP(A97,MDD!A:B,2,0) -> AT_BYGender | C97: =VLOOKUP(A97,MDD!A:C,3,0) -> LOV | D97: Basic | E97: Gender
A98: BCI | B98: =VLOOKUP(A98,MDD!A:B,2,0) -> AT_BCI | C98: =VLOOKUP(A98,MDD!A:C,3,0) -> LOV | D98: Image (BY)
A99: BY Color Group | B99: =VLOOKUP(A99,MDD!A:B,2,0) -> #N/A | C99: =VLOOKUP(A99,MDD!A:C,3,0) -> #N/A | D99: Basic | E99: Color | F99: 6 Color Group
A100: BY Standardized Color | B100: =VLOOKUP(A100,MDD!A:B,2,0) -> #N/A | C100: =VLOOKUP(A100,MDD!A:C,3,0) -> #N/A | D100: Basic | E100: Color | F100: 53 Color Description
A101: Price Range | B101: =VLOOKUP(A101,MDD!A:B,2,0) -> AT_PriceRange | C101: =VLOOKUP(A101,MDD!A:C,3,0) -> LOV | D101: Basic
A102: Silhouette | B102: =VLOOKUP(A102,MDD!A:B,2,0) -> AT_Silhouette | C102: =VLOOKUP(A102,MDD!A:C,3,0) -> LOV | D102: Basic
...

Sheet Crocs(Inline)
A2: Stibo Attribute | B2: Stibo Attribute ID | C2: Stibo Validation | D2: Cluster | E2: Grouping | F2: Attributes Description | G2: Field Mapping Type | H2: Brand File Name & Link | I2: Brand File Sheet Name | J2: Field Name in the Brand File | K2: Mapping Logic | L2: Mapping file for additional Brand specific mapping
A3: Country | B3: =VLOOKUP(A3,MDD!A:B,2,0) -> AT_Country | C3: LOV | F3: "Co Dependent with Description E.g : ID - Indonesia PH - Philiphine TH - Thailand SG - Singapore MY - Malaysia VN - Vietnam KH : Cambodia" | G3: Manual Input
A4: Company | B4: =VLOOKUP(A4,MDD!A:B,2,0) -> AT_CompanyCode | C4: LOV | F4: "Co Dependent with Description 0888 - PT. Map Aktif Adiperkasa 0886 - PT. MAP FTL Adiperkasa 0882 - Magna Management Asia etc (Refer to LOV)" | G4: Manual Input
A5: SBU | B5: =VLOOKUP(A5,MDD!A:B,2,0) -> AT_SBU | C5: LOV | F5: "Co Dependent with Description E.g SP - Sports FQ - Footlocker Etc (refer to LOV)" | G5: Manual Input
A6: Brand | B6: =VLOOKUP(A6,MDD!A:B,2,0) -> AT_Brand | C6: LOV | F6: "Co Dependent with Description E.g ADI - Adidas NIK - Nike NEW - New Balance Etc (refer to LOV)" | G6: Manual Input
A7: Brand Group | B7: =VLOOKUP(A7,MDD!A:B,2,0) -> AT_BrandGroup | C7: LOV | F7: Multiple brand codes that managed under 1 brand group e.g. Adidas, Lego, Hasbro | G7: Formula in system
A8: Brand Type | B8: =VLOOKUP(A8,MDD!A:B,2,0) -> AT_BrandType | C8: LOV | F8: Whether a brand act as a retailer, selling directly to customers (MAA brands, SDI brands) or as a distributor (Non-MAA brands, Non-SDI brands) | G8: Formula in system
A9: Brand Category | B9: =VLOOKUP(A9,MDD!A:B,2,0) -> AT_BrandCategory | C9: LOV | F9: Group of brands that classified based on their performance/ contribution e.g. Top brands, Selected brands, Non-Top brands | G9: Formula in system
A10: Brand Status | B10: =VLOOKUP(A10,MDD!A:B,2,0) -> AT_BrandStatus | C10: =VLOOKUP(A10,MDD!A:C,3,0) -> LOV | F10: Indicating whether the brands is actively being sold or, no longer continued or exit the market (Active/Discontinue) | G10: Formula in system
A11: BY Indicator | B11: =VLOOKUP(A11,MDD!A:B,2,0) -> AT_BYIndicator | C11: =VLOOKUP(A11,MDD!A:C,3,0) -> LOV | F11: Article to be ordered | G11: Formula in system
A12: SAP Indicator | B12: =VLOOKUP(A12,MDD!A:B,2,0) -> AT_SAPIndicator | C12: =VLOOKUP(A12,MDD!A:C,3,0) -> LOV | F12: Article has been created | G12: Formula in system
A13: Ecom Indicator | B13: =VLOOKUP(A13,MDD!A:B,2,0) -> AT_EcomIndicator | C13: =VLOOKUP(A13,MDD!A:C,3,0) -> LOV | F13: Article to be Publish at Online Sales Channel | G13: Manual Input
A14: Principal Style Code | B14: =VLOOKUP(A14,MDD!A:B,2,0) -> AT_PrincipalStyleCode | C14: Text | F14: Original Principal Code | G14: Direct from Principal | H14: S1 26 SEA Line List (SEA) (2).xlsb | J14: Colorway Code | K14: "FW & Acc Line List : Column 'Colorway Code'"
A15: Principal Style Description | B15: =VLOOKUP(A15,MDD!A:B,2,0) -> AT_PrincipalStyleDescription | C15: Text | E15: Description | F15: Original Principal Product Name | G15: Direct from Principal | H15: S1 26 SEA Line List (SEA) (2).xlsb | J15: Style | K15: "FW & Acc Line List : Column 'Style' "
A16: Principal Color Code | B16: =VLOOKUP(A16,MDD!A:B,2,0) -> AT_PrincipalColorCode | C16: Text | E16: Color | F16: Original Principal Color | G16: Formula in system | H16: S1 26 SEA Line List (SEA) (2).xlsb | J16: Colorway Code | K16: "FW & Acc Line List : Column 'Colorway Code' (put the last 3 digits)"
A17: Principal Color Description | B17: =VLOOKUP(A17,MDD!A:B,2,0) -> AT_PrincipalColorName | C17: Text | E17: Color | F17: Original Principal Color Description | G17: Direct from Principal | H17: S1 26 SEA Line List (SEA) (2).xlsb | J17: Colorway | K17: "FW & Acc Line List : Column 'Colorway'"
A18: Principal Gender Code | B18: =VLOOKUP(A18,MDD!A:B,2,0) -> AT_PrincipalGenderCode | E18: Gender | F18: Original Principal Gender | G18: N/A
A19: Principal Gender Description | B19: =VLOOKUP(A19,MDD!A:B,2,0) -> AT_PrincipalGenderDescription | E19: Gender | F19: Original Principal Gender Description | G19: Direct from Principal | H19: S1 26 SEA Line List (SEA) (2).xlsb | J19: Gender | K19: "FW & Acc Line list : Column 'Gender'"
A20: Principal Age Code | B20: =VLOOKUP(A20,MDD!A:B,2,0) -> AT_PrincipalAgeCode | E20: Age | F20: Original Principal Age | G20: N/A
A21: Principal Age Description | B21: =VLOOKUP(A21,MDD!A:B,2,0) -> AT_PrincipalAgeDescription | E21: Age | F21: Original Principal Age Description | G21: N/A
A22: Principal Size Code | B22: AT_PrincipalStyleCode | E22: Sizing | F22: Original Size from Principal (co-dependent with description) | G22: Direct from Principal | H22: S1 26 SEA Line List (SEA) (2).xlsb | J22: Size Range (Colorway) | K22: FW & Acc_x000D_ Line list : Column 'Size Range' (Colorway)
A23: SAP Style Code | B23: =VLOOKUP(A23,MDD!A:B,2,0) -> AT_SAPStyleCode | F23: Adjusted principal style code that has been map to SAP generic (without brand code) | G23: Mapping from Principal | H23: S1 26 SEA Line List (SEA) (2).xlsb | J23: Colorway Code | K23: "FW & Acc Line List : Column 'Colorway Code' FW : (if more than 9, delete ""-"") ex: 212953-90H -> 21295390H JBZ : (add ""-"" after 3 digits) EX:10016475 -> 100-16475"
A24: Generic | B24: =VLOOKUP(A24,MDD!A:B,2,0) -> AT_Generic | F24: MAA Generic Code (Max 12 Digits - 3 Digits brand code + 9 Digits Principal Style) | G24: Mapping from Principal | H24: S1 26 SEA Line List (SEA) (2).xlsb | J24: Colorway Code | K24: "FW & Acc Line List : Column 'Colorway Code' Mapping with rules FW : (if more than 12, delete ""-"") ex: 212953-90H -> CCR21295390H JBZ : (add ""-"" after 3 digits) EX:10016475 -> CCR100-16475"
A25: Generic Description | B25: =VLOOKUP(A25,MDD!A:B,2,0) -> AT_GenericDescription | E25: Description | F25: MAA Generic Description Mapping (Max 40 Digits - 3 Digits brand code + Principal style + (Age/Gender) + Color | G25: Mapping from Principal | K25: MAA Generic Description Mapping (Max 40 Digits - 3 Digits brand code + Principal style + (Age/Gender) + Color
A26: Variant | B26: =VLOOKUP(A26,MDD!A:B,2,0) -> AT_Variant | F26: MAA Article Code (Max 18 Digits - Generic code + 3 Digits MAA / SAP Color (103 color guidance) + 3 Digits MAA size code mapping | G26: Mapping from Principal | K26: "FW & Acc 3 Digits Brand Code + Max 9 DIgits Principal Style Code + 3 digits SAP Color code + 3 digits Size code"
A27: Variant Description | B27: =VLOOKUP(A27,MDD!A:B,2,0) -> AT_VariantDescription | E27: Description | F27: MAA Generic Description Mapping (Max 40 Digits - 3 Digits brand code + Principal style + (Age/Gender) + Color + Size | G27: Mapping from Principal | K27: "FW & Acc MAA Generic Description Mapping (Max 40 Digits - 3 Digits brand code + Principal style + (Age/Gender) + Color + Size Shorten: Classic -Cls/Cs, Clog - Clg/Cg Platform - Pltfrm, Sandal-Sndl (have no fix mapping for shorten the desc) Jibbitz - Jbz, 5 Pack-5P/5Pck"
A28: SAP Color | B28: =VLOOKUP(A28,MDD!A:B,2,0) -> AT_Color | E28: Color | F28: MAA 103 Basic SAP Color Code & Description | G28: Defined from Images | K28: "FW :Defined from Images by AI Acc : Define by AI Default 'No color' Acc - Bag : Defined from Images by AI "
A29: SAP Size | B29: =VLOOKUP(A29,MDD!A:B,2,0) -> AT_Size | E29: Sizing | F29: MAA SAP Size Code & Description | G29: Mapping from Principal | J29: Size Range | K29: "FW : Line list : Size Range (refer to LOV) Acc Bags : Default 'No Size'"
A30: Created on | B30: =VLOOKUP(A30,MDD!A:B,2,0) -> AT_Createdon | C30: =VLOOKUP(A30,MDD!A:C,3,0) -> legacyisodatetime | D30: Basic | F30: When is the creation date | G30: Formula in system
A31: Created by | B31: =VLOOKUP(A31,MDD!A:B,2,0) -> AT_Createdby | C31: =VLOOKUP(A31,MDD!A:C,3,0) -> text | D31: Basic | F31: Who is creating the articles | G31: Formula in system
A32: Musical Box Article Code | B32: =VLOOKUP(A32,MDD!A:B,2,0) -> AT_MusicalBoxArticleCode | C32: =VLOOKUP(A32,MDD!A:C,3,0) -> text | F32: MAA Musical Box Code (Max 18 Digits - 3 Digits brand code + 3 digits of MB- +9 digits of SAP Style Code + 3 Digits Assortment Code)
A33: MB Style code | B33: =VLOOKUP(A33,MDD!A:B,2,0) -> AT_MBStyleCode | C33: =VLOOKUP(A33,MDD!A:C,3,0) -> text | F33: Max 12 digits MB Style (MB- + SAP Style Code )
A34: MB Assortment Code | B34: =VLOOKUP(A34,MDD!A:B,2,0) -> AT_MBAssortmentCode | C34: =VLOOKUP(A34,MDD!A:C,3,0) -> LOV | F34: 3 Digits Assortment code (based on matrix of qty per sizes)
A35: Musical Box Article Description | B35: =VLOOKUP(A35,MDD!A:B,2,0) -> AT_MusicalBoxArticleDescription | C35: =VLOOKUP(A35,MDD!A:C,3,0) -> text | F35: MAA Musical Box Description Mapping (Max 40 Digits - 3 Digits brand code + Principal style + (Age/Gender) + Color + (-MB)
A36: Musical Box Components Qty | B36: =VLOOKUP(A36,MDD!A:B,2,0) -> AT_MusicalBoxComponentsQty | C36: =VLOOKUP(A36,MDD!A:C,3,0) -> LOV | F36: Components qty of Musical Box Articles : Breakdown qty per sizes
A37: Musical Box UOM | B37: =VLOOKUP(A37,MDD!A:B,2,0) -> AT_MusicalBoxUOM | C37: =VLOOKUP(A37,MDD!A:C,3,0) -> LOV | F37: UOM for Musical Box (Default : CAR) | G37: Formula in system | K37: default 'CAR'
A38: SAP Age | B38: =VLOOKUP(A38,MDD!A:B,2,0) -> AT_SAPAge | C38: =VLOOKUP(A38,MDD!A:C,3,0) -> LOV | E38: Age | F38: "MAA SAP Age (Co - Dependent with Description) E.g : CH - Children AA - All Ages AD - Adults" | G38: Mapping from Principal | H38: S1 26 SEA Line List (SEA) (2).xlsb | J38: Gender | K38: "FW Line list : Column 'Gender' (Mapping) Men : Adults Women : Adults Unisex Adults : Adults Unisex Kids : Children Acc : Default 'Adults'"
A39: SAP Gender | B39: =VLOOKUP(A39,MDD!A:B,2,0) -> AT_Gender | C39: =VLOOKUP(A39,MDD!A:C,3,0) -> LOV | E39: Gender | F39: "MAA SAP Gender (co dependent with description) E.g : M - Male F - Female U - Unisex" | G39: Mapping from Principal | H39: S1 26 SEA Line List (SEA) (2).xlsb | J39: Gender | K39: "FW Line list : Column 'Gender' (Mapping) Men : Male Women : Female Unisex Adults : Unisex Unisex Kids : Unisex Acc : Default 'Unisex"
A40: Season | B40: =VLOOKUP(A40,MDD!A:B,2,0) -> AT_Season | C40: =VLOOKUP(A40,MDD!A:C,3,0) -> LOV | F40: "MAA SAP Season (Co Dependent with Description) E.g : SP - Spring SM - Summer FW - Fall Winter SS - Spring Summer etc (refer to LOV) | G40: Manual Input
A41: Season Year | B41: =VLOOKUP(A41,MDD!A:B,2,0) -> AT_SeasonYear | C41: =VLOOKUP(A41,MDD!A:C,3,0) -> number | F41: MAA SAP Year | G41: Manual Input
A42: Country of Origin | B42: =VLOOKUP(A42,MDD!A:B,2,0) -> AT_CountryOrigin | C42: =VLOOKUP(A42,MDD!A:C,3,0) -> LOV | F42: "Co Dependent with Description E.g CN - China VN - Vietnam SG - Singapore etc (refer to LOV) | G42: Mapping from Principal | H42: https://mapcoid.sharepoint.com/:x:/r/sites/MAPONESOURCE/_layouts/15/Doc.aspx?sourcedoc=%7B14E04464-7606-43B0-BB40-E5FFA3343822%7D&file=Shipment%20Confirmation%20-%20Early%20Ready%20(Jan%20orders)%20(12122025).xlsx&action=default&mobileredirect=true&or=EXCEL-WEB.BODY.NT&ct=1780996789565 | J42: COO | K42: "FW & Acc Linelist : Column 'COO' (refer to LOV)"
A43: Vendor | B43: =VLOOKUP(A43,MDD!A:B,2,0) -> AT_Vendor | C43: =VLOOKUP(A43,MDD!A:C,3,0) -> LOV | D43: Basic | F43: MAA Vendor code (Co Dependent with description) Format : Country Code - Comp Code - Vendor Code - Vendor Name MY - 0198 - 10303 - CROCS FOOTWEAR (MALAYSIA) SDN BHD ID - 0888 - 6863 - SKECHERS SARL etc (refer to LOV)
A44: Main Vendor Identification | B44: =VLOOKUP(A44,MDD!A:B,2,0) -> AT_MainVendorIdentification | C44: =VLOOKUP(A44,MDD!A:C,3,0) -> text | D44: Basic | F44: to identify priority vendor
A45: Exchange Rate | B45: =VLOOKUP(A45,MDD!A:B,2,0) -> AT_ExchangeRate | C45: =VLOOKUP(A45,MDD!A:C,3,0) -> number | D45: Price | F45: Exchange Rate to Local Currency
A46: Pricing Distribution Channel | B46: =VLOOKUP(A46,MDD!A:B,2,0) -> AT_PricingDistributionChannel | C46: =VLOOKUP(A46,MDD!A:C,3,0) -> LOV | D46: Price | F46: To identify price channel Co Dependent with Description) E.g : 01 - Retailer 02 - Wholesale 03 - E-comm
A47: Retail Price Currency | B47: =VLOOKUP(A47,MDD!A:B,2,0) -> AT_RetailPriceCurrency | C47: =VLOOKUP(A47,MDD!A:C,3,0) -> LOV | G47: Formula in system | K47: "Default by currency per country e.g : IIndonesia (IDR), Philiphine (PHP), etc"
A48: Original Price | B48: =VLOOKUP(A48,MDD!A:B,2,0) -> AT_OriginalPrice | C48: Regular Expression | F48: MAA Original Price
A49: Valid From | F49: Identify pricing valid period
A50: Valid To | F50: Identify pricing valid period Conditional (default as priority 31.12.9999 - editable)
A51: Created on | B51: =VLOOKUP(A51,MDD!A:B,2,0) -> AT_Createdon | C51: =VLOOKUP(A51,MDD!A:C,3,0) -> legacyisodatetime | F51: Identify when the pricing is registered (Maintainance date)
A52: Created by | B52: =VLOOKUP(A52,MDD!A:B,2,0) -> AT_Createdby | C52: =VLOOKUP(A52,MDD!A:C,3,0) -> text | F52: Identify who is registering the pricing (User)
A53: Current price | B53: =VLOOKUP(A53,MDD!A:B,2,0) -> AT_CurrentPrice | C53: =VLOOKUP(A53,MDD!A:C,3,0) -> regexp | F53: MAA Current Price
A54: Valid From | F54: Identify pricing valid period
A55: Valid To | F55: Identify pricing valid period Conditional (default as priority 31.12.9999 - editable)
A56: Created on | B56: =VLOOKUP(A56,MDD!A:B,2,0) -> AT_Createdon | C56: =VLOOKUP(A56,MDD!A:C,3,0) -> legacyisodatetime | F56: Identify when the pricing is registered (Maintainance date)
A57: Created by | B57: =VLOOKUP(A57,MDD!A:B,2,0) -> AT_Createdby | C57: =VLOOKUP(A57,MDD!A:C,3,0) -> text | F57: Identify who is registering the pricing (User)
A58: Discount Bucket | B58: =VLOOKUP(A58,MDD!A:B,2,0) -> AT_DiscountBucket | C58: =VLOOKUP(A58,MDD!A:C,3,0) -> number | F58: Comparison between original vs current price (non-rounded)
A59: Discount Bucket (Rounded) | B59: =VLOOKUP(A59,MDD!A:B,2,0) -> AT_DiscountBucketRounded | C59: =VLOOKUP(A59,MDD!A:C,3,0) -> number | F59: Comparison between original vs current price (rounded)
A60: Estimated Landed Cost | B60: =VLOOKUP(A60,MDD!A:B,2,0) -> AT_EstimatedLandedCost | C60: =VLOOKUP(A60,MDD!A:C,3,0) -> number
A61: FOB | B61: =VLOOKUP(A61,MDD!A:B,2,0) -> AT_FOB | C61: =VLOOKUP(A61,MDD!A:C,3,0) -> regexp | G61: Direct from Principal | H61: S1 26 SEA Line List (SEA) (2).xlsb | J61: SEA MSRP | K61: "FW & Acc Line List : Column 'SEA MSRP' All division : MSRP price - 64.5% Unless Bags : MSRP price - 57%"
A62: FOB Currency | B62: =VLOOKUP(A62,MDD!A:B,2,0) -> AT_FOBCurrency | C62: =VLOOKUP(A62,MDD!A:C,3,0) -> LOV | G62: Formula in system | K62: Default : USD
A63: Freight Cost | B63: =VLOOKUP(A63,MDD!A:B,2,0) -> AT_FreightCost | C63: =VLOOKUP(A63,MDD!A:C,3,0) -> regexp
A64: Royalty | B64: =VLOOKUP(A64,MDD!A:B,2,0) -> AT_Royalty | C64: =VLOOKUP(A64,MDD!A:C,3,0) -> regexp
A65: Royalty Deduction | B65: =VLOOKUP(A65,MDD!A:B,2,0) -> AT_RoyaltyDeduction | C65: =VLOOKUP(A65,MDD!A:C,3,0) -> regexp
A66: Commision | B66: =VLOOKUP(A66,MDD!A:B,2,0) -> #N/A
A67: SGS | B67: =VLOOKUP(A67,MDD!A:B,2,0) -> AT_SGS | C67: =VLOOKUP(A67,MDD!A:C,3,0) -> regexp
A68: Marketing Fee | B68: =VLOOKUP(A68,MDD!A:B,2,0) -> AT_MarketingFee | C68: =VLOOKUP(A68,MDD!A:C,3,0) -> regexp
A69: Haddad Office Charge | B69: =VLOOKUP(A69,MDD!A:B,2,0) -> AT_HaddadOfficeCharge | C69: =VLOOKUP(A69,MDD!A:C,3,0) -> regexp
A70: Haddad Office Charge - Deduction | B70: =VLOOKUP(A70,MDD!A:B,2,0) -> AT_HaddadOfficeChargeDeduction | C70: =VLOOKUP(A70,MDD!A:C,3,0) -> regexp
A71: Safeguard Duty (ID Only) | B71: =VLOOKUP(A71,MDD!A:B,2,0) -> AT_SafeguardDutyIdOnly | C71: =VLOOKUP(A71,MDD!A:C,3,0) -> number
A72: Label Cost | B72: =VLOOKUP(A72,MDD!A:B,2,0) -> AT_LabelCost | C72: =VLOOKUP(A72,MDD!A:C,3,0) -> regexp
A73: Others | B73: =VLOOKUP(A73,MDD!A:B,2,0) -> AT_Others | C73: =VLOOKUP(A73,MDD!A:C,3,0) -> number
A74: MC Structure (Merchandise Category) | B74: =VLOOKUP(A74,MDD!A:B,2,0) -> #N/A | C74: =VLOOKUP(A74,MDD!A:C,3,0) -> #N/A | F74: "Structure : 1 Digits of SAP Product Div + 2 Digits of SAP Product Group + 2 Digits of SAP Product Category + 3 Digits of Brand Code + 1 Digits of SAP Product Flag"
A75: SAP Product Division | B75: =VLOOKUP(A75,MDD!A:B,2,0) -> #N/A | C75: =VLOOKUP(A75,MDD!A:C,3,0) -> #N/A | F75: "Co Dependent with Description E.g : F - Footwear | A - Apparel etc" | G75: Defined from Images | K75: "AI generation Notes : shoe-shaped keychain images should be mapped under accessories not Footwear. Based on line list sheet naming convention is also applicable to define it"
A76: SAP Product Group | B76: =VLOOKUP(A76,MDD!A:B,2,0) -> #N/A | C76: =VLOOKUP(A76,MDD!A:C,3,0) -> #N/A | F76: "Co Dependent with Description) E.g : FS - Lifestyle Shoes | 34 - Sports Shoes etc" | G76: Formula in system Defined from Images | K76: "FW Default : Lifestyle Shoes Acc : Defined from images by AI"
A77: SAP Product Category | B77: =VLOOKUP(A77,MDD!A:B,2,0) -> #N/A | C77: =VLOOKUP(A77,MDD!A:C,3,0) -> #N/A | F77: "Co Dependent with Description E.g : RU - Running | CS - Casual Shoes etc" | G77: Defined from Images | K77: "AI generation Notes : shoe-shaped keychain images should be mapped under accessories not Footwear."
A78: SAP Product Flag | B78: =VLOOKUP(A78,MDD!A:B,2,0) -> AT_SAPProductFlag | C78: =VLOOKUP(A78,MDD!A:C,3,0) -> LOV | F78: "Co Dependent with Description E.g : A - Intercompany 5 - Direct Local 1 - Consignment etc To indicate the bussiness model (Direct, local, intercompany,consignment, non MD) E.g : A - Intercompany | 5 - Direct Local | 1 - Consignment" | G78: Formula in system
A79: Principal Merchandise Hierarchy L1 | B79: =VLOOKUP(A79,MDD!A:B,2,0) -> AT_PrincipalMerchandiseHierarchyL1 | C79: =VLOOKUP(A79,MDD!A:C,3,0) -> text | D79: Hierarchy | F79: Principal Merchandise Hierarchy Level 1 | G79: Direct from Principal | H79: S1 26 SEA Line List (SEA) (2).xlsb | J79: Franchise | K79: "FW & Acc Line List : Column 'Franchise'"
A80: Principal Merchandise Hierarchy L2 | B80: =VLOOKUP(A80,MDD!A:B,2,0) -> AT_PrincipalMerchandiseHierarchyL2 | C80: =VLOOKUP(A80,MDD!A:C,3,0) -> text | D80: Hierarchy | F80: Principal Merchandise Hierarchy Level 2 | G80: Direct from Principal | H80: S1 26 SEA Line List (SEA) (2).xlsb | J80: Sillhoute | K80: "FW & Acc Line List : Column : Sillhoute"
A81: Principal Merchandise Hierarchy L3 | B81: =VLOOKUP(A81,MDD!A:B,2,0) -> AT_PrincipalMerchandiseHierarchyL3 | C81: =VLOOKUP(A81,MDD!A:C,3,0) -> text | D81: Hierarchy | F81: Principal Merchandise Hierarchy Level 3 | G81: Direct from Principal | H81: S1 26 SEA Line List (SEA) (2).xlsb | J81: Product mix | K81: "FW & Acc Line List : Column Product Mix"
A82: Principal Merchandise Hierarchy L4 | B82: =VLOOKUP(A82,MDD!A:B,2,0) -> AT_PrincipalMerchandiseHierarchyL4 | C82: =VLOOKUP(A82,MDD!A:C,3,0) -> text | D82: Hierarchy | F82: Principal Merchandise Hierarchy Level 4 | G82: N/A | J82: N/A
A83: Principal Merchandise Hierarchy L5 | B83: =VLOOKUP(A83,MDD!A:B,2,0) -> AT_PrincipalMerchandiseHierarchyL5 | C83: =VLOOKUP(A83,MDD!A:C,3,0) -> text | D83: Hierarchy | F83: Principal Merchandise Hierarchy Level 5 | G83: N/A | J83: N/A
A84: Material Type | B84: =VLOOKUP(A84,MDD!A:B,2,0) -> AT_MaterialType | C84: =VLOOKUP(A84,MDD!A:C,3,0) -> LOV | F84: Direct/ Intercompany/ etc | G84: Formula in system | K84: Default : Intercompany
A85: Article Category | B85: =VLOOKUP(A85,MDD!A:B,2,0) -> AT_SAPArticleCategory | C85: =VLOOKUP(A85,MDD!A:C,3,0) -> LOV | F85: SAP Article Category to indicate whether the article is single,Generic,etc | G85: Formula in system | K85: "FW : Generic Acc : Single"
A86: Internal Barcode | B86: =VLOOKUP(A86,MDD!A:B,2,0) -> AT_InternalBarcode | C86: =VLOOKUP(A86,MDD!A:C,3,0) -> regexp | E86: Barcode | G86: N/A
A87: Principal Barcode | B87: =VLOOKUP(A87,MDD!A:B,2,0) -> AT_PrincipalBarcode | C87: =VLOOKUP(A87,MDD!A:C,3,0) -> regexp | E87: Barcode | F87: Original Principal Barcode | G87: Direct from Principal
A88: FG Barcode | B88: =VLOOKUP(A88,MDD!A:B,2,0) -> AT_FGBarcode | C88: =VLOOKUP(A88,MDD!A:C,3,0) -> regexp | E88: Barcode | F88: FG Barcode (Only for Sport Direct) | G88: N/A | K88: Under consideration for SDI
A89: Main EAN Indicator | B89: =VLOOKUP(A89,MDD!A:B,2,0) -> AT_MainEANIndicator | C89: =VLOOKUP(A89,MDD!A:C,3,0) -> LOV | E89: Barcode | G89: Formula in system
A90: EAN Category | B90: =VLOOKUP(A90,MDD!A:B,2,0) -> AT_EANCategory | C90: =VLOOKUP(A90,MDD!A:C,3,0) -> LOV | E90: Barcode | G90: Formula in system
A91: Unit of Measurement (UoM) | B91: =VLOOKUP(A91,MDD!A:B,2,0) -> AT_UOM | C91: =VLOOKUP(A91,MDD!A:C,3,0) -> LOV | G91: Formula in system | K91: Default EA
A92: HS Code | B92: =VLOOKUP(A92,MDD!A:B,2,0) -> AT_HSCode | C92: =VLOOKUP(A92,MDD!A:C,3,0) -> text | G92: Manual Input
A93: Nature of Article (NOA) | B93: =VLOOKUP(A93,MDD!A:B,2,0) -> #N/A | G93: Manual Input
A94: Article Type | B94: =VLOOKUP(A94,MDD!A:B,2,0) -> #N/A | F94: Inline/License/SSE | G94: Manual Input | K94: Default : Inline
A95: Thumbnail Image | B95: =VLOOKUP(A95,MDD!A:B,2,0) -> #N/A | G95: Direct from Principal
A96: BY Age | B96: =VLOOKUP(A96,MDD!A:B,2,0) -> AT_BYAge | C96: =VLOOKUP(A96,MDD!A:C,3,0) -> LOV | G96: Mapping from the principal data | H96: S1 26 SEA Line List (SEA) (2).xlsb | J96: Gender | K96: "FW Line list : Column 'Gender' (Mapping) Men : Adults Women : Adults Unisex Adults : Adults Unisex Kids : Children Acc : Default 'Adults'"
A97: BY Gender | B97: =VLOOKUP(A97,MDD!A:B,2,0) -> AT_BYGender | C97: =VLOOKUP(A97,MDD!A:C,3,0) -> LOV | E97: Gender | G97: Mapping from the principal data | H97: S1 26 SEA Line List (SEA) (2).xlsb | J97: Gender | K97: "FW Line list : Column 'Gender' (Mapping) Men : Male Women : Female Unisex Adults : Unisex Unisex Kids : Unisex Acc : Default 'Unisex"
A98: BCI | B98: =VLOOKUP(A98,MDD!A:B,2,0) -> AT_BCI | C98: =VLOOKUP(A98,MDD!A:C,3,0) -> LOV | G98: Manual Input
A99: BY Color Group | B99: =VLOOKUP(A99,MDD!A:B,2,0) -> #N/A | F99: 6 Color Group | G99: Formula in system | K99: "AI generation FW : Mapping from BY Standardized Color Acc : Default 'Multi'"
A100: BY Standardized Color | B100: =VLOOKUP(A100,MDD!A:B,2,0) -> #N/A | F100: 53 Color Description | G100: Defined from Images | K100: "AI generation FW : Defined from Image by AI Acc : Default 'Multi'"
A101: Price Range | B101: =VLOOKUP(A101,MDD!A:B,2,0) -> AT_PriceRange | C101: =VLOOKUP(A101,MDD!A:C,3,0) -> LOV | G101: Formula in system | K101: Price range : based on suggested retail price calculated by Stibo and mapping to LOV BY price range
...

Sheet Crocs(Inline)-NEW
A2: Stibo Attribute | B2: Stibo Attribute ID | C2: Stibo Validation | D2: Cluster | E2: Grouping | F2: Attributes Description | G2: Field Mapping Type | H2: Brand File Name & Link | I2: Brand File Sheet Name | J2: Field Name in the Brand File | K2: Mapping Logic | L2: Mapping file for additional Brand specific mapping
A3: Country | B3: =VLOOKUP(A3,MDD!A:B,2,0) -> AT_Country | C3: LOV | F3: "Co Dependent with Description E.g : ID - Indonesia PH - Philiphine TH - Thailand SG - Singapore MY - Malaysia VN - Vietnam KH : Cambodia" | G3: Manual Input
A4: Company | B4: =VLOOKUP(A4,MDD!A:B,2,0) -> AT_CompanyCode | C4: LOV | F4: "Co Dependent with Description 0888 - PT. Map Aktif Adiperkasa 0886 - PT. MAP FTL Adiperkasa 0882 - Magna Management Asia etc (Refer to LOV)" | G4: Manual Input
A5: SBU | B5: =VLOOKUP(A5,MDD!A:B,2,0) -> AT_SBU | C5: LOV | F5: "Co Dependent with Description E.g SP - Sports FQ - Footlocker Etc (refer to LOV)" | G5: Manual Input
A6: Brand | B6: =VLOOKUP(A6,MDD!A:B,2,0) -> AT_Brand | C6: LOV | F6: "Co Dependent with Description E.g ADI - Adidas NIK - Nike NEW - New Balance Etc (refer to LOV)" | G6: Manual Input
A7: Brand Group | B7: =VLOOKUP(A7,MDD!A:B,2,0) -> AT_BrandGroup | C7: LOV | F7: Multiple brand codes that managed under 1 brand group e.g. Adidas, Lego, Hasbro | G7: Formula in system
A8: Brand Type | B8: =VLOOKUP(A8,MDD!A:B,2,0) -> AT_BrandType | C8: LOV | F8: Whether a brand act as a retailer, selling directly to customers (MAA brands, SDI brands) or as a distributor (Non-MAA brands, Non-SDI brands) | G8: Formula in system
A9: Brand Category | B9: =VLOOKUP(A9,MDD!A:B,2,0) -> AT_BrandCategory | C9: LOV | F9: Group of brands that classified based on their performance/ contribution e.g. Top brands, Selected brands, Non-Top brands | G9: Formula in system
A10: Brand Status | B10: =VLOOKUP(A10,MDD!A:B,2,0) -> AT_BrandStatus | C10: =VLOOKUP(A10,MDD!A:C,3,0) -> LOV | F10: Indicating whether the brands is actively being sold or, no longer continued or exit the market (Active/Discontinue) | G10: Formula in system
A11: BY Indicator | B11: =VLOOKUP(A11,MDD!A:B,2,0) -> AT_BYIndicator | C11: =VLOOKUP(A11,MDD!A:C,3,0) -> LOV | F11: Article to be ordered | G11: Formula in system
A12: SAP Indicator | B12: =VLOOKUP(A12,MDD!A:B,2,0) -> AT_SAPIndicator | C12: =VLOOKUP(A12,MDD!A:C,3,0) -> LOV | F12: Article has been created | G12: Formula in system
A13: Ecom Indicator | B13: =VLOOKUP(A13,MDD!A:B,2,0) -> AT_EcomIndicator | C13: =VLOOKUP(A13,MDD!A:C,3,0) -> LOV | F13: Article to be Publish at Online Sales Channel | G13: Manual Input
A14: Principal Style Code | B14: =VLOOKUP(A14,MDD!A:B,2,0) -> AT_PrincipalStyleCode | C14: Text | F14: Original Principal Code | G14: Direct from Principal | H14: H1 27 SEA Line List - SEA (5.15).xlsx | I14: all sheet should be loaded FTW : Footwear Charms : Accessories (jibbitz) ACC | J14: FW & ACC : Colorway Code Charms : Style Code | K14: FW & ACC : Colorway Code Charms : Style Code
A15: Principal Style Description | B15: =VLOOKUP(A15,MDD!A:B,2,0) -> AT_PrincipalStyleDescription | C15: Text | E15: Description | F15: Original Principal Product Name | G15: Direct from Principal | H15: H1 27 SEA Line List - SEA (5.15).xlsx | I15: all sheet should be loaded FTW : Footwear Charms : Accessories (jibbitz) ACC | J15: Style | K15: "FW & Acc Line List : Column 'Style' "
A16: Principal Color Code | B16: =VLOOKUP(A16,MDD!A:B,2,0) -> AT_PrincipalColorCode | C16: Text | E16: Color | F16: Original Principal Color | G16: Formula in system | H16: H1 27 SEA Line List - SEA (5.15).xlsx | I16: all sheet should be loaded FTW : Footwear Charms : Accessories (jibbitz) ACC | J16: FW & Acc : Colorway Code Charms : N/A | K16: "FW & Acc Line List : Column 'Colorway Code' (put the last 3 digits)" Charms :N/A
A17: Principal Color Description | B17: =VLOOKUP(A17,MDD!A:B,2,0) -> AT_PrincipalColorName | C17: Text | E17: Color | F17: Original Principal Color Description | G17: Direct from Principal | H17: H1 27 SEA Line List - SEA (5.15).xlsx | I17: all sheet should be loaded FTW : Footwear Charms : Accessories (jibbitz) ACC | J17: FW & Acc : Colorway Charms: N/A | K17: FW & Acc : Colorway Charms: N/A
A18: Principal Gender Code | B18: =VLOOKUP(A18,MDD!A:B,2,0) -> AT_PrincipalGenderCode | E18: Gender | F18: Original Principal Gender | G18: N/A | I18: all sheet should be loaded FTW : Footwear Charms : Accessories (jibbitz) ACC
A19: Principal Gender Description | B19: =VLOOKUP(A19,MDD!A:B,2,0) -> AT_PrincipalGenderDescription | E19: Gender | F19: Original Principal Gender Description | G19: Direct from Principal | H19: H1 27 SEA Line List - SEA (5.15).xlsx | I19: all sheet should be loaded FTW : Footwear Charms : Accessories (jibbitz) ACC | J19: FW & Acc : Gender Charms : N/A | K19: FW & Acc : Gender Charms : N/A
A20: Principal Age Code | B20: =VLOOKUP(A20,MDD!A:B,2,0) -> AT_PrincipalAgeCode | E20: Age | F20: Original Principal Age | G20: N/A | I20: all sheet should be loaded FTW : Footwear Charms : Accessories (jibbitz) ACC
A21: Principal Age Description | B21: =VLOOKUP(A21,MDD!A:B,2,0) -> AT_PrincipalAgeDescription | E21: Age | F21: Original Principal Age Description | G21: N/A | I21: all sheet should be loaded FTW : Footwear Charms : Accessories (jibbitz) ACC
A22: Principal Size Code | B22: AT_PrincipalStyleCode | E22: Sizing | F22: Original Size from Principal (co-dependent with description) | G22: Direct from Principal | H22: H1 27 SEA Line List - SEA (5.15).xlsx | I22: all sheet should be loaded FTW : Footwear Charms : Accessories (jibbitz) ACC | J22: Size Range (Colorway) | K22: FW & Acc_x000D_ Line list : Column 'Size Range' (Colorway)
A23: SAP Style Code | B23: =VLOOKUP(A23,MDD!A:B,2,0) -> AT_SAPStyleCode | F23: Adjusted principal style code that has been map to SAP generic (without brand code) | G23: Mapping from Principal | H23: H1 27 SEA Line List - SEA (5.15).xlsx | I23: all sheet should be loaded FTW : Footwear Charms : Accessories (jibbitz) ACC | J23: FW & Acc : Colorway Code Charms : Style | K23: FW & Acc & Charms : Type B.1 (generic without brand code)
A24: Generic | B24: =VLOOKUP(A24,MDD!A:B,2,0) -> AT_Generic | F24: MAA Generic Code (Max 12 Digits - 3 Digits brand code + 9 Digits Principal Style) | G24: Mapping from Principal | H24: H1 27 SEA Line List - SEA (5.15).xlsx | I24: all sheet should be loaded FTW : Footwear Charms : Accessories (jibbitz) ACC | J24: FW & Acc : Colorway Code Charms : Style | K24: FW & Acc & Charms : Type B.1 (generic without brand code)
A25: Generic Description | B25: =VLOOKUP(A25,MDD!A:B,2,0) -> AT_GenericDescription | E25: Description | F25: MAA Generic Description Mapping (Max 40 Digits - 3 Digits brand code + Principal style + (Age/Gender) + Color | G25: Mapping from Principal | K25: MAA Generic Description Mapping (Max 40 Digits - 3 Digits brand code + Principal style + (Age/Gender) + Color
A26: Variant | B26: =VLOOKUP(A26,MDD!A:B,2,0) -> AT_Variant | F26: MAA Article Code (Max 18 Digits - Generic code + 3 Digits MAA / SAP Color (103 color guidance) + 3 Digits MAA size code mapping | G26: Mapping from Principal | K26: "FW & Acc 3 Digits Brand Code + Max 9 DIgits Principal Style Code + 3 digits SAP Color code + 3 digits Size code"
A27: Variant Description | B27: =VLOOKUP(A27,MDD!A:B,2,0) -> AT_VariantDescription | E27: Description | F27: MAA Generic Description Mapping (Max 40 Digits - 3 Digits brand code + Principal style + (Age/Gender) + Color + Size | G27: Mapping from Principal | K27: "FW & Acc MAA Generic Description Mapping (Max 40 Digits - 3 Digits brand code + Principal style + (Age/Gender) + Color + Size Shorten: Classic -Cls/Cs, Clog - Clg/Cg Platform - Pltfrm, Sandal-Sndl (have no fix mapping for shorten the desc) Jibbitz - Jbz, 5 Pack-5P/5Pck"
A28: SAP Color | B28: =VLOOKUP(A28,MDD!A:B,2,0) -> AT_Color | E28: Color | F28: MAA 103 Basic SAP Color Code & Description | G28: Defined from Images | K28: "FW :Defined from Images by AI Acc : Define by AI Default 'No color' Acc - Bag : Defined from Images by AI "
A29: SAP Size | B29: =VLOOKUP(A29,MDD!A:B,2,0) -> AT_Size | E29: Sizing | F29: MAA SAP Size Code & Description | G29: Mapping from Principal | J29: Size Range | K29: "FW : Line list : Size Range (refer to LOV) Acc Bags : Default 'No Size'"
A30: Created on | B30: =VLOOKUP(A30,MDD!A:B,2,0) -> AT_Createdon | C30: =VLOOKUP(A30,MDD!A:C,3,0) -> legacyisodatetime | D30: Basic | F30: When is the creation date | G30: Formula in system
A31: Created by | B31: =VLOOKUP(A31,MDD!A:B,2,0) -> AT_Createdby | C31: =VLOOKUP(A31,MDD!A:C,3,0) -> text | D31: Basic | F31: Who is creating the articles | G31: Formula in system
A32: Musical Box Article Code | B32: =VLOOKUP(A32,MDD!A:B,2,0) -> AT_MusicalBoxArticleCode | C32: =VLOOKUP(A32,MDD!A:C,3,0) -> text | F32: MAA Musical Box Code (Max 18 Digits - 3 Digits brand code + 3 digits of MB- +9 digits of SAP Style Code + 3 Digits Assortment Code)
A33: MB Style code | B33: =VLOOKUP(A33,MDD!A:B,2,0) -> AT_MBStyleCode | C33: =VLOOKUP(A33,MDD!A:C,3,0) -> text | F33: Max 12 digits MB Style (MB- + SAP Style Code )
A34: MB Assortment Code | B34: =VLOOKUP(A34,MDD!A:B,2,0) -> AT_MBAssortmentCode | C34: =VLOOKUP(A34,MDD!A:C,3,0) -> LOV | F34: 3 Digits Assortment code (based on matrix of qty per sizes)
A35: Musical Box Article Description | B35: =VLOOKUP(A35,MDD!A:B,2,0) -> AT_MusicalBoxArticleDescription | C35: =VLOOKUP(A35,MDD!A:C,3,0) -> text | F35: MAA Musical Box Description Mapping (Max 40 Digits - 3 Digits brand code + Principal style + (Age/Gender) + Color + (-MB)
A36: Musical Box Components Qty | B36: =VLOOKUP(A36,MDD!A:B,2,0) -> AT_MusicalBoxComponentsQty | C36: =VLOOKUP(A36,MDD!A:C,3,0) -> LOV | F36: Components qty of Musical Box Articles : Breakdown qty per sizes
A37: Musical Box UOM | B37: =VLOOKUP(A37,MDD!A:B,2,0) -> AT_MusicalBoxUOM | C37: =VLOOKUP(A37,MDD!A:C,3,0) -> LOV | F37: UOM for Musical Box (Default : CAR) | G37: Formula in system | K37: default 'CAR'
A38: SAP Age | B38: =VLOOKUP(A38,MDD!A:B,2,0) -> AT_SAPAge | C38: =VLOOKUP(A38,MDD!A:C,3,0) -> LOV | E38: Age | F38: "MAA SAP Age (Co - Dependent with Description) E.g : CH - Children AA - All Ages AD - Adults" | G38: Mapping from Principal | H38: H1 27 SEA Line List - SEA (5.15).xlsx | I38: all sheet should be loaded FTW : Footwear Charms : Accessories (jibbitz) ACC | J38: Gender | K38: "FW Line list : Column 'Gender' (Mapping) Men : Adults Women : Adults Unisex Adults : Adults Unisex Kids : Children Acc & Charms : Default 'Adults'"
A39: SAP Gender | B39: =VLOOKUP(A39,MDD!A:B,2,0) -> AT_Gender | C39: =VLOOKUP(A39,MDD!A:C,3,0) -> LOV | E39: Gender | F39: "MAA SAP Gender (co dependent with description) E.g : M - Male F - Female U - Unisex" | G39: Mapping from Principal | H39: H1 27 SEA Line List - SEA (5.15).xlsx | I39: all sheet should be loaded FTW : Footwear Charms : Accessories (jibbitz) ACC | J39: Gender | K39: "FW Line list : Column 'Gender' (Mapping) Men : Male Women : Female Unisex Adults : Unisex Unisex Kids : Unisex Acc & Charms : Default 'Unisex"
A40: Season | B40: =VLOOKUP(A40,MDD!A:B,2,0) -> AT_Season | C40: =VLOOKUP(A40,MDD!A:C,3,0) -> LOV | F40: "MAA SAP Season (Co Dependent with Description) E.g : SP - Spring SM - Summer FW - Fall Winter SS - Spring Summer etc (refer to LOV) | G40: Manual Input
A41: Season Year | B41: =VLOOKUP(A41,MDD!A:B,2,0) -> AT_SeasonYear | C41: =VLOOKUP(A41,MDD!A:C,3,0) -> number | F41: MAA SAP Year | G41: Manual Input
A42: Country of Origin | B42: =VLOOKUP(A42,MDD!A:B,2,0) -> AT_CountryOrigin | C42: =VLOOKUP(A42,MDD!A:C,3,0) -> LOV | F42: "Co Dependent with Description E.g CN - China VN - Vietnam SG - Singapore etc (refer to LOV) | G42: Mapping from Principal | H42: H1 27 SEA Line List - SEA (5.15).xlsx | I42: all sheet should be loaded FTW : Footwear Charms : Accessories (jibbitz) ACC | J42: COO | K42: "FW & Acc Linelist : Column 'COO' (refer to LOV)"
A43: Vendor | B43: =VLOOKUP(A43,MDD!A:B,2,0) -> AT_Vendor | C43: =VLOOKUP(A43,MDD!A:C,3,0) -> LOV | D43: Basic | F43: MAA Vendor code (Co Dependent with description) Format : Country Code - Comp Code - Vendor Code - Vendor Name MY - 0198 - 10303 - CROCS FOOTWEAR (MALAYSIA) SDN BHD ID - 0888 - 6863 - SKECHERS SARL etc (refer to LOV)
A44: Main Vendor Identification | B44: =VLOOKUP(A44,MDD!A:B,2,0) -> AT_MainVendorIdentification | C44: =VLOOKUP(A44,MDD!A:C,3,0) -> text | D44: Basic | F44: to identify priority vendor
A45: Exchange Rate | B45: =VLOOKUP(A45,MDD!A:B,2,0) -> AT_ExchangeRate | C45: =VLOOKUP(A45,MDD!A:C,3,0) -> number | D45: Price | F45: Exchange Rate to Local Currency
A46: Pricing Distribution Channel | B46: =VLOOKUP(A46,MDD!A:B,2,0) -> AT_PricingDistributionChannel | C46: =VLOOKUP(A46,MDD!A:C,3,0) -> LOV | D46: Price | F46: To identify price channel Co Dependent with Description) E.g : 01 - Retailer 02 - Wholesale 03 - E-comm | G46: Formula in system | K46: Default: Retailer
A47: Retail Price Currency | B47: =VLOOKUP(A47,MDD!A:B,2,0) -> AT_RetailPriceCurrency | C47: =VLOOKUP(A47,MDD!A:C,3,0) -> LOV | G47: Formula in system | K47: "Default by currency per country e.g : IIndonesia (IDR), Philiphine (PHP), etc"
A48: Original Price | B48: =VLOOKUP(A48,MDD!A:B,2,0) -> AT_OriginalPrice | C48: Regular Expression | F48: MAA Original Price
A49: Valid From | F49: Identify pricing valid period
A50: Valid To | F50: Identify pricing valid period Conditional (default as priority 31.12.9999 - editable)
A51: Created on | B51: =VLOOKUP(A51,MDD!A:B,2,0) -> AT_Createdon | C51: =VLOOKUP(A51,MDD!A:C,3,0) -> legacyisodatetime | F51: Identify when the pricing is registered (Maintainance date)
A52: Created by | B52: =VLOOKUP(A52,MDD!A:B,2,0) -> AT_Createdby | C52: =VLOOKUP(A52,MDD!A:C,3,0) -> text | F52: Identify who is registering the pricing (User)
A53: Current price | B53: =VLOOKUP(A53,MDD!A:B,2,0) -> AT_CurrentPrice | C53: =VLOOKUP(A53,MDD!A:C,3,0) -> regexp | F53: MAA Current Price
A54: Valid From | F54: Identify pricing valid period
A55: Valid To | F55: Identify pricing valid period Conditional (default as priority 31.12.9999 - editable)
A56: Created on | B56: =VLOOKUP(A56,MDD!A:B,2,0) -> AT_Createdon | C56: =VLOOKUP(A56,MDD!A:C,3,0) -> legacyisodatetime | F56: Identify when the pricing is registered (Maintainance date)
A57: Created by | B57: =VLOOKUP(A57,MDD!A:B,2,0) -> AT_Createdby | C57: =VLOOKUP(A57,MDD!A:C,3,0) -> text | F57: Identify who is registering the pricing (User)
A58: Discount Bucket | B58: =VLOOKUP(A58,MDD!A:B,2,0) -> AT_DiscountBucket | C58: =VLOOKUP(A58,MDD!A:C,3,0) -> number | F58: Comparison between original vs current price (non-rounded)
A59: Discount Bucket (Rounded) | B59: =VLOOKUP(A59,MDD!A:B,2,0) -> AT_DiscountBucketRounded | C59: =VLOOKUP(A59,MDD!A:C,3,0) -> number | F59: Comparison between original vs current price (rounded)
A60: Estimated Landed Cost | B60: =VLOOKUP(A60,MDD!A:B,2,0) -> AT_EstimatedLandedCost | C60: =VLOOKUP(A60,MDD!A:C,3,0) -> number
A61: FOB | B61: =VLOOKUP(A61,MDD!A:B,2,0) -> AT_FOB | C61: =VLOOKUP(A61,MDD!A:C,3,0) -> regexp | G61: Direct from Principal | H61: H1 27 SEA Line List - SEA (5.15).xlsx | I61: FTW : FTW Bags : ACC (exclude BRN & MM) Charms : Charms | J61: SEA MSRP | K61: "FW & Acc Line List : Column 'SEA MSRP' All division : MSRP price - 64.5% Unless Bags : MSRP price - 57%" Notes: FW : Column : Reporting Silhouette (Clog, Flat, Sandal, Shoes becomes Footwear)) Charms & Acc : Reporting Silhouette (Charms : Acc)
A62: FOB Currency | B62: =VLOOKUP(A62,MDD!A:B,2,0) -> AT_FOBCurrency | C62: =VLOOKUP(A62,MDD!A:C,3,0) -> LOV | G62: Formula in system | K62: Default : USD
A63: Freight Cost | B63: =VLOOKUP(A63,MDD!A:B,2,0) -> AT_FreightCost | C63: =VLOOKUP(A63,MDD!A:C,3,0) -> regexp
A64: Royalty | B64: =VLOOKUP(A64,MDD!A:B,2,0) -> AT_Royalty | C64: =VLOOKUP(A64,MDD!A:C,3,0) -> regexp
A65: Royalty Deduction | B65: =VLOOKUP(A65,MDD!A:B,2,0) -> AT_RoyaltyDeduction | C65: =VLOOKUP(A65,MDD!A:C,3,0) -> regexp
A66: Commision | B66: =VLOOKUP(A66,MDD!A:B,2,0) -> #N/A
A67: SGS | B67: =VLOOKUP(A67,MDD!A:B,2,0) -> AT_SGS | C67: =VLOOKUP(A67,MDD!A:C,3,0) -> regexp
A68: Marketing Fee | B68: =VLOOKUP(A68,MDD!A:B,2,0) -> AT_MarketingFee | C68: =VLOOKUP(A68,MDD!A:C,3,0) -> regexp
A69: Haddad Office Charge | B69: =VLOOKUP(A69,MDD!A:B,2,0) -> AT_HaddadOfficeCharge | C69: =VLOOKUP(A69,MDD!A:C,3,0) -> regexp
A70: Haddad Office Charge - Deduction | B70: =VLOOKUP(A70,MDD!A:B,2,0) -> AT_HaddadOfficeChargeDeduction | C70: =VLOOKUP(A70,MDD!A:C,3,0) -> regexp
A71: Safeguard Duty (ID Only) | B71: =VLOOKUP(A71,MDD!A:B,2,0) -> AT_SafeguardDutyIdOnly | C71: =VLOOKUP(A71,MDD!A:C,3,0) -> number
A72: Label Cost | B72: =VLOOKUP(A72,MDD!A:B,2,0) -> AT_LabelCost | C72: =VLOOKUP(A72,MDD!A:C,3,0) -> regexp
A73: Others | B73: =VLOOKUP(A73,MDD!A:B,2,0) -> AT_Others | C73: =VLOOKUP(A73,MDD!A:C,3,0) -> number
A74: MC Structure (Merchandise Category) | B74: =VLOOKUP(A74,MDD!A:B,2,0) -> #N/A | C74: =VLOOKUP(A74,MDD!A:C,3,0) -> #N/A | F74: "Structure : 1 Digits of SAP Product Div + 2 Digits of SAP Product Group + 2 Digits of SAP Product Category + 3 Digits of Brand Code + 1 Digits of SAP Product Flag"
A75: SAP Product Division | B75: =VLOOKUP(A75,MDD!A:B,2,0) -> #N/A | C75: =VLOOKUP(A75,MDD!A:C,3,0) -> #N/A | F75: "Co Dependent with Description E.g : F - Footwear | A - Apparel etc" | G75: Mapping from Principal | K75: based on sheet name Notes: FW : Column : Reporting Silhouette (Clog, Flat, Sandal, Shoes becomes Footwear)) Charms & Acc : Reporting Silhouette (Charms : Acc)
A76: SAP Product Group | B76: =VLOOKUP(A76,MDD!A:B,2,0) -> #N/A | C76: =VLOOKUP(A76,MDD!A:C,3,0) -> #N/A | F76: "Co Dependent with Description) E.g : FS - Lifestyle Shoes | 34 - Sports Shoes etc" | G76: Formula in system Defined from Images | H76: H1 27 SEA Line List - SEA (5.15).xlsx | J76: Image | K76: "FW Default : Lifestyle Shoes Acc : Defined from images by AI"
A77: SAP Product Category | B77: =VLOOKUP(A77,MDD!A:B,2,0) -> #N/A | C77: =VLOOKUP(A77,MDD!A:C,3,0) -> #N/A | F77: "Co Dependent with Description E.g : RU - Running | CS - Casual Shoes etc" | G77: Defined from Images | H77: H1 27 SEA Line List - SEA (5.15).xlsx | J77: Image | K77: "AI generation Notes : shoe-shaped keychain images should be mapped under accessories not Footwear."
A78: SAP Product Flag | B78: =VLOOKUP(A78,MDD!A:B,2,0) -> AT_SAPProductFlag | C78: =VLOOKUP(A78,MDD!A:C,3,0) -> LOV | F78: "Co Dependent with Description E.g : A - Intercompany 5 - Direct Local 1 - Consignment etc To indicate the bussiness model (Direct, local, intercompany,consignment, non MD) E.g : A - Intercompany | 5 - Direct Local | 1 - Consignment" | G78: Formula in system | K78: Default :A - intercompany
A79: Principal Merchandise Hierarchy L1 | B79: =VLOOKUP(A79,MDD!A:B,2,0) -> AT_PrincipalMerchandiseHierarchyL1 | C79: =VLOOKUP(A79,MDD!A:C,3,0) -> text | D79: Hierarchy | F79: Principal Merchandise Hierarchy Level 1 | G79: Direct from Principal | H79: H1 27 SEA Line List - SEA (5.15).xlsx | J79: All : Franchise | K79: "FW & Acc & Charms Line List : Column 'Franchise'"
A80: Principal Merchandise Hierarchy L2 | B80: =VLOOKUP(A80,MDD!A:B,2,0) -> AT_PrincipalMerchandiseHierarchyL2 | C80: =VLOOKUP(A80,MDD!A:C,3,0) -> text | D80: Hierarchy | F80: Principal Merchandise Hierarchy Level 2 | G80: Direct from Principal | H80: H1 27 SEA Line List - SEA (5.15).xlsx | J80: FW & Acc: Sillhoute Charms : Reporting Silhouette | K80: FW & Acc: Sillhoute Charms : Reporting Silhouette
A81: Principal Merchandise Hierarchy L3 | B81: =VLOOKUP(A81,MDD!A:B,2,0) -> AT_PrincipalMerchandiseHierarchyL3 | C81: =VLOOKUP(A81,MDD!A:C,3,0) -> text | D81: Hierarchy | F81: Principal Merchandise Hierarchy Level 3 | G81: Direct from Principal | H81: H1 27 SEA Line List - SEA (5.15).xlsx | J81: FW & Acc :Product Mix Charms : N/A | K81: FW & Acc :Product Mix Charms : N/A
A82: Principal Merchandise Hierarchy L4 | B82: =VLOOKUP(A82,MDD!A:B,2,0) -> AT_PrincipalMerchandiseHierarchyL4 | C82: =VLOOKUP(A82,MDD!A:C,3,0) -> text | D82: Hierarchy | F82: Principal Merchandise Hierarchy Level 4 | G82: N/A | J82: N/A
A83: Principal Merchandise Hierarchy L5 | B83: =VLOOKUP(A83,MDD!A:B,2,0) -> AT_PrincipalMerchandiseHierarchyL5 | C83: =VLOOKUP(A83,MDD!A:C,3,0) -> text | D83: Hierarchy | F83: Principal Merchandise Hierarchy Level 5 | G83: N/A | J83: N/A
A84: Material Type | B84: =VLOOKUP(A84,MDD!A:B,2,0) -> AT_MaterialType | C84: =VLOOKUP(A84,MDD!A:C,3,0) -> LOV | F84: Direct/ Intercompany/ etc | G84: Formula in system | K84: Default : Intercompany
A85: Article Category | B85: =VLOOKUP(A85,MDD!A:B,2,0) -> AT_SAPArticleCategory | C85: =VLOOKUP(A85,MDD!A:C,3,0) -> LOV | F85: SAP Article Category to indicate whether the article is single,Generic,etc | G85: Formula in system | K85: "FW : Generic Acc : Single"
A86: Internal Barcode | B86: =VLOOKUP(A86,MDD!A:B,2,0) -> AT_InternalBarcode | C86: =VLOOKUP(A86,MDD!A:C,3,0) -> regexp | E86: Barcode | G86: N/A
A87: Principal Barcode | B87: =VLOOKUP(A87,MDD!A:B,2,0) -> AT_PrincipalBarcode | C87: =VLOOKUP(A87,MDD!A:C,3,0) -> regexp | E87: Barcode | F87: Original Principal Barcode | G87: Direct from Principal | H87: Shipment Confirmation - Early Ready (Jan orders) (12122025).xlsx Order form FW https://mapcoid.sharepoint.com/:x:/r/sites/MAPONESOURCE/_layouts/15/Doc.aspx?sourcedoc=%7B13BB9B83-7BB2-4D03-A468-5070DA30737C%7D&file=FW%20Order%20Form.xlsx&action=default&mobileredirect=true Jibbitz https://mapcoid.sharepoint.com/:x:/r/sites/MAPONESOURCE/_layouts/15/Doc.aspx?sourcedoc=%7B863E49C8-EF58-4195-AE99-40AACBF178B9%7D&file=JBZ%20Order%20form.xlsx&action=default&mobileredirect=true ACC https://mapcoid.sharepoint.com/:x:/r/sites/MAPONESOURCE/_layouts/15/Doc.aspx?sourcedoc=%7B3BDEB950-B8F4-4FC4-89AD-34DBDE9224AA%7D&file=ACCs%20BAG%20Order%20Form.xlsx&action=default&mobileredirect=true | I87: Shipment Order : DEtails Order Form FW : Sheet All Sheet "SP,WHS,KS" exclude : Total Charms : Sheet All Sheet "SP,WHS,KS" exclude : Total Accs Bag: Sheet All Sheet "Accs Bags) exclude : Total | J87: Shipment Order Principal style code : Material Sizes : 'Grid Value' Barcode : UPC Notes : Charms will not be having sizes - one style is assigned for one sizes (sizing SAP will be "000-No Size") Order Form FW Principal style code : Style Sizes : Size Barcode : UPC [Column (I)] Order Form Charms Principal style code : Style Barcode : UPC [Column (I)] Notes : Charms will not be having sizes - one style is assigned for one sizes (sizing SAP will be "000-No Size") Order Form Accs Bag Principal style code : Style Sizes : Size Barcode : UPC
A88: FG Barcode | B88: =VLOOKUP(A88,MDD!A:B,2,0) -> AT_FGBarcode | C88: =VLOOKUP(A88,MDD!A:C,3,0) -> regexp | E88: Barcode | F88: FG Barcode (Only for Sport Direct) | G88: N/A | K88: Under consideration for SDI
A89: Main EAN Indicator | B89: =VLOOKUP(A89,MDD!A:B,2,0) -> AT_MainEANIndicator | C89: =VLOOKUP(A89,MDD!A:C,3,0) -> LOV | E89: Barcode | G89: Formula in system
A90: EAN Category | B90: =VLOOKUP(A90,MDD!A:B,2,0) -> AT_EANCategory | C90: =VLOOKUP(A90,MDD!A:C,3,0) -> LOV | E90: Barcode | G90: Formula in system
A91: Unit of Measurement (UoM) | B91: =VLOOKUP(A91,MDD!A:B,2,0) -> AT_UOM | C91: =VLOOKUP(A91,MDD!A:C,3,0) -> LOV | G91: Formula in system | K91: Default EA
A92: HS Code | B92: =VLOOKUP(A92,MDD!A:B,2,0) -> AT_HSCode | C92: =VLOOKUP(A92,MDD!A:C,3,0) -> text | G92: Manual Input
A93: Nature of Article (NOA) | B93: =VLOOKUP(A93,MDD!A:B,2,0) -> #N/A | G93: Manual Input
A94: Article Type | B94: =VLOOKUP(A94,MDD!A:B,2,0) -> #N/A | F94: Inline/License/SSE | G94: Manual Input | K94: Default : Inline
A95: Thumbnail Image | B95: =VLOOKUP(A95,MDD!A:B,2,0) -> #N/A | G95: Direct from Principal | H95: H1 27 SEA Line List - SEA (5.15).xlsx | J95: Image
A96: BY Age | B96: =VLOOKUP(A96,MDD!A:B,2,0) -> AT_BYAge | C96: =VLOOKUP(A96,MDD!A:C,3,0) -> LOV | G96: Mapping from the principal data | H96: H1 27 SEA Line List - SEA (5.15).xlsx | J96: Gender | K96: "FW Line list : Column 'Gender' (Mapping) Men : Adults Women : Adults Unisex Adults : Adults Unisex Kids : Children Acc & Charms : Default 'Adult'"
A97: BY Gender | B97: =VLOOKUP(A97,MDD!A:B,2,0) -> AT_BYGender | C97: =VLOOKUP(A97,MDD!A:C,3,0) -> LOV | E97: Gender | G97: Mapping from the principal data | H97: H1 27 SEA Line List - SEA (5.15).xlsx | J97: Gender | K97: "FW Line list : Column 'Gender' (Mapping) Men : Male Women : Female Unisex Adults : Unisex Unisex Kids : Unisex Acc & Charms : Default 'Unisex"
A98: BCI | B98: =VLOOKUP(A98,MDD!A:B,2,0) -> AT_BCI | C98: =VLOOKUP(A98,MDD!A:C,3,0) -> LOV | G98: Manual Input
A99: BY Color Group | B99: =VLOOKUP(A99,MDD!A:B,2,0) -> #N/A | F99: 6 Color Group | G99: Formula in system | K99: "AI generation FW : Mapping from BY Standardized Color Acc : Default 'Multi'"
A100: BY Standardized Color | B100: =VLOOKUP(A100,MDD!A:B,2,0) -> #N/A | F100: 53 Color Description | G100: Defined from Images | K100: "AI generation FW : Defined from Image by AI Acc : Default 'Multi'"
A101: Price Range | B101: =VLOOKUP(A101,MDD!A:B,2,0) -> AT_PriceRange | C101: =VLOOKUP(A101,MDD!A:C,3,0) -> LOV | G101: Formula in system | K101: Price range : based on suggested retail price calculated by Stibo and mapping to LOV BY price range
...

Sheet Lotto(Inline + Lincensed)
A1: Stibo Attribute | B1: Stibo Attribute ID | C1: Stibo Validation | D1: Cluster | E1: Grouping | F1: Attributes Description | G1: Field Mapping Type | H1: Brand File Name & Link | I1: Brand File Sheet Name | J1: Field Name in the Brand File | K1: Mapping Logic | L1: Mapping file for additional Brand specific mapping
A2: Country | B2: =VLOOKUP(A2,MDD!A:B,2,0) -> AT_Country | C2: =VLOOKUP(A2,MDD!A:C,3,0) -> LOV | D2: Basic | F2: Co Dependent with Description E.g : ID - Indonesia PH - Philiphine TH - Thailand SG - Singapore MY - Malaysia VN - Vietnam KH : Cambodia | G2: Manual Input
A3: Company | B3: =VLOOKUP(A3,MDD!A:B,2,0) -> AT_CompanyCode | C3: =VLOOKUP(A3,MDD!A:C,3,0) -> LOV | D3: Basic | F3: Co Dependent with Description 0888 - PT. Map Aktif Adiperkasa 0886 - PT. MAP FTL Adiperkasa 0882 - Magna Management Asia etc (Refer to LOV) | G3: Manual Input
A4: SBU | B4: =VLOOKUP(A4,MDD!A:B,2,0) -> AT_SBU | C4: =VLOOKUP(A4,MDD!A:C,3,0) -> LOV | D4: Basic | F4: Co Dependent with Description E.g SP - Sports FQ - Footlocker Etc (refer to LOV) | G4: Manual Input
A5: Brand | B5: =VLOOKUP(A5,MDD!A:B,2,0) -> AT_Brand | C5: =VLOOKUP(A5,MDD!A:C,3,0) -> LOV | D5: Basic | F5: Co Dependent with Description E.g ADI - Adidas NIK - Nike NEW - New Balance Etc (refer to LOV) | G5: Manual Input
A6: Brand Group | B6: =VLOOKUP(A6,MDD!A:B,2,0) -> AT_BrandGroup | C6: =VLOOKUP(A6,MDD!A:C,3,0) -> LOV | D6: Basic | F6: Multiple brand codes that managed under 1 brand group e.g. Adidas, Lego, Hasbro | G6: Formula in system
A7: Brand Type | B7: =VLOOKUP(A7,MDD!A:B,2,0) -> AT_BrandType | C7: =VLOOKUP(A7,MDD!A:C,3,0) -> LOV | D7: Commercial | F7: Whether a brand act as a retailer, selling directly to customers (MAA brands, SDI brands) or as a distributor (Non-MAA brands, Non-SDI brands) | G7: Formula in system
A8: Brand Category | B8: =VLOOKUP(A8,MDD!A:B,2,0) -> AT_BrandCategory | C8: =VLOOKUP(A8,MDD!A:C,3,0) -> LOV | D8: Commercial | F8: Group of brands that classified based on their performance/ contribution e.g. Top brands, Selected brands, Non-Top brands | G8: Formula in system
A9: Brand Status | B9: =VLOOKUP(A9,MDD!A:B,2,0) -> AT_BrandStatus | C9: =VLOOKUP(A9,MDD!A:C,3,0) -> LOV | D9: Commercial | F9: Indicating whether the brands is actively being sold or, no longer continued or exit the market (Active/Discontinue) | G9: Formula in system
A10: BY Indicator | B10: =VLOOKUP(A10,MDD!A:B,2,0) -> AT_BYIndicator | C10: =VLOOKUP(A10,MDD!A:C,3,0) -> LOV | D10: System indicator | F10: Article to be ordered | G10: Formula in system
A11: SAP Indicator | B11: =VLOOKUP(A11,MDD!A:B,2,0) -> AT_SAPIndicator | C11: =VLOOKUP(A11,MDD!A:C,3,0) -> LOV | D11: System indicator | F11: Article has been created | G11: Formula in system
A12: Ecom Indicator | B12: =VLOOKUP(A12,MDD!A:B,2,0) -> AT_EcomIndicator | C12: =VLOOKUP(A12,MDD!A:C,3,0) -> LOV | D12: System indicator | F12: Article to be Publish at Online Sales Channel | G12: Manual Input
A13: Principal Style Code | B13: =VLOOKUP(A13,MDD!A:B,2,0) -> AT_PrincipalStyleCode | C13: =VLOOKUP(A13,MDD!A:C,3,0) -> text | D13: Basic | F13: Original Principal Code | G13: Direct from Principal | H13: https://mapcoid.sharepoint.com/:x:/r/sites/MAPONESOURCE/_layouts/15/Doc.aspx?sourcedoc=%7BE4C2484E-2B04-4F15-9F0B-2065D59345AB%7D&file=RECAP%20SAMPLE%20DEVELOPMENT%20LOTTO%20SS26%20(2).xlsx&action=default&mobileredirect=true&or=EXCEL-WEB.BODY.NT&ct=1781595179775 | K13: "FW Inline Refer Line list : Style code FW Licensed Refer Recap Sample Development : 'Supp Art# Licence App & Acc :Catalog : refer to designer code"
A14: Principal Style Description | B14: =VLOOKUP(A14,MDD!A:B,2,0) -> AT_PrincipalStyleDescription | C14: =VLOOKUP(A14,MDD!A:C,3,0) -> text | D14: Basic | E14: Description | F14: Original Principal Product Name | G14: Direct from Principal | K14: "FW Inline Refer Line list : Style Description FW, App, Acc Licensed : N/a (SS23 : A, FW23: B, FW26 : H naming person western priority begin with ""H"" for FW26 and it will seqyently per season) - Generated by AI for the principal style description"
A15: Principal Color Code | B15: =VLOOKUP(A15,MDD!A:B,2,0) -> AT_PrincipalColorCode | C15: =VLOOKUP(A15,MDD!A:C,3,0) -> text | D15: Basic | E15: Color | F15: Original Principal Color | G15: Direct from Principal | K15: "FW Inline Refer Line list : Color code FW Licensed : N/a"
A16: Principal Color Description | B16: =VLOOKUP(A16,MDD!A:B,2,0) -> AT_PrincipalColorName | C16: =VLOOKUP(A16,MDD!A:C,3,0) -> text | D16: Basic | E16: Color | F16: Original Principal Color Description | G16: Direct from Principal | H16: https://mapcoid.sharepoint.com/:x:/r/sites/MAPONESOURCE/_layouts/15/Doc.aspx?sourcedoc=%7BE4C2484E-2B04-4F15-9F0B-2065D59345AB%7D&file=RECAP%20SAMPLE%20DEVELOPMENT%20LOTTO%20SS26%20(2).xlsx&action=default&mobileredirect=true&or=EXCEL-WEB.BODY.NT&ct=1781595179775&wdLOR=cD7A20E03-11F8-44A9-BF9D-6E70EB098F00 | K16: "FW Inline Refer Line list : Color FW Licensed Refer Recap Sample Development : Color App & Acc : n/a"
A17: Principal Gender Code | B17: =VLOOKUP(A17,MDD!A:B,2,0) -> AT_PrincipalGenderCode | C17: =VLOOKUP(A17,MDD!A:C,3,0) -> text | D17: Basic | E17: Gender | F17: Original Principal Gender | G17: N/A
A18: Principal Gender Description | B18: =VLOOKUP(A18,MDD!A:B,2,0) -> AT_PrincipalGenderDescription | C18: =VLOOKUP(A18,MDD!A:C,3,0) -> text | D18: Basic | E18: Gender | F18: Original Principal Gender Description | G18: Direct from Principal | H18: https://mapcoid.sharepoint.com/:x:/r/sites/MAPONESOURCE/_layouts/15/doc2.aspx?sourcedoc=%7BD6094834-FFE0-447C-8CCC-14FB959CBC16%7D&file=Attributes%20List_complete_v6_25032026.xlsx&action=default&mobileredirect=true&isSPOFile=1&ovuser=ab852023-79a1-4526-8dc1-e853ef901b75%2Csrishti.b%40ducoconsultancy.com&wdExp=TEAMS-TREATMENT&web=1&TeamsCID=a3a0b74a-c756-46ea-8416-08a12f66ec45&clickparams=eyJBcHBOYW1lIjoiVGVhbXMtRGVza3RvcCIsIkFwcFZlcnNpb24iOiI0OS8yNjA1MTQxNjcxMyJ9&linkOpenTime=1780991606851 | K18: "FW Inline Refer Line list : Gender FW Licensed Refer Recap Sample Development : Gender App & Acc : n/a"
A19: Principal Age Code | B19: =VLOOKUP(A19,MDD!A:B,2,0) -> AT_PrincipalAgeCode | C19: =VLOOKUP(A19,MDD!A:C,3,0) -> text | D19: Basic | E19: Age | F19: Original Principal Age | G19: N/A
A20: Principal Age Description | B20: =VLOOKUP(A20,MDD!A:B,2,0) -> AT_PrincipalAgeDescription | C20: =VLOOKUP(A20,MDD!A:C,3,0) -> text | D20: Basic | E20: Age | F20: Original Principal Age Description | G20: Direct from Principal
A21: Principal Size Code | B21: =VLOOKUP(A21,MDD!A:B,2,0) -> #N/A | C21: =VLOOKUP(A21,MDD!A:C,3,0) -> #N/A | D21: Basic | E21: Sizing | F21: Original Size from Principal (co-dependent with description) | G21: Direct from Principal | H21: https://mapcoid.sharepoint.com/:x:/r/sites/MAPONESOURCE/_layouts/15/doc2.aspx?sourcedoc=%7BD6094834-FFE0-447C-8CCC-14FB959CBC16%7D&file=Attributes%20List_complete_v6_25032026.xlsx&action=default&mobileredirect=true&isSPOFile=1&ovuser=ab852023-79a1-4526-8dc1-e853ef901b75%2Csrishti.b%40ducoconsultancy.com&wdExp=TEAMS-TREATMENT&web=1&TeamsCID=a3a0b74a-c756-46ea-8416-08a12f66ec45&clickparams=eyJBcHBOYW1lIjoiVGVhbXMtRGVza3RvcCIsIkFwcFZlcnNpb24iOiI0OS8yNjA1MTQxNjcxMyJ9&linkOpenTime=1780991606851 | K21: "FW Inline Refer Line list : Size Desc FW Licensed Refer Recap Sample Development : Size Range App & Acc : Catalog Designer size range"
A22: SAP Style Code | B22: =VLOOKUP(A22,MDD!A:B,2,0) -> AT_SAPStyleCode | C22: =VLOOKUP(A22,MDD!A:C,3,0) -> text | D22: Basic | F22: Adjusted principal style code that has been map to SAP generic (without brand code) | G22: Formula in system | K22: "All Div 2 Digits Sub Division + 2 Digits Year + 2Digits Months + 2 Digits Style Number (Running Number)+ 1 Digits Color code mapping Notes : Please inform the list of Sub Division (defined by AI)"
A23: Generic | B23: =VLOOKUP(A23,MDD!A:B,2,0) -> AT_Generic | C23: =VLOOKUP(A23,MDD!A:C,3,0) -> text | D23: Basic | F23: MAA Generic Code (Max 12 Digits - 3 Digits brand code + 9 Digits Principal Style) | G23: Formula in system | K23: "All Div 3 Digits Brand Code + 2 Digits Sub Division + 2 Digits Year + 2Digits Months + 2 Digits Style Number (Running Number)+ 1 Digits Color code mapping Notes : Please inform the list of Sub Division (defined by AI)"
A24: Generic Description | B24: =VLOOKUP(A24,MDD!A:B,2,0) -> AT_GenericDescription | C24: =VLOOKUP(A24,MDD!A:C,3,0) -> regexp | D24: Basic | E24: Description | F24: MAA Generic Description Mapping (Max 40 Digits - 3 Digits brand code + Principal style + (Age/Gender) + Color | G24: Formula in system | K24: "All Div MAA Generic Description Mapping (Max 40 Digits - 3 Digits brand code + Principal style + (Age/Gender) + Color + Size"
A25: Variant | B25: =VLOOKUP(A25,MDD!A:B,2,0) -> AT_Variant | C25: =VLOOKUP(A25,MDD!A:C,3,0) -> text | D25: Basic | F25: MAA Article Code (Max 18 Digits - Generic code + 3 Digits MAA / SAP Color (103 color guidance) + 3 Digits MAA size code mapping | G25: Formula in system | K25: "All Div 3 Digits Brand Code + Max 9 DIgits Principal Style Code + 3 digits SAP Color code + 3 digits Size code"
A26: Variant Description | B26: =VLOOKUP(A26,MDD!A:B,2,0) -> AT_VariantDescription | C26: =VLOOKUP(A26,MDD!A:C,3,0) -> text | D26: Basic | E26: Description | F26: MAA Generic Description Mapping (Max 40 Digits - 3 Digits brand code + Principal style + (Age/Gender) + Color + Size | G26: Formula in system | K26: "All Div MAA Generic Description Mapping (Max 40 Digits - 3 Digits brand code + Principal style + (Age/Gender) + Color + Size"
A27: SAP Color | B27: =VLOOKUP(A27,MDD!A:B,2,0) -> AT_Color | C27: =VLOOKUP(A27,MDD!A:C,3,0) -> LOV | D27: Basic | E27: Color | F27: MAA 103 Basic SAP Color Code & Description | G27: Defined from Images | K27: "FW Inline : Defined from images by AI FW Licensed : Defined from images by AI App & Acc & Sport Equipment Licensed : Catalog : Defined from images by AI "
A28: SAP Size | B28: =VLOOKUP(A28,MDD!A:B,2,0) -> AT_Size | C28: =VLOOKUP(A28,MDD!A:C,3,0) -> LOV | D28: Basic | E28: Sizing | F28: MAA SAP Size Code & Description | G28: Mapping from Principal Data | H28: https://mapcoid.sharepoint.com/:x:/r/sites/MAPONESOURCE/_layouts/15/doc2.aspx?sourcedoc=%7BD6094834-FFE0-447C-8CCC-14FB959CBC16%7D&file=Attributes%20List_complete_v6_25032026.xlsx&action=default&mobileredirect=true&isSPOFile=1&ovuser=ab852023-79a1-4526-8dc1-e853ef901b75%2Csrishti.b%40ducoconsultancy.com&wdExp=TEAMS-TREATMENT&web=1&TeamsCID=a3a0b74a-c756-46ea-8416-08a12f66ec45&clickparams=eyJBcHBOYW1lIjoiVGVhbXMtRGVza3RvcCIsIkFwcFZlcnNpb24iOiI0OS8yNjA1MTQxNjcxMyJ9&linkOpenTime=1780991606851 | K28: "FW Inline Refer Line list : Size Range FW License : Recap Sample Development : Size range (mapping refer to LOV) App : Default S-XXL Acc & Equipment Default : no size"
A29: Created on | B29: =VLOOKUP(A29,MDD!A:B,2,0) -> AT_Createdon | C29: =VLOOKUP(A29,MDD!A:C,3,0) -> legacyisodatetime | D29: Basic | F29: When is the creation date
A30: Created by | B30: =VLOOKUP(A30,MDD!A:B,2,0) -> AT_Createdby | C30: =VLOOKUP(A30,MDD!A:C,3,0) -> text | D30: Basic | F30: Who is creating the articles
A31: Musical Box Article Code | B31: =VLOOKUP(A31,MDD!A:B,2,0) -> AT_MusicalBoxArticleCode | C31: =VLOOKUP(A31,MDD!A:C,3,0) -> text | D31: Basic | F31: MAA Musical Box Code (Max 18 Digits - 3 Digits brand code + 3 digits of MB- +9 digits of SAP Style Code + 3 Digits Assortment Code) | G31: Not applicable | K31: "FW Inline : N/A Only licensed is having MB"
A32: MB Style code | B32: =VLOOKUP(A32,MDD!A:B,2,0) -> AT_MBStyleCode | C32: =VLOOKUP(A32,MDD!A:C,3,0) -> text | D32: Basic | F32: Max 12 digits MB Style (MB- + SAP Style Code ) | G32: Not applicable | K32: "FW Inline : N/A Only licensed is having MB"
A33: MB Assortment Code | B33: =VLOOKUP(A33,MDD!A:B,2,0) -> AT_MBAssortmentCode | C33: =VLOOKUP(A33,MDD!A:C,3,0) -> LOV | D33: Basic | F33: 3 Digits Assortment code (based on matrix of qty per sizes) | G33: Not applicable | K33: "FW Inline : N/A Only licensed is having MB"
A34: Musical Box Article Description | B34: =VLOOKUP(A34,MDD!A:B,2,0) -> AT_MusicalBoxArticleDescription | C34: =VLOOKUP(A34,MDD!A:C,3,0) -> text | D34: Basic | E34: Description | F34: MAA Musical Box Description Mapping (Max 40 Digits - 3 Digits brand code + Principal style + (Age/Gender) + Color + (-MB) | G34: Not applicable | K34: "FW Inline : N/A Only licensed is having MB"
A35: Musical Box Components Qty | B35: =VLOOKUP(A35,MDD!A:B,2,0) -> AT_MusicalBoxComponentsQty | C35: =VLOOKUP(A35,MDD!A:C,3,0) -> LOV | D35: Basic | F35: Components qty of Musical Box Articles : Breakdown qty per sizes | G35: Not applicable | K35: "FW Inline : N/A Only licensed is having MB"
A36: Musical Box UOM | B36: =VLOOKUP(A36,MDD!A:B,2,0) -> AT_MusicalBoxUOM | C36: =VLOOKUP(A36,MDD!A:C,3,0) -> LOV | D36: Basic | F36: UOM for Musical Box (Default : CAR) | G36: Not applicable | K36: "FW Inline : N/A Only licensed is having MB"
A37: SAP Age | B37: =VLOOKUP(A37,MDD!A:B,2,0) -> AT_SAPAge | C37: =VLOOKUP(A37,MDD!A:C,3,0) -> LOV | D37: Basic | E37: Age | F37: MAA SAP Age (Co - Dependent with Description) E.g : CH - Children AA - All Ages AD - Adults | G37: Mapping from Principal Data | H37: https://mapcoid.sharepoint.com/:x:/r/sites/MAPONESOURCE/_layouts/15/Doc.aspx?sourcedoc=%7BE4C2484E-2B04-4F15-9F0B-2065D59345AB%7D&file=RECAP%20SAMPLE%20DEVELOPMENT%20LOTTO%20SS26%20(2).xlsx&action=default&mobileredirect=true&or=EXCEL-WEB.BODY.NT&ct=1781595179775 | K37: "FW Inline Refer Line list : Gender Junior - kids Men - adults Women - adults FW Licensed Refer Recap Sample Development : SIze Range 36-40 Adults 39 - 45 Ad App Acc Equipment : Default Adults"
A38: SAP Gender | B38: =VLOOKUP(A38,MDD!A:B,2,0) -> AT_Gender | C38: =VLOOKUP(A38,MDD!A:C,3,0) -> LOV | D38: Basic | E38: Gender | F38: MAA SAP Gender (co dependent with description) E.g : M - Male F - Female U - Unisex | G38: Mapping from Principal Data | H38: https://mapcoid.sharepoint.com/:x:/r/sites/MAPONESOURCE/_layouts/15/Doc.aspx?sourcedoc=%7BE4C2484E-2B04-4F15-9F0B-2065D59345AB%7D&file=RECAP%20SAMPLE%20DEVELOPMENT%20LOTTO%20SS26%20(2).xlsx&action=default&mobileredirect=true&or=EXCEL-WEB.BODY.NT&ct=1781595179775 | K38: "FW Inline Refer Line list : Gender FW Licensed Refer Recap Sample Development : Gender App : Catalog : Defined from images by AI Acc & Equipment : Default Unisex"
A39: Season | B39: =VLOOKUP(A39,MDD!A:B,2,0) -> AT_Season | C39: =VLOOKUP(A39,MDD!A:C,3,0) -> LOV | D39: Basic | F39: MAA SAP Season (Co Dependent with Description) E.g : SP - Spring SM - Summer FW - Fall Winter SS - Spring Summer etc (refer to LOV) | G39: Manual Input
A40: Season Year | B40: =VLOOKUP(A40,MDD!A:B,2,0) -> AT_SeasonYear | C40: =VLOOKUP(A40,MDD!A:C,3,0) -> number | D40: Basic | F40: MAA SAP Year | G40: Manual Input
A41: Country of Origin | B41: =VLOOKUP(A41,MDD!A:B,2,0) -> AT_CountryOrigin | C41: =VLOOKUP(A41,MDD!A:C,3,0) -> LOV | D41: Basic | F41: Co Dependent with Description E.g CN - China VN - Vietnam SG - Singapore etc (refer to LOV) | G41: Formula in system | K41: "FW Inline Refer Line list : Made in. (mapping refer to LOV) FW License Refer Line list : COO (Mapping refer to LOV) App Acc Equipment : Manual"
A42: Vendor | B42: =VLOOKUP(A42,MDD!A:B,2,0) -> AT_Vendor | C42: =VLOOKUP(A42,MDD!A:C,3,0) -> LOV | D42: Basic | F42: MAA Vendor code (Co Dependent with description) Format : Country Code - Comp Code - Vendor Code - Vendor Name MY - 0198 - 10303 - CROCS FOOTWEAR (MALAYSIA) SDN BHD ID - 0888 - 6863 - SKECHERS SARL etc (refer to LOV)
A43: Main Vendor Identification | B43: =VLOOKUP(A43,MDD!A:B,2,0) -> AT_MainVendorIdentification | C43: =VLOOKUP(A43,MDD!A:C,3,0) -> text | D43: Basic | F43: to identify priority vendor
A44: Exchange Rate | B44: =VLOOKUP(A44,MDD!A:B,2,0) -> AT_ExchangeRate | C44: =VLOOKUP(A44,MDD!A:C,3,0) -> number | D44: Price | F44: Exchange Rate to Local Currency
A45: Pricing Distribution Channel | B45: =VLOOKUP(A45,MDD!A:B,2,0) -> AT_PricingDistributionChannel | C45: =VLOOKUP(A45,MDD!A:C,3,0) -> LOV | D45: Price | F45: To identify price channel Co Dependent with Description) E.g : 01 - Retailer 02 - Wholesale 03 - E-comm
A46: Retail Price Currency | B46: =VLOOKUP(A46,MDD!A:B,2,0) -> AT_RetailPriceCurrency | C46: =VLOOKUP(A46,MDD!A:C,3,0) -> LOV | D46: Price | G46: Formula in system | K46: "Default by currency per country e.g : IIndonesia (IDR), Philiphine (PHP), etc"
A47: Original Price | B47: =VLOOKUP(A47,MDD!A:B,2,0) -> AT_OriginalPrice | C47: =VLOOKUP(A47,MDD!A:C,3,0) -> regexp | D47: Price | F47: MAA Original Price
A48: Valid From | B48: =VLOOKUP(A48,MDD!A:B,2,0) -> #N/A | C48: =VLOOKUP(A48,MDD!A:C,3,0) -> #N/A | D48: Price | F48: Identify pricing valid period
A49: Valid To | B49: =VLOOKUP(A49,MDD!A:B,2,0) -> #N/A | C49: =VLOOKUP(A49,MDD!A:C,3,0) -> #N/A | D49: Price | F49: Identify pricing valid period Conditional (default as priority 31.12.9999 - editable)
A50: Created on | B50: =VLOOKUP(A50,MDD!A:B,2,0) -> AT_Createdon | C50: =VLOOKUP(A50,MDD!A:C,3,0) -> legacyisodatetime | D50: Basic | F50: Identify when the pricing is registered (Maintainance date)
A51: Created by | B51: =VLOOKUP(A51,MDD!A:B,2,0) -> AT_Createdby | C51: =VLOOKUP(A51,MDD!A:C,3,0) -> text | D51: Basic | F51: Identify who is registering the pricing (User)
A52: Current price | B52: =VLOOKUP(A52,MDD!A:B,2,0) -> AT_CurrentPrice | C52: =VLOOKUP(A52,MDD!A:C,3,0) -> regexp | D52: Price | F52: MAA Current Price
A53: Valid From | B53: =VLOOKUP(A53,MDD!A:B,2,0) -> #N/A | C53: =VLOOKUP(A53,MDD!A:C,3,0) -> #N/A | D53: Price | F53: Identify pricing valid period
A54: Valid To | B54: =VLOOKUP(A54,MDD!A:B,2,0) -> #N/A | C54: =VLOOKUP(A54,MDD!A:C,3,0) -> #N/A | D54: Price | F54: Identify pricing valid period Conditional (default as priority 31.12.9999 - editable)
A55: Created on | B55: =VLOOKUP(A55,MDD!A:B,2,0) -> AT_Createdon | C55: =VLOOKUP(A55,MDD!A:C,3,0) -> legacyisodatetime | D55: Basic | F55: Identify when the pricing is registered (Maintainance date)
A56: Created by | B56: =VLOOKUP(A56,MDD!A:B,2,0) -> AT_Createdby | C56: =VLOOKUP(A56,MDD!A:C,3,0) -> text | D56: Basic | F56: Identify who is registering the pricing (User)
A57: Discount Bucket | B57: =VLOOKUP(A57,MDD!A:B,2,0) -> AT_DiscountBucket | C57: =VLOOKUP(A57,MDD!A:C,3,0) -> number | D57: Price | F57: Comparison between original vs current price (non-rounded)
A58: Discount Bucket (Rounded) | B58: =VLOOKUP(A58,MDD!A:B,2,0) -> AT_DiscountBucketRounded | C58: =VLOOKUP(A58,MDD!A:C,3,0) -> number | D58: Price | F58: Comparison between original vs current price (rounded)
A59: Estimated Landed Cost | B59: =VLOOKUP(A59,MDD!A:B,2,0) -> AT_EstimatedLandedCost | C59: =VLOOKUP(A59,MDD!A:C,3,0) -> number | D59: Cost
A60: FOB | B60: =VLOOKUP(A60,MDD!A:B,2,0) -> AT_FOB | C60: =VLOOKUP(A60,MDD!A:C,3,0) -> regexp | D60: Cost | G60: Direct from Principal | K60: "FW Inline Line List : WHL Price FW License : Recap Sample Development : FOB price App Acc Equip : Manual input"
A61: FOB Currency | B61: =VLOOKUP(A61,MDD!A:B,2,0) -> AT_FOBCurrency | C61: =VLOOKUP(A61,MDD!A:C,3,0) -> LOV | D61: Cost | G61: Direct from Principal | K61: "FW Inline Line List : VAL Price FW License Recap Sample Development : FOB Currency App Acc Equip : Manual input"
A62: Freight Cost | B62: =VLOOKUP(A62,MDD!A:B,2,0) -> AT_FreightCost | C62: =VLOOKUP(A62,MDD!A:C,3,0) -> regexp | D62: Cost | G62: Formula in system
A63: Royalty | B63: =VLOOKUP(A63,MDD!A:B,2,0) -> AT_Royalty | C63: =VLOOKUP(A63,MDD!A:C,3,0) -> regexp | D63: Cost | G63: Formula in system
A64: Royalty Deduction | B64: =VLOOKUP(A64,MDD!A:B,2,0) -> AT_RoyaltyDeduction | C64: =VLOOKUP(A64,MDD!A:C,3,0) -> regexp | D64: Cost | G64: Formula in system
A65: Commision | B65: =VLOOKUP(A65,MDD!A:B,2,0) -> #N/A | C65: =VLOOKUP(A65,MDD!A:C,3,0) -> #N/A | D65: Cost | G65: Formula in system
A66: SGS | B66: =VLOOKUP(A66,MDD!A:B,2,0) -> AT_SGS | C66: =VLOOKUP(A66,MDD!A:C,3,0) -> regexp | D66: Cost | G66: Formula in system
A67: Marketing Fee | B67: =VLOOKUP(A67,MDD!A:B,2,0) -> AT_MarketingFee | C67: =VLOOKUP(A67,MDD!A:C,3,0) -> regexp | D67: Cost | G67: Formula in system
A68: Haddad Office Charge | B68: =VLOOKUP(A68,MDD!A:B,2,0) -> AT_HaddadOfficeCharge | C68: =VLOOKUP(A68,MDD!A:C,3,0) -> regexp | D68: Cost | G68: Formula in system
A69: Haddad Office Charge - Deduction | B69: =VLOOKUP(A69,MDD!A:B,2,0) -> AT_HaddadOfficeChargeDeduction | C69: =VLOOKUP(A69,MDD!A:C,3,0) -> regexp | D69: Cost | G69: Formula in system
A70: Safeguard Duty (ID Only) | B70: =VLOOKUP(A70,MDD!A:B,2,0) -> AT_SafeguardDutyIdOnly | C70: =VLOOKUP(A70,MDD!A:C,3,0) -> number | D70: Cost | G70: Formula in system
A71: Label Cost | B71: =VLOOKUP(A71,MDD!A:B,2,0) -> AT_LabelCost | C71: =VLOOKUP(A71,MDD!A:C,3,0) -> regexp | D71: Cost | G71: Formula in system
A72: Others | B72: =VLOOKUP(A72,MDD!A:B,2,0) -> AT_Others | C72: =VLOOKUP(A72,MDD!A:C,3,0) -> number | D72: Cost | G72: Formula in system
A73: MC Structure (Merchandise Category) | B73: =VLOOKUP(A73,MDD!A:B,2,0) -> #N/A | C73: =VLOOKUP(A73,MDD!A:C,3,0) -> #N/A | D73: MC | F73: Structure : 1 Digits of SAP Product Div + 2 Digits of SAP Product Group + 2 Digits of SAP Product Category + 3 Digits of Brand Code + 1 Digits of SAP Product Flag | G73: Formula in system
A74: SAP Product Division | B74: =VLOOKUP(A74,MDD!A:B,2,0) -> #N/A | C74: =VLOOKUP(A74,MDD!A:C,3,0) -> #N/A | D74: MC | F74: Co Dependent with Description E.g : F - Footwear | A - Apparel etc | K74: "FW Inline : Line List : Product type FW License : Defined from images by Ai App Acc Equipment License : Defined from images by AI"
A75: SAP Product Group | B75: =VLOOKUP(A75,MDD!A:B,2,0) -> #N/A | C75: =VLOOKUP(A75,MDD!A:C,3,0) -> #N/A | D75: MC | F75: Co Dependent with Description) E.g : FS - Lifestyle Shoes | 34 - Sports Shoes etc | K75: "FW Inline Line List : Discipline FW License Recap Sample Development : Category App Acc Equipment License : Defined from images by AI"
A76: SAP Product Category | B76: =VLOOKUP(A76,MDD!A:B,2,0) -> #N/A | C76: =VLOOKUP(A76,MDD!A:C,3,0) -> #N/A | D76: MC | F76: Co Dependent with Description E.g : RU - Running | CS - Casual Shoes etc | K76: "FW Inline Line List : Discipline FW License Recap Sample Development : Category App Acc Equipment License : Defined from images by AI"
A77: SAP Product Flag | B77: =VLOOKUP(A77,MDD!A:B,2,0) -> AT_SAPProductFlag | C77: =VLOOKUP(A77,MDD!A:C,3,0) -> LOV | D77: MC | F77: Co Dependent with Description E.g : A - Intercompany 5 - Direct Local 1 - Consignment etc To indicate the bussiness model (Direct, local, intercompany,consignment, non MD) E.g : A - Intercompany | 5 - Direct Local | 1 - Consignment | K77: "All Division: Default : Intercompany (A)"
A78: Principal Merchandise Hierarchy L1 | B78: =VLOOKUP(A78,MDD!A:B,2,0) -> AT_PrincipalMerchandiseHierarchyL1 | C78: =VLOOKUP(A78,MDD!A:C,3,0) -> text | D78: Hierarchy | F78: Principal Merchandise Hierarchy Level 1 | G78: Direct from Principal | K78: "FW Inline Line list : Product Type"
A79: Principal Merchandise Hierarchy L2 | B79: =VLOOKUP(A79,MDD!A:B,2,0) -> AT_PrincipalMerchandiseHierarchyL2 | C79: =VLOOKUP(A79,MDD!A:C,3,0) -> text | D79: Hierarchy | F79: Principal Merchandise Hierarchy Level 2 | G79: Direct from Principal | K79: "FW Inline Line List :Discipline"
A80: Principal Merchandise Hierarchy L3 | B80: =VLOOKUP(A80,MDD!A:B,2,0) -> AT_PrincipalMerchandiseHierarchyL3 | C80: =VLOOKUP(A80,MDD!A:C,3,0) -> text | D80: Hierarchy | F80: Principal Merchandise Hierarchy Level 3 | G80: n/a | K80: n/a
A81: Principal Merchandise Hierarchy L4 | B81: =VLOOKUP(A81,MDD!A:B,2,0) -> AT_PrincipalMerchandiseHierarchyL4 | C81: =VLOOKUP(A81,MDD!A:C,3,0) -> text | D81: Hierarchy | F81: Principal Merchandise Hierarchy Level 4 | G81: n/a | K81: n/a
A82: Principal Merchandise Hierarchy L5 | B82: =VLOOKUP(A82,MDD!A:B,2,0) -> AT_PrincipalMerchandiseHierarchyL5 | C82: =VLOOKUP(A82,MDD!A:C,3,0) -> text | D82: Hierarchy | F82: Principal Merchandise Hierarchy Level 5 | G82: n/a | K82: n/a
A83: Material Type | B83: =VLOOKUP(A83,MDD!A:B,2,0) -> AT_MaterialType | C83: =VLOOKUP(A83,MDD!A:C,3,0) -> LOV | D83: Commercial | F83: Direct/ Intercompany/ etc | K83: "All Division: Default : Intercompany"
A84: Article Category | B84: =VLOOKUP(A84,MDD!A:B,2,0) -> AT_SAPArticleCategory | C84: =VLOOKUP(A84,MDD!A:C,3,0) -> LOV | D84: Basic | F84: SAP Article Category to indicate whether the article is single,Generic,etc | K84: All Division : Default "Generic"
A85: Internal Barcode | B85: =VLOOKUP(A85,MDD!A:B,2,0) -> AT_InternalBarcode | C85: =VLOOKUP(A85,MDD!A:C,3,0) -> regexp | D85: Basic | E85: Barcode
A86: Principal Barcode | B86: =VLOOKUP(A86,MDD!A:B,2,0) -> AT_PrincipalBarcode | C86: =VLOOKUP(A86,MDD!A:C,3,0) -> regexp | D86: Basic | E86: Barcode | F86: Original Principal Barcode | K86: "FW Inline Order Confirmation : EAN 13"
A87: FG Barcode | B87: =VLOOKUP(A87,MDD!A:B,2,0) -> AT_FGBarcode | C87: =VLOOKUP(A87,MDD!A:C,3,0) -> regexp | D87: Basic | E87: Barcode | F87: FG Barcode (Only for Sport Direct)
A88: Main EAN Indicator | B88: =VLOOKUP(A88,MDD!A:B,2,0) -> AT_MainEANIndicator | C88: =VLOOKUP(A88,MDD!A:C,3,0) -> LOV | D88: Basic | E88: Barcode
A89: EAN Category | B89: =VLOOKUP(A89,MDD!A:B,2,0) -> AT_EANCategory | C89: =VLOOKUP(A89,MDD!A:C,3,0) -> LOV | D89: Basic | E89: Barcode
A90: Unit of Measurement (UoM) | B90: =VLOOKUP(A90,MDD!A:B,2,0) -> AT_UOM | C90: =VLOOKUP(A90,MDD!A:C,3,0) -> LOV | D90: Basic
A91: HS Code | B91: =VLOOKUP(A91,MDD!A:B,2,0) -> AT_HSCode | C91: =VLOOKUP(A91,MDD!A:C,3,0) -> text | D91: Cost | K91: "FW Inline Order confirmation : HS Code FW App Acc Equip Licensed Catalog : Manual Input"
A92: Nature of Article (NOA) | B92: =VLOOKUP(A92,MDD!A:B,2,0) -> #N/A | C92: =VLOOKUP(A92,MDD!A:C,3,0) -> #N/A | D92: Commercial | G92: Manual Input
A93: Article Type | B93: =VLOOKUP(A93,MDD!A:B,2,0) -> #N/A | C93: =VLOOKUP(A93,MDD!A:C,3,0) -> #N/A | D93: Commercial | F93: Inline/License/SSE | G93: Manual Input
A94: Thumbnail Image | B94: =VLOOKUP(A94,MDD!A:B,2,0) -> #N/A | C94: =VLOOKUP(A94,MDD!A:C,3,0) -> #N/A | D94: Image (BY) | E94: Images | G94: Direct from Prinicpal
A95: BY Age | B95: =VLOOKUP(A95,MDD!A:B,2,0) -> AT_BYAge | C95: =VLOOKUP(A95,MDD!A:C,3,0) -> LOV | D95: Basic | G95: Mapping from Principal Data | K95: "FW Inline Refer Line list :Gender FW Licensed Refer Recap Sample Development : Gender App Acc Equipment : Default Adults"
A96: BY Gender | B96: =VLOOKUP(A96,MDD!A:B,2,0) -> AT_BYGender | C96: =VLOOKUP(A96,MDD!A:C,3,0) -> LOV | D96: Basic | E96: Gender | G96: Mapping from Principal Data | K96: "FW Inline Refer Line list : Gender FW Licensed Refer Recap Sample Development : Gender App : Catalog : Defined from images by AI Acc & Equipment : Default Unisex"
A97: BCI | B97: =VLOOKUP(A97,MDD!A:B,2,0) -> AT_BCI | C97: =VLOOKUP(A97,MDD!A:C,3,0) -> LOV | D97: Image (BY) | G97: Formula in system | K97: "All Division Default : Commercial"
A98: BY Color Group | B98: =VLOOKUP(A98,MDD!A:B,2,0) -> #N/A | C98: =VLOOKUP(A98,MDD!A:C,3,0) -> #N/A | D98: Basic | E98: Color | F98: 6 Color Group | G98: Formula in system | K98: "All Division Mapping from BY Standardized color"
A99: BY Standardized Color | B99: =VLOOKUP(A99,MDD!A:B,2,0) -> #N/A | C99: =VLOOKUP(A99,MDD!A:C,3,0) -> #N/A | D99: Basic | E99: Color | F99: 53 Color Description | G99: Defined from Images | K99: "All Division Defined from Images (AI)"
A100: Price Range | B100: =VLOOKUP(A100,MDD!A:B,2,0) -> AT_PriceRange | C100: =VLOOKUP(A100,MDD!A:C,3,0) -> LOV | D100: Basic | G100: Formula in system | K100: Price range : based on suggested retail price calculated by Stibo and mapping to LOV BY price range
...

Sheet 2XU(Inline)
A1: Stibo Attribute | B1: Stibo Attribute ID | C1: Stibo Validation | D1: Cluster | E1: Grouping | F1: Attributes Description | G1: Field Mapping Type | H1: Brand File Name & Link | I1: Brand File Sheet Name | J1: Field Name in the Brand File | K1: Mapping Logic | L1: Mapping file for additional Brand specific mapping
A2: Country | B2: =VLOOKUP(A2,MDD!A:B,2,0) -> AT_Country | C2: =VLOOKUP(A2,MDD!A:C,3,0) -> LOV | D2: Basic | F2: Co Dependent with Description E.g : ID - Indonesia PH - Philiphine TH - Thailand SG - Singapore MY - Malaysia VN - Vietnam KH : Cambodia | G2: Manual Input
A3: Company | B3: =VLOOKUP(A3,MDD!A:B,2,0) -> AT_CompanyCode | C3: =VLOOKUP(A3,MDD!A:C,3,0) -> LOV | D3: Basic | F3: Co Dependent with Description 0888 - PT. Map Aktif Adiperkasa 0886 - PT. MAP FTL Adiperkasa 0882 - Magna Management Asia etc (Refer to LOV) | G3: Manual Input
A4: SBU | B4: =VLOOKUP(A4,MDD!A:B,2,0) -> AT_SBU | C4: =VLOOKUP(A4,MDD!A:C,3,0) -> LOV | D4: Basic | F4: Co Dependent with Description E.g SP - Sports FQ - Footlocker Etc (refer to LOV) | G4: Manual Input
A5: Brand | B5: =VLOOKUP(A5,MDD!A:B,2,0) -> AT_Brand | C5: =VLOOKUP(A5,MDD!A:C,3,0) -> LOV | D5: Basic | F5: Co Dependent with Description E.g ADI - Adidas NIK - Nike NEW - New Balance Etc (refer to LOV) | G5: Manual Input
A6: Brand Group | B6: =VLOOKUP(A6,MDD!A:B,2,0) -> AT_BrandGroup | C6: =VLOOKUP(A6,MDD!A:C,3,0) -> LOV | D6: Basic | F6: Multiple brand codes that managed under 1 brand group e.g. Adidas, Lego, Hasbro | G6: Formula in system
A7: Brand Type | B7: =VLOOKUP(A7,MDD!A:B,2,0) -> AT_BrandType | C7: =VLOOKUP(A7,MDD!A:C,3,0) -> LOV | D7: Commercial | F7: Whether a brand act as a retailer, selling directly to customers (MAA brands, SDI brands) or as a distributor (Non-MAA brands, Non-SDI brands) | G7: Formula in system
A8: Brand Category | B8: =VLOOKUP(A8,MDD!A:B,2,0) -> AT_BrandCategory | C8: =VLOOKUP(A8,MDD!A:C,3,0) -> LOV | D8: Commercial | F8: Group of brands that classified based on their performance/ contribution e.g. Top brands, Selected brands, Non-Top brands | G8: Formula in system
A9: Brand Status | B9: =VLOOKUP(A9,MDD!A:B,2,0) -> AT_BrandStatus | C9: =VLOOKUP(A9,MDD!A:C,3,0) -> LOV | D9: Commercial | F9: Indicating whether the brands is actively being sold or, no longer continued or exit the market (Active/Discontinue) | G9: Formula in system
A10: BY Indicator | B10: =VLOOKUP(A10,MDD!A:B,2,0) -> AT_BYIndicator | C10: =VLOOKUP(A10,MDD!A:C,3,0) -> LOV | D10: System indicator | F10: Article to be ordered | G10: Formula in system
A11: SAP Indicator | B11: =VLOOKUP(A11,MDD!A:B,2,0) -> AT_SAPIndicator | C11: =VLOOKUP(A11,MDD!A:C,3,0) -> LOV | D11: System indicator | F11: Article has been created | G11: Formula in system
A12: Ecom Indicator | B12: =VLOOKUP(A12,MDD!A:B,2,0) -> AT_EcomIndicator | C12: =VLOOKUP(A12,MDD!A:C,3,0) -> LOV | D12: System indicator | F12: Article to be Publish at Online Sales Channel | G12: Manual Input
A13: Principal Style Code | B13: =VLOOKUP(A13,MDD!A:B,2,0) -> AT_PrincipalStyleCode | C13: =VLOOKUP(A13,MDD!A:C,3,0) -> text | D13: Basic | F13: Original Principal Code | G13: Direct from Principal | H13: https://mapcoid.sharepoint.com/:x:/r/sites/MAPONESOURCE/_layouts/15/Doc.aspx?sourcedoc=%7BFB450107-E518-43FC-9020-1755050C5AB5%7D&file=H1%2027%20Product%20Bible%20-%20Wholesale.xlsx&action=default&mobileredirect=true&or=EXCEL-WEB.BODY.NT&ct=1781775190500 | J13: Product Code | K13: "Apparel & Acc Product Bibble : Column 'Product Code'"
A14: Principal Style Description | B14: =VLOOKUP(A14,MDD!A:B,2,0) -> AT_PrincipalStyleDescription | C14: =VLOOKUP(A14,MDD!A:C,3,0) -> text | D14: Basic | E14: Description | F14: Original Principal Product Name | G14: Direct from Principal | H14: https://mapcoid.sharepoint.com/:x:/r/sites/MAPONESOURCE/_layouts/15/Doc.aspx?sourcedoc=%7BFB450107-E518-43FC-9020-1755050C5AB5%7D&file=H1%2027%20Product%20Bible%20-%20Wholesale.xlsx&action=default&mobileredirect=true&or=EXCEL-WEB.BODY.NT&ct=1781775190500 | J14: Product Namen | K14: "Apparel & Acc Product Bibble : Column 'Product Namen'"
A15: Principal Color Code | B15: =VLOOKUP(A15,MDD!A:B,2,0) -> AT_PrincipalColorCode | C15: =VLOOKUP(A15,MDD!A:C,3,0) -> text | D15: Basic | E15: Color | F15: Original Principal Color | G15: Direct from Principal | H15: https://mapcoid.sharepoint.com/:x:/r/sites/MAPONESOURCE/_layouts/15/Doc.aspx?sourcedoc=%7BFB450107-E518-43FC-9020-1755050C5AB5%7D&file=H1%2027%20Product%20Bible%20-%20Wholesale.xlsx&action=default&mobileredirect=true&or=EXCEL-WEB.BODY.NT&ct=1781775190500 | J15: Colour Code | K15: "Apparel & Acc Product Bibble : Column 'Colour Code'"
A16: Principal Color Description | B16: =VLOOKUP(A16,MDD!A:B,2,0) -> AT_PrincipalColorName | C16: =VLOOKUP(A16,MDD!A:C,3,0) -> text | D16: Basic | E16: Color | F16: Original Principal Color Description | G16: Direct from Principal | H16: https://mapcoid.sharepoint.com/:x:/r/sites/MAPONESOURCE/_layouts/15/Doc.aspx?sourcedoc=%7BFB450107-E518-43FC-9020-1755050C5AB5%7D&file=H1%2027%20Product%20Bible%20-%20Wholesale.xlsx&action=default&mobileredirect=true&or=EXCEL-WEB.BODY.NT&ct=1781775190500 | J16: Colour Description | K16: "Apparel & Acc Product Bibble : Column 'Colour Description'"
A17: Principal Gender Code | B17: =VLOOKUP(A17,MDD!A:B,2,0) -> AT_PrincipalGenderCode | C17: =VLOOKUP(A17,MDD!A:C,3,0) -> text | D17: Basic | E17: Gender | F17: Original Principal Gender | G17: N/A
A18: Principal Gender Description | B18: =VLOOKUP(A18,MDD!A:B,2,0) -> AT_PrincipalGenderDescription | C18: =VLOOKUP(A18,MDD!A:C,3,0) -> text | D18: Basic | E18: Gender | F18: Original Principal Gender Description | G18: Direct from Principal | H18: https://mapcoid.sharepoint.com/:x:/r/sites/MAPONESOURCE/_layouts/15/Doc.aspx?sourcedoc=%7BFB450107-E518-43FC-9020-1755050C5AB5%7D&file=H1%2027%20Product%20Bible%20-%20Wholesale.xlsx&action=default&mobileredirect=true&or=EXCEL-WEB.BODY.NT&ct=1781775190500 | J18: Gender | K18: "Apparel & Acc Product Bibble : Column 'Gender'"
A19: Principal Age Code | B19: =VLOOKUP(A19,MDD!A:B,2,0) -> AT_PrincipalAgeCode | C19: =VLOOKUP(A19,MDD!A:C,3,0) -> text | D19: Basic | E19: Age | F19: Original Principal Age | G19: N/A
A20: Principal Age Description | B20: =VLOOKUP(A20,MDD!A:B,2,0) -> AT_PrincipalAgeDescription | C20: =VLOOKUP(A20,MDD!A:C,3,0) -> text | D20: Basic | E20: Age | F20: Original Principal Age Description | G20: N/A
A21: Principal Size Code | B21: =VLOOKUP(A21,MDD!A:B,2,0) -> #N/A | C21: =VLOOKUP(A21,MDD!A:C,3,0) -> #N/A | D21: Basic | E21: Sizing | F21: Original Size from Principal (co-dependent with description) | G21: Direct from Principal | H21: https://mapcoid.sharepoint.com/:x:/r/sites/MAPONESOURCE/_layouts/15/Doc.aspx?sourcedoc=%7BFB450107-E518-43FC-9020-1755050C5AB5%7D&file=H1%2027%20Product%20Bible%20-%20Wholesale.xlsx&action=default&mobileredirect=true&or=EXCEL-WEB.BODY.NT&ct=1781775190500 | J21: Size | K21: "Apparel & Acc Product Bibble Sheet EAN Barcode : Column 'Size' "
A22: SAP Style Code | B22: =VLOOKUP(A22,MDD!A:B,2,0) -> AT_SAPStyleCode | C22: =VLOOKUP(A22,MDD!A:C,3,0) -> text | D22: Basic | F22: Adjusted principal style code that has been map to SAP generic (without brand code) | G22: Formula in system | K22: "Apparel & Accessories Max 9 Digits : 7 Digits Principal Style Code + 2 Digits MD Mapping Example : UQ7707E WHT/BLK Result : UQ7707EWB"
A23: Generic | B23: =VLOOKUP(A23,MDD!A:B,2,0) -> AT_Generic | C23: =VLOOKUP(A23,MDD!A:C,3,0) -> text | D23: Basic | F23: MAA Generic Code (Max 12 Digits - 3 Digits brand code + 9 Digits Principal Style) | G23: Formula in system | K23: "Apparel & Accesories Max 12 Digits : Max 9 : 7 Digits Principal Style Code + 2 Digits MD Mapping Example : UQ7707E WHT/BLK Result : 2XUUQ7707EWB"
A24: Generic Description | B24: =VLOOKUP(A24,MDD!A:B,2,0) -> AT_GenericDescription | C24: =VLOOKUP(A24,MDD!A:C,3,0) -> regexp | D24: Basic | E24: Description | F24: MAA Generic Description Mapping (Max 40 Digits - 3 Digits brand code + Principal style + (Age/Gender) + Color | G24: Formula in system | K24: "Apparel & Accessories Mapping formula : 3 Digits Brand Code + Principal Style Description + SAP (Age/Gender) + SAP Mapping Color Description"
A25: Variant | B25: =VLOOKUP(A25,MDD!A:B,2,0) -> AT_Variant | C25: =VLOOKUP(A25,MDD!A:C,3,0) -> text | D25: Basic | F25: MAA Article Code (Max 18 Digits - Generic code + 3 Digits MAA / SAP Color (103 color guidance) + 3 Digits MAA size code mapping | G25: Formula in system | K25: "Apparel/Accessories Mapping formula: Generic + 3 Digits SAP Color Code + 3 Digits SAP Size code Example: 2XUUQ770EWB0PK00M"
A26: Variant Description | B26: =VLOOKUP(A26,MDD!A:B,2,0) -> AT_VariantDescription | C26: =VLOOKUP(A26,MDD!A:C,3,0) -> text | D26: Basic | E26: Description | F26: MAA Generic Description Mapping (Max 40 Digits - 3 Digits brand code + Principal style + (Age/Gender) + Color + Size | G26: Formula in system | K26: "Apparel and Accessories Mapping formula : 3 Digits Brand Code + Principal Style Description + SAP (Age/Gender) + SAP Mapping Color Description + Size Description"
A27: SAP Color | B27: =VLOOKUP(A27,MDD!A:B,2,0) -> AT_Color | C27: =VLOOKUP(A27,MDD!A:C,3,0) -> LOV | D27: Basic | E27: Color | F27: MAA 103 Basic SAP Color Code & Description | G27: Defined from Images | K27: "Apparel & Accessories Defined from images by AI"
A28: SAP Size | B28: =VLOOKUP(A28,MDD!A:B,2,0) -> AT_Size | C28: =VLOOKUP(A28,MDD!A:C,3,0) -> LOV | D28: Basic | E28: Sizing | F28: MAA SAP Size Code & Description | G28: Formula in system | H28: https://mapcoid.sharepoint.com/:x:/r/sites/MAPONESOURCE/_layouts/15/Doc.aspx?sourcedoc=%7BFB450107-E518-43FC-9020-1755050C5AB5%7D&file=H1%2027%20Product%20Bible%20-%20Wholesale.xlsx&action=default&mobileredirect=true&or=EXCEL-WEB.BODY.NT&ct=1781775190500 | J28: Size | K28: "Apparel & Acc Product Bibble : Column 'Size' Refer to LOV"
A29: Created on | B29: =VLOOKUP(A29,MDD!A:B,2,0) -> AT_Createdon | C29: =VLOOKUP(A29,MDD!A:C,3,0) -> legacyisodatetime | D29: Basic | F29: When is the creation date | G29: Formula in system | K29: Default based on user key in (DD.MM.YYYY)
A30: Created by | B30: =VLOOKUP(A30,MDD!A:B,2,0) -> AT_Createdby | C30: =VLOOKUP(A30,MDD!A:C,3,0) -> text | D30: Basic | F30: Who is creating the articles | G30: Formula in system | K30: Default on the creation date (format DD.MM.YYYY)
A31: Musical Box Article Code | B31: =VLOOKUP(A31,MDD!A:B,2,0) -> AT_MusicalBoxArticleCode | C31: =VLOOKUP(A31,MDD!A:C,3,0) -> text | D31: Basic | F31: MAA Musical Box Code (Max 18 Digits - 3 Digits brand code + 3 digits of MB- +9 digits of SAP Style Code + 3 Digits Assortment Code) | G31: N/A
A32: MB Style code | B32: =VLOOKUP(A32,MDD!A:B,2,0) -> AT_MBStyleCode | C32: =VLOOKUP(A32,MDD!A:C,3,0) -> text | D32: Basic | F32: Max 12 digits MB Style (MB- + SAP Style Code ) | G32: N/A
A33: MB Assortment Code | B33: =VLOOKUP(A33,MDD!A:B,2,0) -> AT_MBAssortmentCode | C33: =VLOOKUP(A33,MDD!A:C,3,0) -> LOV | D33: Basic | F33: 3 Digits Assortment code (based on matrix of qty per sizes) | G33: N/A
A34: Musical Box Article Description | B34: =VLOOKUP(A34,MDD!A:B,2,0) -> AT_MusicalBoxArticleDescription | C34: =VLOOKUP(A34,MDD!A:C,3,0) -> text | D34: Basic | E34: Description | F34: MAA Musical Box Description Mapping (Max 40 Digits - 3 Digits brand code + Principal style + (Age/Gender) + Color + (-MB) | G34: N/A
A35: Musical Box Components Qty | B35: =VLOOKUP(A35,MDD!A:B,2,0) -> AT_MusicalBoxComponentsQty | C35: =VLOOKUP(A35,MDD!A:C,3,0) -> LOV | D35: Basic | F35: Components qty of Musical Box Articles : Breakdown qty per sizes | G35: N/A
A36: Musical Box UOM | B36: =VLOOKUP(A36,MDD!A:B,2,0) -> AT_MusicalBoxUOM | C36: =VLOOKUP(A36,MDD!A:C,3,0) -> LOV | D36: Basic | F36: UOM for Musical Box (Default : CAR) | G36: N/A
A37: SAP Age | B37: =VLOOKUP(A37,MDD!A:B,2,0) -> AT_SAPAge | C37: =VLOOKUP(A37,MDD!A:C,3,0) -> LOV | D37: Basic | E37: Age | F37: MAA SAP Age (Co - Dependent with Description) E.g : CH - Children AA - All Ages AD - Adults | G37: Formula in system | K37: "Apparel & Acc Default: Adults"
A38: SAP Gender | B38: =VLOOKUP(A38,MDD!A:B,2,0) -> AT_Gender | C38: =VLOOKUP(A38,MDD!A:C,3,0) -> LOV | D38: Basic | E38: Gender | F38: MAA SAP Gender (co dependent with description) E.g : M - Male F - Female U - Unisex | G38: Mapping from Principal | H38: https://mapcoid.sharepoint.com/:x:/r/sites/MAPONESOURCE/_layouts/15/Doc.aspx?sourcedoc=%7BFB450107-E518-43FC-9020-1755050C5AB5%7D&file=H1%2027%20Product%20Bible%20-%20Wholesale.xlsx&action=default&mobileredirect=true&or=EXCEL-WEB.BODY.NT&ct=1781775190500 | J38: Gender | K38: "Apparel & Acc Product Bibble : Column 'Gender' Mens: M - Male Womens: F - Female Unisex: U - Unisex"
A39: Season | B39: =VLOOKUP(A39,MDD!A:B,2,0) -> AT_Season | C39: =VLOOKUP(A39,MDD!A:C,3,0) -> LOV | D39: Basic | F39: MAA SAP Season (Co Dependent with Description) E.g : SP - Spring SM - Summer FW - Fall Winter SS - Spring Summer etc (refer to LOV) | G39: Manual Input
A40: Season Year | B40: =VLOOKUP(A40,MDD!A:B,2,0) -> AT_SeasonYear | C40: =VLOOKUP(A40,MDD!A:C,3,0) -> number | D40: Basic | F40: MAA SAP Year | G40: Manual Input
A41: Country of Origin | B41: =VLOOKUP(A41,MDD!A:B,2,0) -> AT_CountryOrigin | C41: =VLOOKUP(A41,MDD!A:C,3,0) -> LOV | D41: Basic | F41: Co Dependent with Description E.g CN - China VN - Vietnam SG - Singapore etc (refer to LOV) | G41: Formula in system | H41: https://mapcoid.sharepoint.com/:x:/r/sites/MAPONESOURCE/_layouts/15/Doc.aspx?sourcedoc=%7BFB450107-E518-43FC-9020-1755050C5AB5%7D&file=H1%2027%20Product%20Bible%20-%20Wholesale.xlsx&action=default&mobileredirect=true&or=EXCEL-WEB.BODY.NT&ct=1781775190500 | K41: "Product Bible Sheet H2 26 Catalogue Copy : Column 'Country of Manufacture Refer to LOV"
A42: Vendor | B42: =VLOOKUP(A42,MDD!A:B,2,0) -> AT_Vendor | C42: =VLOOKUP(A42,MDD!A:C,3,0) -> LOV | D42: Basic | F42: MAA Vendor code (Co Dependent with description) Format : Country Code - Comp Code - Vendor Code - Vendor Name MY - 0198 - 10303 - CROCS FOOTWEAR (MALAYSIA) SDN BHD ID - 0888 - 6863 - SKECHERS SARL etc (refer to LOV) | G42: Manual Input
A43: Main Vendor Identification | B43: =VLOOKUP(A43,MDD!A:B,2,0) -> AT_MainVendorIdentification | C43: =VLOOKUP(A43,MDD!A:C,3,0) -> text | D43: Basic | F43: to identify priority vendor | G43: Formula in system | K43: Default : 1st entry data
A44: Exchange Rate | B44: =VLOOKUP(A44,MDD!A:B,2,0) -> AT_ExchangeRate | C44: =VLOOKUP(A44,MDD!A:C,3,0) -> number | D44: Price | F44: Exchange Rate to Local Currency | G44: Formula in system
A45: Pricing Distribution Channel | B45: =VLOOKUP(A45,MDD!A:B,2,0) -> AT_PricingDistributionChannel | C45: =VLOOKUP(A45,MDD!A:C,3,0) -> LOV | D45: Price | F45: To identify price channel Co Dependent with Description) E.g : 01 - Retailer 02 - Wholesale 03 - E-comm | G45: Formula in system
A46: Retail Price Currency | B46: =VLOOKUP(A46,MDD!A:B,2,0) -> AT_RetailPriceCurrency | C46: =VLOOKUP(A46,MDD!A:C,3,0) -> LOV | D46: Price | G46: Formula in system | K46: "Default by currency per country e.g : IIndonesia (IDR), Philiphine (PHP), etc"
A47: Original Price | B47: =VLOOKUP(A47,MDD!A:B,2,0) -> AT_OriginalPrice | C47: =VLOOKUP(A47,MDD!A:C,3,0) -> regexp | D47: Price | F47: MAA Original Price | G47: Formula in system
A48: Valid From | B48: =VLOOKUP(A48,MDD!A:B,2,0) -> #N/A | C48: =VLOOKUP(A48,MDD!A:C,3,0) -> #N/A | D48: Price | F48: Identify pricing valid period | G48: Formula in system | K48: Based on price creation date (DD.MM.YYYY)
A49: Valid To | B49: =VLOOKUP(A49,MDD!A:B,2,0) -> #N/A | C49: =VLOOKUP(A49,MDD!A:C,3,0) -> #N/A | D49: Price | F49: Identify pricing valid period Conditional (default as priority 31.12.9999 - editable) | G49: Formula in system | K49: Default date (31.12.9999)
A50: Created on | B50: =VLOOKUP(A50,MDD!A:B,2,0) -> AT_Createdon | C50: =VLOOKUP(A50,MDD!A:C,3,0) -> legacyisodatetime | D50: Basic | F50: Identify when the pricing is registered (Maintainance date) | G50: Formula in system | K50: Based article creation date (DD.MM.YYYY)
A51: Created by | B51: =VLOOKUP(A51,MDD!A:B,2,0) -> AT_Createdby | C51: =VLOOKUP(A51,MDD!A:C,3,0) -> text | D51: Basic | F51: Identify who is registering the pricing (User) | G51: Formula in system | K51: Based initial user creation
A52: Current price | B52: =VLOOKUP(A52,MDD!A:B,2,0) -> AT_CurrentPrice | C52: =VLOOKUP(A52,MDD!A:C,3,0) -> regexp | D52: Price | F52: MAA Current Price | G52: Formula in system
A53: Valid From | B53: =VLOOKUP(A53,MDD!A:B,2,0) -> #N/A | C53: =VLOOKUP(A53,MDD!A:C,3,0) -> #N/A | D53: Price | F53: Identify pricing valid period | G53: Formula in system | K53: Based on price creation date (DD.MM.YYYY)
A54: Valid To | B54: =VLOOKUP(A54,MDD!A:B,2,0) -> #N/A | C54: =VLOOKUP(A54,MDD!A:C,3,0) -> #N/A | D54: Price | F54: Identify pricing valid period Conditional (default as priority 31.12.9999 - editable) | G54: Formula in system | K54: Default date (31.12.9999)
A55: Created on | B55: =VLOOKUP(A55,MDD!A:B,2,0) -> AT_Createdon | C55: =VLOOKUP(A55,MDD!A:C,3,0) -> legacyisodatetime | D55: Basic | F55: Identify when the pricing is registered (Maintainance date) | G55: Formula in system | K55: Based article creation date (DD.MM.YYYY)
A56: Created by | B56: =VLOOKUP(A56,MDD!A:B,2,0) -> AT_Createdby | C56: =VLOOKUP(A56,MDD!A:C,3,0) -> text | D56: Basic | F56: Identify who is registering the pricing (User) | G56: Formula in system | K56: Based initial user creation
A57: Discount Bucket | B57: =VLOOKUP(A57,MDD!A:B,2,0) -> AT_DiscountBucket | C57: =VLOOKUP(A57,MDD!A:C,3,0) -> number | D57: Price | F57: Comparison between original vs current price (non-rounded) | G57: Formula in system
A58: Discount Bucket (Rounded) | B58: =VLOOKUP(A58,MDD!A:B,2,0) -> AT_DiscountBucketRounded | C58: =VLOOKUP(A58,MDD!A:C,3,0) -> number | D58: Price | F58: Comparison between original vs current price (rounded) | G58: Formula in system
A59: Estimated Landed Cost | B59: =VLOOKUP(A59,MDD!A:B,2,0) -> AT_EstimatedLandedCost | C59: =VLOOKUP(A59,MDD!A:C,3,0) -> number | D59: Cost | G59: Formula in system
A60: FOB | B60: =VLOOKUP(A60,MDD!A:B,2,0) -> AT_FOB | C60: =VLOOKUP(A60,MDD!A:C,3,0) -> regexp | D60: Cost | G60: Formula in system | H60: https://mapcoid.sharepoint.com/:x:/r/sites/MAPONESOURCE/_layouts/15/Doc.aspx?sourcedoc=%7BFB450107-E518-43FC-9020-1755050C5AB5%7D&file=H1%2027%20Product%20Bible%20-%20Wholesale.xlsx&action=default&mobileredirect=true&or=EXCEL-WEB.BODY.NT&ct=1781775190500 | J60: MSRP(USD) ex | K60: "App/ Acc Product Bible : Column 'MSRP (USD) ex' Calculation : MSRP*74%"
A61: FOB Currency | B61: =VLOOKUP(A61,MDD!A:B,2,0) -> AT_FOBCurrency | C61: =VLOOKUP(A61,MDD!A:C,3,0) -> LOV | D61: Cost | G61: Formula in system | K61: "App/Acc Default: USD"
A62: Freight Cost | B62: =VLOOKUP(A62,MDD!A:B,2,0) -> AT_FreightCost | C62: =VLOOKUP(A62,MDD!A:C,3,0) -> regexp | D62: Cost | G62: Formula in system
A63: Royalty | B63: =VLOOKUP(A63,MDD!A:B,2,0) -> AT_Royalty | C63: =VLOOKUP(A63,MDD!A:C,3,0) -> regexp | D63: Cost | G63: Formula in system
A64: Royalty Deduction | B64: =VLOOKUP(A64,MDD!A:B,2,0) -> AT_RoyaltyDeduction | C64: =VLOOKUP(A64,MDD!A:C,3,0) -> regexp | D64: Cost | G64: Formula in system
A65: Commision | B65: =VLOOKUP(A65,MDD!A:B,2,0) -> #N/A | C65: =VLOOKUP(A65,MDD!A:C,3,0) -> #N/A | D65: Cost | G65: Formula in system
A66: SGS | B66: =VLOOKUP(A66,MDD!A:B,2,0) -> AT_SGS | C66: =VLOOKUP(A66,MDD!A:C,3,0) -> regexp | D66: Cost | G66: Formula in system
A67: Marketing Fee | B67: =VLOOKUP(A67,MDD!A:B,2,0) -> AT_MarketingFee | C67: =VLOOKUP(A67,MDD!A:C,3,0) -> regexp | D67: Cost | G67: Formula in system
A68: Haddad Office Charge | B68: =VLOOKUP(A68,MDD!A:B,2,0) -> AT_HaddadOfficeCharge | C68: =VLOOKUP(A68,MDD!A:C,3,0) -> regexp | D68: Cost | G68: Formula in system
A69: Haddad Office Charge - Deduction | B69: =VLOOKUP(A69,MDD!A:B,2,0) -> AT_HaddadOfficeChargeDeduction | C69: =VLOOKUP(A69,MDD!A:C,3,0) -> regexp | D69: Cost | G69: Formula in system
A70: Safeguard Duty (ID Only) | B70: =VLOOKUP(A70,MDD!A:B,2,0) -> AT_SafeguardDutyIdOnly | C70: =VLOOKUP(A70,MDD!A:C,3,0) -> number | D70: Cost | G70: Formula in system
A71: Label Cost | B71: =VLOOKUP(A71,MDD!A:B,2,0) -> AT_LabelCost | C71: =VLOOKUP(A71,MDD!A:C,3,0) -> regexp | D71: Cost | G71: Formula in system
A72: Others | B72: =VLOOKUP(A72,MDD!A:B,2,0) -> AT_Others | C72: =VLOOKUP(A72,MDD!A:C,3,0) -> number | D72: Cost | G72: Formula in system
A73: MC Structure (Merchandise Category) | B73: =VLOOKUP(A73,MDD!A:B,2,0) -> #N/A | C73: =VLOOKUP(A73,MDD!A:C,3,0) -> #N/A | D73: MC | F73: Structure : 1 Digits of SAP Product Div + 2 Digits of SAP Product Group + 2 Digits of SAP Product Category + 3 Digits of Brand Code + 1 Digits of SAP Product Flag | G73: Formula in system
A74: SAP Product Division | B74: =VLOOKUP(A74,MDD!A:B,2,0) -> #N/A | C74: =VLOOKUP(A74,MDD!A:C,3,0) -> #N/A | D74: MC | F74: Co Dependent with Description E.g : F - Footwear | A - Apparel etc | G74: Mapping from Principal | H74: https://mapcoid.sharepoint.com/:x:/r/sites/MAPONESOURCE/_layouts/15/Doc.aspx?sourcedoc=%7BFB450107-E518-43FC-9020-1755050C5AB5%7D&file=H1%2027%20Product%20Bible%20-%20Wholesale.xlsx&action=default&mobileredirect=true&or=EXCEL-WEB.BODY.NT&ct=1781775190500 | K74: "App / Acc Product Bible : 'Category'" | L74: 2XU - Stibo Mapping (upd. 21 April 2026).xlsx
A75: SAP Product Group | B75: =VLOOKUP(A75,MDD!A:B,2,0) -> #N/A | C75: =VLOOKUP(A75,MDD!A:C,3,0) -> #N/A | D75: MC | F75: Co Dependent with Description) E.g : FS - Lifestyle Shoes | 34 - Sports Shoes etc | G75: Mapping from Principal | H75: https://mapcoid.sharepoint.com/:x:/r/sites/MAPONESOURCE/_layouts/15/Doc.aspx?sourcedoc=%7BFB450107-E518-43FC-9020-1755050C5AB5%7D&file=H1%2027%20Product%20Bible%20-%20Wholesale.xlsx&action=default&mobileredirect=true&or=EXCEL-WEB.BODY.NT&ct=1781775190500 | K75: "App / Acc Product Bible : 'Hierarchy' and 'Field of play'" | L75: 2XU - Stibo Mapping (upd. 21 April 2026).xlsx
A76: SAP Product Category | B76: =VLOOKUP(A76,MDD!A:B,2,0) -> #N/A | C76: =VLOOKUP(A76,MDD!A:C,3,0) -> #N/A | D76: MC | F76: Co Dependent with Description E.g : RU - Running | CS - Casual Shoes etc | G76: Mapping from Principal | H76: https://mapcoid.sharepoint.com/:x:/r/sites/MAPONESOURCE/_layouts/15/Doc.aspx?sourcedoc=%7BFB450107-E518-43FC-9020-1755050C5AB5%7D&file=H1%2027%20Product%20Bible%20-%20Wholesale.xlsx&action=default&mobileredirect=true&or=EXCEL-WEB.BODY.NT&ct=1781775190500 | K76: "App/Acc Product Bible : 'Category'" | L76: 2XU - Stibo Mapping (upd. 21 April 2026).xlsx
A77: SAP Product Flag | B77: =VLOOKUP(A77,MDD!A:B,2,0) -> AT_SAPProductFlag | C77: =VLOOKUP(A77,MDD!A:C,3,0) -> LOV | D77: MC | F77: Co Dependent with Description E.g : A - Intercompany 5 - Direct Local 1 - Consignment etc To indicate the bussiness model (Direct, local, intercompany,consignment, non MD) E.g : A - Intercompany | 5 - Direct Local | 1 - Consignment | G77: Formula in system
A78: Principal Merchandise Hierarchy L1 | B78: =VLOOKUP(A78,MDD!A:B,2,0) -> AT_PrincipalMerchandiseHierarchyL1 | C78: =VLOOKUP(A78,MDD!A:C,3,0) -> text | D78: Hierarchy | F78: Principal Merchandise Hierarchy Level 1 | G78: Direct from Principal | H78: https://mapcoid.sharepoint.com/:x:/r/sites/MAPONESOURCE/_layouts/15/Doc.aspx?sourcedoc=%7BFB450107-E518-43FC-9020-1755050C5AB5%7D&file=H1%2027%20Product%20Bible%20-%20Wholesale.xlsx&action=default&mobileredirect=true&or=EXCEL-WEB.BODY.NT&ct=1781775190500 | J78: Hierarchy | K78: "App/Acc Product Bibble : 'Hierarchy'"
A79: Principal Merchandise Hierarchy L2 | B79: =VLOOKUP(A79,MDD!A:B,2,0) -> AT_PrincipalMerchandiseHierarchyL2 | C79: =VLOOKUP(A79,MDD!A:C,3,0) -> text | D79: Hierarchy | F79: Principal Merchandise Hierarchy Level 2 | G79: Direct from Principal | H79: https://mapcoid.sharepoint.com/:x:/r/sites/MAPONESOURCE/_layouts/15/Doc.aspx?sourcedoc=%7BFB450107-E518-43FC-9020-1755050C5AB5%7D&file=H1%2027%20Product%20Bible%20-%20Wholesale.xlsx&action=default&mobileredirect=true&or=EXCEL-WEB.BODY.NT&ct=1781775190500 | J79: Field of Play | K79: "App/Acc Product Bibble : 'Field of Play'"
A80: Principal Merchandise Hierarchy L3 | B80: =VLOOKUP(A80,MDD!A:B,2,0) -> AT_PrincipalMerchandiseHierarchyL3 | C80: =VLOOKUP(A80,MDD!A:C,3,0) -> text | D80: Hierarchy | F80: Principal Merchandise Hierarchy Level 3 | G80: Direct from Principal | H80: https://mapcoid.sharepoint.com/:x:/r/sites/MAPONESOURCE/_layouts/15/Doc.aspx?sourcedoc=%7BFB450107-E518-43FC-9020-1755050C5AB5%7D&file=H1%2027%20Product%20Bible%20-%20Wholesale.xlsx&action=default&mobileredirect=true&or=EXCEL-WEB.BODY.NT&ct=1781775190500 | J80: Category | K80: "App/Acc Product Bibble : 'Category'"
A81: Principal Merchandise Hierarchy L4 | B81: =VLOOKUP(A81,MDD!A:B,2,0) -> AT_PrincipalMerchandiseHierarchyL4 | C81: =VLOOKUP(A81,MDD!A:C,3,0) -> text | D81: Hierarchy | F81: Principal Merchandise Hierarchy Level 4 | G81: N/A
A82: Principal Merchandise Hierarchy L5 | B82: =VLOOKUP(A82,MDD!A:B,2,0) -> AT_PrincipalMerchandiseHierarchyL5 | C82: =VLOOKUP(A82,MDD!A:C,3,0) -> text | D82: Hierarchy | F82: Principal Merchandise Hierarchy Level 5 | G82: N/A
A83: Material Type | B83: =VLOOKUP(A83,MDD!A:B,2,0) -> AT_MaterialType | C83: =VLOOKUP(A83,MDD!A:C,3,0) -> LOV | D83: Commercial | F83: Direct/ Intercompany/ etc | G83: Formula in system | K83: "App/ Acc Default : Intercompany"
A84: Article Category | B84: =VLOOKUP(A84,MDD!A:B,2,0) -> AT_SAPArticleCategory | C84: =VLOOKUP(A84,MDD!A:C,3,0) -> LOV | D84: Basic | F84: SAP Article Category to indicate whether the article is single,Generic,etc | G84: Formula in system | K84: "App/Acc Default : Generic / Variant"
A85: Internal Barcode | B85: =VLOOKUP(A85,MDD!A:B,2,0) -> AT_InternalBarcode | C85: =VLOOKUP(A85,MDD!A:C,3,0) -> regexp | D85: Basic | E85: Barcode | G85: N/A
A86: Principal Barcode | B86: =VLOOKUP(A86,MDD!A:B,2,0) -> AT_PrincipalBarcode | C86: =VLOOKUP(A86,MDD!A:C,3,0) -> regexp | D86: Basic | E86: Barcode | F86: Original Principal Barcode | G86: Direct from Principal | H86: https://mapcoid.sharepoint.com/:x:/r/sites/MAPONESOURCE/_layouts/15/Doc.aspx?sourcedoc=%7B71D05E55-A5E4-4080-BE41-D03032D6FECF%7D&file=H226CN1%201MAPA001%20Order%20Confirmation.xlsx&action=default&mobileredirect=true&or=EXCEL-WEB.BODY.NT&ct=1781775220047 | J86: Barcode/EAN | K86: "App/Acc Order Confirmation : Barcode/EAN"
A87: FG Barcode | B87: =VLOOKUP(A87,MDD!A:B,2,0) -> AT_FGBarcode | C87: =VLOOKUP(A87,MDD!A:C,3,0) -> regexp | D87: Basic | E87: Barcode | F87: FG Barcode (Only for Sport Direct) | G87: Manual Input
A88: Main EAN Indicator | B88: =VLOOKUP(A88,MDD!A:B,2,0) -> AT_MainEANIndicator | C88: =VLOOKUP(A88,MDD!A:C,3,0) -> LOV | D88: Basic | E88: Barcode | G88: Formula in system
A89: EAN Category | B89: =VLOOKUP(A89,MDD!A:B,2,0) -> AT_EANCategory | C89: =VLOOKUP(A89,MDD!A:C,3,0) -> LOV | D89: Basic | E89: Barcode | G89: Formula in system
A90: Unit of Measurement (UoM) | B90: =VLOOKUP(A90,MDD!A:B,2,0) -> AT_UOM | C90: =VLOOKUP(A90,MDD!A:C,3,0) -> LOV | D90: Basic | G90: Formula in system | K90: "App/Acc Default : EA"
A91: HS Code | B91: =VLOOKUP(A91,MDD!A:B,2,0) -> AT_HSCode | C91: =VLOOKUP(A91,MDD!A:C,3,0) -> text | D91: Cost | G91: Formula in system | H91: https://mapcoid.sharepoint.com/:x:/r/sites/MAPONESOURCE/_layouts/15/Doc.aspx?sourcedoc=%7B71D05E55-A5E4-4080-BE41-D03032D6FECF%7D&file=H226CN1%201MAPA001%20Order%20Confirmation.xlsx&action=default&mobileredirect=true&or=EXCEL-WEB.BODY.NT&ct=1781775220047 | J91: HS Code | K91: "App/Acc Order Confirmation : HS CODE"
A92: Nature of Article (NOA) | B92: =VLOOKUP(A92,MDD!A:B,2,0) -> #N/A | C92: =VLOOKUP(A92,MDD!A:C,3,0) -> #N/A | D92: Commercial | G92: Manual Input
A93: Article Type | B93: =VLOOKUP(A93,MDD!A:B,2,0) -> #N/A | C93: =VLOOKUP(A93,MDD!A:C,3,0) -> #N/A | D93: Commercial | F93: Inline/License/SSE | G93: Formula in system | K93: "App/Acc Default : Inline"
A94: Thumbnail Image | B94: =VLOOKUP(A94,MDD!A:B,2,0) -> #N/A | C94: =VLOOKUP(A94,MDD!A:C,3,0) -> #N/A | D94: Image (BY) | E94: Images | G94: Direct from Principal
A95: BY Age | B95: =VLOOKUP(A95,MDD!A:B,2,0) -> AT_BYAge | C95: =VLOOKUP(A95,MDD!A:C,3,0) -> LOV | D95: Basic | K95: App & ACC: Default Adults
A96: BY Gender | B96: =VLOOKUP(A96,MDD!A:B,2,0) -> AT_BYGender | C96: =VLOOKUP(A96,MDD!A:C,3,0) -> LOV | D96: Basic | E96: Gender | G96: Formula in system | H96: https://mapcoid.sharepoint.com/:x:/r/sites/MAPONESOURCE/_layouts/15/Doc.aspx?sourcedoc=%7BFB450107-E518-43FC-9020-1755050C5AB5%7D&file=H1%2027%20Product%20Bible%20-%20Wholesale.xlsx&action=default&mobileredirect=true&or=EXCEL-WEB.BODY.NT&ct=1781775190500 | J96: Gender | K96: "Apparel & Acc Product Bibble : Column 'Gender'"
A97: BCI | B97: =VLOOKUP(A97,MDD!A:B,2,0) -> AT_BCI | C97: =VLOOKUP(A97,MDD!A:C,3,0) -> LOV | D97: Image (BY) | G97: Mapping from Principal
A98: BY Color Group | B98: =VLOOKUP(A98,MDD!A:B,2,0) -> #N/A | C98: =VLOOKUP(A98,MDD!A:C,3,0) -> #N/A | D98: Basic | E98: Color | F98: 6 Color Group | G98: Formula in system | K98: Mapping from BY Standardized Color
A99: BY Standardized Color | B99: =VLOOKUP(A99,MDD!A:B,2,0) -> #N/A | C99: =VLOOKUP(A99,MDD!A:C,3,0) -> #N/A | D99: Basic | E99: Color | F99: 53 Color Description | G99: Defined from Images
A100: Price Range | B100: =VLOOKUP(A100,MDD!A:B,2,0) -> AT_PriceRange | C100: =VLOOKUP(A100,MDD!A:C,3,0) -> LOV | D100: Basic | G100: Formula in system
...

Sheet Nike(Inline)
A1: Stibo Attribute | B1: Stibo Attribute ID | C1: Stibo Validation | D1: Cluster | E1: Grouping | F1: Attributes Description | G1: Field Mapping Type | H1: Brand File Name & Link | I1: Brand File Sheet Name | J1: Field Name in the Brand File | K1: Mapping Logic | L1: Mapping file for additional Brand specific mapping
A2: Country | B2: =VLOOKUP(A2,MDD!A:B,2,0) -> AT_Country | C2: =VLOOKUP(A2,MDD!A:C,3,0) -> LOV | D2: Basic | F2: Co Dependent with Description E.g : ID - Indonesia PH - Philiphine TH - Thailand SG - Singapore MY - Malaysia VN - Vietnam KH : Cambodia | G2: Manual Input
A3: Company | B3: =VLOOKUP(A3,MDD!A:B,2,0) -> AT_CompanyCode | C3: =VLOOKUP(A3,MDD!A:C,3,0) -> LOV | D3: Basic | F3: Co Dependent with Description 0888 - PT. Map Aktif Adiperkasa 0886 - PT. MAP FTL Adiperkasa 0882 - Magna Management Asia etc (Refer to LOV) | G3: Manual Input
A4: SBU | B4: =VLOOKUP(A4,MDD!A:B,2,0) -> AT_SBU | C4: =VLOOKUP(A4,MDD!A:C,3,0) -> LOV | D4: Basic | F4: Co Dependent with Description E.g SP - Sports FQ - Footlocker Etc (refer to LOV) | G4: Manual Input
A5: Brand | B5: =VLOOKUP(A5,MDD!A:B,2,0) -> AT_Brand | C5: =VLOOKUP(A5,MDD!A:C,3,0) -> LOV | D5: Basic | F5: Co Dependent with Description E.g ADI - Adidas NIK - Nike NEW - New Balance Etc (refer to LOV) | G5: Manual Input
A6: Brand Group | B6: =VLOOKUP(A6,MDD!A:B,2,0) -> AT_BrandGroup | C6: =VLOOKUP(A6,MDD!A:C,3,0) -> LOV | D6: Basic | F6: Multiple brand codes that managed under 1 brand group e.g. Adidas, Lego, Hasbro | G6: Manual Input
A7: Brand Type | B7: =VLOOKUP(A7,MDD!A:B,2,0) -> AT_BrandType | C7: =VLOOKUP(A7,MDD!A:C,3,0) -> LOV | D7: Commercial | F7: Whether a brand act as a retailer, selling directly to customers (MAA brands, SDI brands) or as a distributor (Non-MAA brands, Non-SDI brands) | G7: Manual Input
A8: Brand Category | B8: =VLOOKUP(A8,MDD!A:B,2,0) -> AT_BrandCategory | C8: =VLOOKUP(A8,MDD!A:C,3,0) -> LOV | D8: Commercial | F8: Group of brands that classified based on their performance/ contribution e.g. Top brands, Selected brands, Non-Top brands | G8: Manual Input
